Workbook
Name AdhesiveList: #REF!
Name amount: #REF!
Name BagNamesDropdown: [6]HELPER!$DI$2:$DI$6
Name BagNamesDropdown: HELPER!$DI$2:$DI$6
Name BagTypeList: #REF!
Name Barier: #REF!
Name Clear: #REF!
Name ColorBandsDropdown: [6]HELPER!$DL$2:$DL$5
Name ColorBandsDropdown: HELPER!$DL$2:$DL$5
Name Config_302FG: #REF!
Name Config_302FGW: #REF!
Name Config_306: #REF!
Name Config_308: #REF!
Name Config_312FG: #REF!
Name Config_312W: #REF!
Name Config_NKR: #REF!
Name Config_PL2021: "'Film Pricing- New'!$AF$10:$AF$20"
Name Config_PL2022: "'Film Pricing- New'!$AG$10:$AG$20"
Name Config_PL2023: "'Film Pricing- New'!$AH$10:$AH$20"
Name ConverterDropdown: [6]HELPER!$DM$2:$DM$4
Name ConverterDropdown: HELPER!$DM$2:$DM$4
Name Family: #REF!
Name Film_type: '[1]List of names'!$Y$15:$Y$16
Name Film_type: #REF!
Name FilmList: #REF!
Name FilmNamesDropdown: [6]HELPER!$DJ$5:$DJ$11
Name FilmNamesDropdown: HELPER!$DJ$5:$DJ$11
Name GF048.1: #REF!
Name Grouped: #REF!
Name HardenerList: #REF!
Name JOB: OFFSET('[2]GEF063 WP Sales'!B6,0,0,COUNTA('[2]GEF063 WP Sales'!$AS$11:$AS$200),COUNTA('[2]GEF063 WP Sales'!$AS$11:$AT$11))
Name JOB: OFFSET(#REF!,0,0,COUNTA(#REF!),COUNTA(#REF!))
Name Jobs: '[2]GEF063 WP Sales'!$AS$10:$AS$210+'[2]GEF063 WP Sales'!$AU$10-2
Name Jobs: #REF!+#REF!-2
Name Jobss: '[2]GEF063 WP Sales'!XFC2:XFC2+VALUE('[2]GEF063 WP Sales'!$AU$10)
Name Jobss: #REF!+VALUE(#REF!)
Name Laminate: '[1]List of names'!$P$15:$P$22
Name Laminate: #REF!
Name Laminate_Thickness: #REF!
Name Laminate_type: '[1]List of names'!$P$14:$X$14
Name Laminate_type: #REF!
Name Laminate106: #REF!
Name Laminate604: [1]!Table4[Laminate618]
Name Laminate604: #REF!
Name Laminate607: #REF!
Name Laminate607\: [1]!Table6[Laminate607]
Name Laminate607\: #REF!
Name Laminate608W: [1]!Table3[Laminate608W]
Name Laminate608W: #REF!
Name LaminateList: #REF!
Name MATERIAL: '[3]Raw materials prices'!$L$51:$L$61
Name MATERIAL: #REF!
Name Materials: '[4]list for drop down menu'!$A$1:$A$20
Name Materials: #REF!
Name Metalize: #REF!
Name NKR: #REF!
Name Paper: #REF!
Name pirce: #REF!
Name PO: #REF!
Name price: #REF!

Sheet Sheet1
A3: Film | B3: Grade | C3: Sum of Price Calculated(€) Thickness & QTY related
A4: TIPA 302FG | B4: S723 | C4: 0.2424
B5: S724 | C5: 0.02352
A6: TIPA 302FG W | B6: S723 | C6: 0.2424
B7: S724 | C7: 0.09408
A8: TIPA 306M | B8: S723 | C8: 0.2424
B9: S724 | C9: 0.0588
A10: TIPA 306W | B10: S723 | C10: 0.2424
B11: S724 | C11: 0.1176
A12: TIPA 312 MFG | B12: S723 | C12: 0.2424
B13: S724 | C13: 0.06762
A14: TIPA 312MFGW | B14: S723 | C14: 0.2424
B15: S724 | C15: 0.06762
A16: Grand Total | C16: 1.88364
A20: Film | B20: Price (€/kg) | C20: Price ($/kg)
A21: PL202.1 | B21: 8.995784 | C21: 10.435109
A22: PL202.2 | B22: 6.73178 | C22: 7.8088648
A23: PL202.3 | B23: 5.74578 | C23: 6.6651048
A24: TIPA 302FG | B24: 3.599712 | C24: 4.1756659
A25: TIPA 302FG W | B25: 3.916872 | C25: 4.5435715
A26: TIPA 306M | B26: 3.520798 | C26: 4.0841257
A27: TIPA 306W | B27: 3.805774 | C27: 4.4146978
A28: TIPA 312 MFG | B28: 2.899978 | C28: 3.3639745
A29: TIPA 312MFGW | B29: 3.178978 | C29: 3.6876145
A32: FILM | B32: Material | C32: % from Total
A33: TIPA 302FG | B33: S723 | C33: =C4/$B$24 -> 0.06733872
B34: S724 | C34: =C5/$B$24 -> 0.006533856
A35: TIPA 302FG W | B35: S723 | C35: =C6/$B$25 -> 0.061886117
B36: S724 | C36: =C7/$B$25 -> 0.024019166
A37: TIPA 306M | B37: S723 | C37: =C8/$B$26 -> 0.068848028
B38: S724 | C38: =C9/$B$26 -> 0.016700759
A39: TIPA 306W | B39: S723 | C39: =C10/$B$27 -> 0.063692694
B40: S724 | C40: =C11/$B$27 -> 0.030900416
A41: TIPA 312 MFG | B41: S723 | C41: =C12/$B$28 -> 0.083586841
B42: S724 | C42: =C13/$B$28 -> 0.023317418
A43: TIPA 312MFGW | B43: S723 | C43: =C14/$B$29 -> 0.076250921
B44: S724 | C44: =C15/$B$29 -> 0.021270987

Sheet Laminate for reels  - Sales
B1: Laminate608 W | C1: Tipa302WFG | E1: Quote in | G1: =C38 -> Ml | H1: =C39 -> 50000
A2: Laminate | B2: Layer | C2: Laminate structure | D2: Width of reel asked | E2: Width Used | F2: length of impression | G2: FG/NF | H2: Laminate length (m) width asked | I2: PR/ NonPR | J2: No of paints | K2: Lemination Width (mm) | L2: Thickness (µ) | M2: Density | N2: Weight (kg) | O2: Raw material Cost | P2: TRANSPORTATION | Q2: Cost (€) | R2: Cost ($) | T2: Cost Per KG | W2: מחיר הדפסה למ"א | X2: מ"א מודפס | AB2: SDR Price
A3: =IF(C36="Laminate607",607,IF(C36="Laminate608",608,IF(C36="Laminate418",418,IF(C36="Laminate608W","608W",IF(C36="Laminate106",106,IF(C36="Laminate428",428,IF(C36="Laminate819",819,IF(C36="Laminate823",823,IF(C36="Laminate618",618,"Check"))))))))) -> 819 | B3: =IF(C3<>"","A","") -> A | C3: =IF(C36="Laminate608W","Tipa302WFG",IF(C36="Laminate418","Tipa312Met",IF(C36="Laminate428","Tipa312Met",IF(C36="Laminate823","Tipa312Met","Tipa302FG")))) -> Tipa302FG | D3: =IF(G1="Impression",B14,B18) -> 260 | E3: =IF(OR(A3<>"608W",A3<>608),IF((K4-29)/D3>6,D3*6,IF((K4-29)/D3>5,D3*5,IF((K4-29)/D3>4,D3*4,IF((K4-29)/D3>3,D3*3,IF((K4-29)/D3>2,D3*2,D3))))),MAX(750,IF((K4-29)/D3>6,D3*6,IF((K4-29)/D3>5,D3*5,IF((K4-29)/D3>4,D3*4,IF((K4-29)/D3>3,D3*3,IF((K4-29)/D3>2,D3*2,D3))))))) -> 1040 | F3: =IF(G1="Impression",B15,"") | G3: =C37 -> FG | H3: =IF(G1="Ml",H1,IF(G1="KG",(1/N8*ROUNDDOWN((K8-30)/D3,0))*H1,H1*F3/1000)) -> 50000 | I3: =C43 -> PR | J3: =C44 -> 5 to 8 | K3: =IF(OR(A3="608W",A3=608),E3+40*2,E3+50) -> 1090 | L3: =IF($AA$4=1,L8-SUM(L4:L5,3),L8-SUM(L4:L5,6)) -> 25 | M3: =VLOOKUP(C3,'[1]List of names'!L:N,3,0) -> 1.25 | N3: =IF(C3="PAPER",42/1000*$K3/1000,M3*1000*(L3/1000000)*($K3/1000)) -> 0.0340625 | O3: =IF(E3<950,'[1]Film -Summary'!Q35,'[1]Film -Summary'!Q35*1.25) -> 10.950906 | P3: =VLOOKUP(C3,'[1]List of names'!$L$2:$M$10,2,FALSE)+Q32 -> 0.2 | Q3: =N3*(O3+P3) -> 0.37982774 | R3: =Q3*USD -> 0.41781051 | T3: =(O3+P3)*N3/$N$8 -> 3.128902 | W3: =Y3/X3 -> 0.1444032 | X3: =IF(OR(A3="608W",A3=608),1/N8,1/N4) -> 27.700217 | Y3: =IF(OR(A3="608W",A3=608),Y11*Y10,IF(J3="1 to 4",Y7,Y8)) -> 4 | Z3: הדפסה לק"ג | AA3: כמות שכבות | AB3: מחיר לק"ג
B4: =IF(C4<>"","B","") -> B | C4: =VLOOKUP(A3,'[1]List of names'!$F$2:$G$11,2,0) -> NKR | K4: =IF(D3<300,D3*4+50,IF(D3<400,D3*3+50,IF(D3<600,D3*2+50,D3+50))) -> 1090 | L4: {=IF(C4="NKR",23,IF(C4="NKME",20,IF(C4="Tipa312Met",25,NA)))} -> 23 | M4: =VLOOKUP(C4,'[1]List of names'!L:N,3,0) -> 1.44 | N4: =IF(C4="PAPER",42/1000*$K4/1000,M4*1000*(L4/1000000)*($K4/1000)) -> 0.0361008 | O4: =VLOOKUP(C4,'[1]Raw material summary'!$I$10:$K$16,IF($K$3<900,2,3),0) -> 7.95 | P4: =VLOOKUP(C4,'[1]List of names'!$L$2:$M$7,2,FALSE)+Q32 -> 0.35 | Q4: =N4*(O4+P4) -> 0.29963664 | R4: =Q4*USD -> 0.3296003 | T4: =(O4+P4)*N4/$N$8 -> 2.4683128 | W4: =Y4/X4 -> 0.29134392 | X4: =1/N8 -> 8.2376869 | Y4: =IF(OR(A3=608,A3="608W"),AA4*Y12*Y10,Y12*AA4*Y10) -> 2.4 | Z4: למינציה לק"ג | AA4: =IF(OR(A3="608W",A3=608,A3=618,A3=418),1,2) -> 2 | AB4: 2.5
B5: =IF(C5<>"","C","") -> C | C5: =IF(VLOOKUP(A3,'[1]List of names'!F2:H11,3,FALSE)=0,"",VLOOKUP(A3,'[1]List of names'!F2:H11,3,FALSE)) -> Paper | K5: =IF(D3<300,D3*4+50,IF(D3<400,D3*3+50,IF(D3<600,D3*2+50,D3+50))) -> 1090 | L5: =IF(C5="","",IF(C5="NKR",23,IF(C5="NKME",20,IF(C5="Paper",67,IF(C5="PBAT",INDEX('[1]List of names'!$F$34:$F$40,MATCH($L$8,'[1]List of names'!$D$34:$D$40,0)),IF(C5="",0,"NA")))))) -> 67 | M5: =IF(C5="",0,VLOOKUP(C5,'[1]List of names'!L2:N7,3,0)) -> 1 | N5: =IF(C5="","",IF(C5="PAPER",42/1000*$K5/1000,M5*1000*(L5/1000000)*($K5/1000))) -> 0.04578 | O5: 1.31 | P5: =IF(C5="",0,VLOOKUP(C5,'[1]List of names'!$L$2:$M$7,2,FALSE)) -> 0.3 | Q5: =IF(C5="","",N5*(O5+P5)) -> 0.0737058 | R5: =IF(C5="","",Q5*USD) -> 0.08107638 | T5: =IF(C5="","",(O5+P5)*N5/$N$8) -> 0.6071653 | W5: =Y5/X5 -> 0.091044975 | X5: =1/N8 -> 8.2376869 | Y5: 0.75 | Z5: חיתוך לק"ג
C6: ADHISIVE | N6: =IF(A3=608,0,(K3/1000*0.0025*IF(B5="C",2,1))) -> 0.00545 | O6: 4.65 | P6: =0.2+Q32 -> 0.2 | Q6: =N6*(O6+P6) -> 0.0264325 | R6: =Q6*USD -> 0.02907575 | T6: =(O6+P6)*N6/$N$8 -> 0.21774266
C7: HARDENER | Q7: =N7*(O7+P7) -> 0 | R7: =Q7*USD -> 0 | T7: =(O7+P7)*N7/$N$8 -> 0 | Y7: 3.5 | Z7: מחיר הדפסה 1-4
A8: =A3 -> 819 | C8: =COUNTA(C3:C5) -> 3 | E8: =COUNTIF(C3:C5,"") -> 0 | G8: Lemingth length width used | H8: =H3/(ROUNDDOWN(K3/D3,0)) -> 12500 | K8: =SUMPRODUCT(K3:K5,L3:L5)/IF(AA4=1,($L$8-3),($L$8-6)) -> 1090 | L8: =C45 -> 121 | N8: =SUM(N3:N7) -> 0.1213933 | P8: Total materials cost | Q8: =SUM(Q3:Q7) -> 0.77960268 | R8: =Q8*USD -> 0.85756295 | T8: =SUM(T3:T7) -> 6.4221228 | Y8: 4 | Z8: מחיר הדפסה 5-8
E9: =IF(OR((680-D3*1)<120,AND((680-D3*2)<120,(680-D3*2)>0),AND((680-D3*3)<120,(680-D3*3)>0)),680,0) -> 0 | L9: =K3*L3+K4*L4 -> 52320 | P9: Lamination | Q9: {=IF(OR(H8="",K8=""),"",IF(K8>1220,"Error! please choose lamination width not higher than 1220",_xlfn.LET(_xlpm.struct,C3:C7,_xlpm.realLayers,SUMPRODUCT(--(_xlpm.struct<>""),--ISERROR(SEARCH("EPOTAL",_xlpm.struct&"")),--ISERROR(SEARCH("BASONAT",_xlpm.struct&"")),--ISERROR(SEARCH("ADH",_xlpm.struct&"")),--ISERROR(SEARCH("HARDENER",_xlpm.struct&""))),_xlpm.lamSteps,MAX(0,_xlpm.realLayers-1),_xlpm.len,H8,_xlpm.colNum,IF(_xlpm.len<3000,1,IF(_xlpm.len<10000,2,IF(_xlpm.len<25000,3,IF(_xlpm.len<50000,4,IF(_xlpm.len<100000,5,IF(_xlpm.len<250000,6,7)))))),_xlpm.widthRow,IF(K8<=990,0,5),_xlpm.baseRate,INDEX('Lmntn & Prntng- Marma & Bastin '!$D$1:$J$22,3+_xlpm.widthRow,_xlpm.colNum),IF(_xlpm.realLayers=0,"",_xlpm.baseRate*_xlpm.lamSteps))))} -> 0.18306 | R9: =Q9*USD -> 0.201366 | T9: =+Y4 -> 2.4
B10: 4 | C10: EURO | E10: =IF(680-D3*1<120,680,0) -> 0 | F10: =IF(C5="NKR",19,IF(C5="NKME",20,IF(C5="",0,"NA"))) -> NA | K10: =IF(OR(A3=607,A3=608),'[1]SDR price list'!Y5,'[1]SDR price list'!Y21) -> 782 | P10: Slitting | Q10: {=IF(OR(H8="",K8=""),"",IF(K8>1220,"Error! please choose lamination width not higher than 1220",_xlfn.LET(_xlpm.len,H8,_xlpm.colNum,IF(_xlpm.len<3000,1,IF(_xlpm.len<10000,2,IF(_xlpm.len<25000,3,IF(_xlpm.len<50000,4,IF(_xlpm.len<100000,5,IF(_xlpm.len<250000,6,7)))))),_xlpm.widthRow,IF(K8<=990,0,5),INDEX('Lmntn & Prntng- Marma & Bastin '!$D$1:$J$22,7+_xlpm.widthRow,_xlpm.colNum))))} -> 0.025916667 | R10: =Q10*USD -> 0.028508333 | T10: =Y5 -> 0.75 | Y10: =IF(L19<300,2,IF(L19<750,1.75,IF(L19<1500,1.5,1))) -> 1 | Z10: מקדם מתחת ל300 ק"ג
B11: 3.6 | C11: $ | P11: Printing | Q11: 0.169 | R11: =Q11*USD -> 0.1859 | T11: =IF(I3="PR",Y3*N4/N8,0) -> 1.1895484 | Y11: 2.5 | Z11: מחיר הדפסה DP | AA11: DP Price
D12: =IF(C36=OR("Laminate418","Laminate428","Laminate823"),"Tipa312Met") -> #VALUE! | N12: =100*N8 -> 12.13933 | P12: Total | Q12: =SUM(Q8:Q11) -> 1.1575793 | R12: =SUM(R8:R11) -> 1.2733373 | T12: =SUM(T8:T11) -> 10.761671 | Y12: 1.2 | Z12: למינציה DP
A13: Impression details | H13: Gross profit | I13: COST | K13: Cost per ml | L13: =$Q13/ROUNDDOWN((K8-30)/D3,0) -> 0.30660086 | M13: =L13*$B$10/$B$11 -> 0.34066762 | P13: Total + 10% | Q13: =Q8*(1+Q17)+SUM(Q9:Q11) -> 1.2264034 | R13: =R12*(1.1) -> 1.400671 | T13: =T8*(1+Q17)+SUM(T9:T11) -> 11.328623
A14: Width | B14: =C40 -> 260 | C14: This is the height of the bag | H14: 0.15 | K14: Cost per kg | L14: =$L13*$L22*K8/E3 -> 10.588436 | M14: =L14*$B$10/$B$11 -> 11.764929 | T14: =T13*(K8/E3) -> 11.873268
A15: Length | B15: 110 | C15: This is the width of the bag | I15: SELL | K15: Price per ml | L15: =$L13/(1-$H14) -> 0.3607069 | M15: =L15*$B$10/$B$11 -> 0.40078544 | X15: Total Weight | Y15: Total Cost
K16: Price per kg | L16: =L14/(1-H14) -> 12.456983 | M16: =L16*$B$10/$B$11 -> 13.841092 | T16: =T8/T12 -> 0.59675888 | X16: =$H$8*N3 -> 425.78125 | Y16: =X16*(O3+P3) -> 4747.8467 | AB16: "680,900,1100"
A17: Reel details | P17: Waste assumption Printed | Q17: =IF(A3=607,(D24*L4/L8+D23+D27*H8)/H8,(D24*L4/L8+D23+D22*0.8+D27*H8)/H8) -> 0.088280992 | X17: =$H$8*N4 -> 451.26 | Y17: =X17*(O4+P4) -> 3745.458
A18: Width | B18: =C40 -> 260 | C18: This is the height of the bag*2 | K18: Printed KG | L18: =L19*L4/L8 -> 288.43449 | P18: Waste assumption Non Printed | Q18: =IF(C5="",(D23+D27*H8)/H8,(D23+D22*0.8+D27*H8)/H8) -> 0.086 | X18: =$H$8*N5 -> 572.25 | Y18: =X18*(O5+P5) -> 921.3225
A19: Length | B19: =C42 -> 0 | C19: to check if there is any length limitation - Must be filled!!! | K19: Total KG | L19: =N8/ROUNDDOWN((K8-29)/D3,0)*H3 -> 1517.4163 | M19: =+L19*N3/N8 -> 425.78125 | X19: =$H$8*N6 -> 68.125 | Y19: =X19*(O6+P6) -> 330.40625
K20: Net KG | L20: =N8/ROUNDDOWN(K8/D3,0)*(E3/K8)*H1 -> 1447.81 | X20: =$H$8*N7 -> 0 | Y20: =X20*O7 -> 0
A21: Waste assumptions | C21: Number of works | D21: Waste per work | K21: Ml & Lem used width of reel in kg | L21: =1/N8 -> 8.2376869 | X21: =SUM(X16:X20) -> 1517.4163 | Y21: =SUM(Y16:Y20) -> 9745.0335
A22: 1st laminate | B22: 1000 | C22: 4 | D22: =B22/C22 -> 250 | K22: Ml & Lem Asked width of reel in kg | L22: =1/N8*ROUNDDOWN(K8/D3,0) -> 32.950748 | P22: Number of impression | Q22: =ROUNDDOWN(K3/D3,0)*1000/B15 -> 36.363636 | X22: Waste of width | Y22: =+(K3/E3*T13-T13)*L19 -> 826.45365
A23: 2nd laminate | B23: 1000 | C23: 4 | D23: =B23/C23 -> 250 | H23: Printed Waste Assumption | P23: Cost per impressiom | Q23: =Q13/Q22 -> 0.033726095 | X23: SDR | Y23: =X21*SUM(T9:T11) -> 6584.9012
A24: Prining | B24: 1200 | C24: 8 | D24: =B24/C24 -> 150 | I24: Eur | K24: USD | P24: Price Per impression | Q24: =Q23*1.25 -> 0.042157618 | R24: =Q24*1.16 -> 0.048902837 | X24: Waste | Y24: =IF(C43="PR",Y21*Q17,Y21*Q18) -> 860.30122
A25: Reel change | B25: 50 | C25: evrey 3K Meter | I25: Cost | J25: Sale price | K25: Cost | L25: Sale price | X25: Total Cost | Y25: =SUM(Y21:Y24) -> 18016.69
A26: Converting | B26: 500 | C26: Set up | H26: ML | I26: =L13 -> 0.30660086 | J26: =L15 -> 0.3607069 | K26: =I26*$O$29 -> 0.35872301 | L26: =J26*$O$29 -> 0.42202707 | P26: Meter MOQ | Q26: =IF(C36="Laminate608",750/N8*(E3/D3),500/N8*(E3/D3)) -> 16475.374 | X26: Total Price | Y26: =C50 -> 18035.345
A27: Converting process | B27: 0.1 | C27: Based on the run length | D27: 0.05 | H27: KG | I27: =L14 -> 10.588436 | J27: =L16 -> 12.456983 | K27: =I27*$O$29 -> 12.38847 | L27: =J27*$O$29 -> 14.57467 | X27: Profit | Y27: =Y26-Y25 -> 18.655211
O28: Euro to dollar rate | Y28: =Y27/Y26 -> 0.0010343695
H29: Non Printed waste Assumption | O29: 1.17
I31: Eur | K31: USD
B32: Laminat Reel 607, 106 | C32: MOQ = 500KG | G32: =H14 -> 0.15 | I32: Cost | J32: Sale price | K32: Cost | L32: Sale price | P32: Shipment addition
B33: Laminat Reel 608 | C33: MOQ = 750KG | H33: ML | I33: =(Q8*(1+Q18)+SUM(Q9:Q11))/ROUNDDOWN((K3-30)/D3,0) -> 0.30615629 | J33: =I33/(1-$G$32) -> 0.36018388 | K33: =I33*$O$29 -> 0.35820286 | L33: =J33*$O$29 -> 0.42141513
B34: Laminat Reel 608W | C34: MOQ = 2000KG | H34: KG | I34: =$I33*$L22*K8/E3 -> 10.573083 | J34: =I34/(1-$G$32) -> 12.438921 | K34: =I34*$O$29 -> 12.370507 | L34: =J34*$O$29 -> 14.553537
B36: Laminate type | C36: Laminate819 | I36: =I33*800 -> 244.92504
B37: Food grade | C37: FG
B38: Quote by | C38: Ml | D38: Meter MOQ | E38: =IF(C36="Laminate608w",2000/N8*(E3/D3),IF(C36="Laminate608",750/N8*(E3/D3),500/N8*(E3/D3))) -> 16475.374
B39: Amount | C39: 50000 | D39: KG MOQ | E39: =IF(C36="Laminate608W",2000,IF(C36="Laminate608",750,500)) -> 500 | I39: QTY | J39: Cost | K39: Price
B40: Width of reel | C40: 260 | D40: Total KG | E40: =+L19 -> 1517.4163 | H40: Z10771.00023-000 | I40: 5000 | J40: 11.485134 | K40: 14.356417 | L40: =K40*I40 -> 71782.087
B41: Length limitation <50Kg (Y/N) | C41: Y | D41: (*) Min is 500 Meter | H41: Z10771.00023-000 | I41: =I40*2 -> 10000 | J41: =$I$34 -> 10.573083 | K41: =$J$34 -> 12.438921 | L41: =K41*I41 -> 124389.21 | M41: =K41/K40-1 -> -0.13356374
B42: Length Limit | D42: (*) Up to 1,150 width | H42: Z10771.00023-000 | I42: =I40*3 -> 15000 | J42: =$I$34 -> 10.573083 | K42: =$J$34 -> 12.438921 | L42: =K42*I42 -> 186583.81 | M42: =K42/K41-1 -> 0
B43: Printed | C43: PR
B44: Number of Colurs | C44: 5 to 8 | I44: Imp | J44: Meters | K44: Kg | L44: Cost | M44: Price | N44: Deal amount
B45: Thickness (µ) | C45: 121 | I45: 500000 | J45: =I45/(1000/$B$15) -> 55000 | K45: =$N$8/ROUNDDOWN(($K$3-29)/$D$3,0)*$H$3 -> 1517.4163 | M45: 0.0437 | N45: =M45*I45 -> 21850
I46: 1000000 | J46: =I46/(1000/$B$15) -> 110000 | K46: =$N$8/ROUNDDOWN(($K$3-29)/$D$3,0)*$H$3 -> 1517.4163 | M46: 0.0396 | N46: =M46*I46 -> 39600
B47: Check amount | C47: =IF(AND(C38="KG",J34*H1>150000),"X",IF(AND(C38="Ml",J33*H1>150000),"X",1)) -> 1 | I47: 2000000 | J47: =I47/(1000/$B$15) -> 220000 | K47: =$N$8/ROUNDDOWN(($K$3-29)/$D$3,0)*$H$3 -> 1517.4163 | M47: 0.0375 | N47: =M47*I47 -> 75000
B48: Price per unit EXW Italy | C48: =IF(C49*C39>150000,"Higher than 40K",C49) -> 0.3607069 | H48: MOQ | I48: 3000000 | J48: =I48/(1000/$B$15) -> 330000 | K48: 532.025 | L48: =$Q$23 -> 0.033726095 | M48: 0.037 | N48: =M48*I48 -> 111000
B49: Price per unit | C49: =IF(AND(C43="PR",C38="Ml"),J26,IF(AND(C43="PR",C38="KG"),J27,IF(AND(C43="Non PR",C38="Ml"),J33,J34))) -> 0.3607069 | I49: 4000000 | J49: =I49/(1000/$B$15) -> 440000 | K49: =$N$8/ROUNDDOWN(($K$3-29)/$D$3,0)*$H$3 -> 1517.4163 | L49: =$Q$23 -> 0.033726095 | M49: 0.0365 | N49: =M49*I49 -> 146000 | O49: =N49/$L$20 -> 100.84196
B50: Total order price | C50: =C48*C47*C39 -> 18035.345
N51: =M51*I51 -> 0
B52: Lam Cost | C52: =IF(AND(C43="PR",C38="Ml"),I26,IF(AND(C43="PR",C38="KG"),I27,IF(AND(C43="Non PR",C38="Ml"),I33,I34)))*C47 -> 0.30660086 | N52: =M52*I52 -> 0
K53: Per day | L53: per month | N53: per hour | O53: Set up time
B54: Price per unit $ | C54: =+C49*USD -> 0.39677758 | I54: Laminate production | K54: =120*60*12 -> 86400 | L54: =K54*25 -> 2160000 | M54: Meters | N54: =350/(120*60) -> 0.048611111 | O54: 3 hours | P54: Flexo
B55: Total order price | C55: =+C54*C39 -> 19838.879 | I55: Pouch production | K55: =200*60*12 -> 144000 | L55: =K55*25 -> 3600000 | M55: Minute | O55: 2 hours
I56: Printing per minute | K56: =300*60*12 -> 216000 | L56: =K56*25 -> 5400000 | M56: Meters | N56: =700/(120*60) -> 0.097222222 | O56: 1.5 hours
C57: EXW Italy or Poland
C59: 1000, 3000, 5000 | I59: סוג תהליך | J59: ארה"ב (USD) | K59: אירופה (EUR) | L59: מרכיבי עלות מרכזיים
C60: 1500ת 3000ת 5000 | I60: הדפסה דיגיטלית (Indigo 25K) | J60: $450 - $600 | K60: €400 - €550 | L60: פחת גבוה ($1.5M+ מכונה), חוזי שירות יקרים, מפעיל מומחה.
B61: 608 | C61: 14.7 | I61: הדפסת פלקסו (Wide Web) | J61: $650 - $950 | K61: €600 - €850 | L61: השקעה הונית אדירה, 2 מפעילים, צריכת אנרגיה גבוהה לייבוש.
I62: למינציה / ורניש | J62: $280 - $420 | K62: €250 - €380 | L62: עלויות דבק/לקה, אנרגיה (חימום), פחת מכונה בינוני.
I63: קונברטינג (Totani) | J63: $200 - $320 | K63: €180 - €290 | L63: עבודה אינטנסיבית (בדיקות איכות), פחת מכונה נמוך יותר.

Sheet Step by Step
B2: 📋 FILM PRICING LIST - STEP BY STEP GUIDE
B3: How to use the Film Pricing calculator
B5: 🔄 PRICING WORKFLOW
B7: STEP 1 | C7: → | D7: STEP 2 | E7: → | F7: STEP 3 | G7: → | H7: STEP 4 | I7: → | J7: STEP 5
B8: 📝 INPUT | D8: ⚙️ SPECS | F8: 💰 COSTS | H8: 📦 SHIP | J8: 💵 PRICE
B11: 📝 DETAILED STEPS
B13: Step | C13: Action | D13: Column | E13: Example | F13: Notes
B14: 1️⃣ | C14: Select Film Type | D14: A | E14: TIPA 302FG | F14: Dropdown list
B15: 2️⃣ | C15: Enter Width | D15: B | E15: 406 mm | F15: Width in mm
B16: 3️⃣ | C16: Enter Thickness | D16: C | E16: 20 µ | F16: Dropdown list
B17: 4️⃣ | C17: Enter Weight | D17: E | E17: 500 Kg | F17: Order qty (Kg)
B18: 5️⃣ | C18: Weight Override | D18: F | E18: 500 Kg | F18: Optional
B19: 6️⃣ | C19: Shipping Dest. | D19: S | E19: EU/USA | F19: Dropdown list
B20: 7️⃣ | C20: Review Price | D20: W | E20: Auto | F20: Final price/Kg
B21: 8️⃣ | C21: Compare Margins | D21: X+ | E21: 25%, 30% | F21: Multiple options
B24: ⚡ AUTO-CALCULATIONS
B26: Calculation | C26: Formula Logic
B27: Length (Mr) | C27: Weight ÷ (Width × Thickness × Density)
B28: Production Cost | C28: Hourly Rate × Production Time
B29: Total Cost | C29: RM + Production + Depreciation + Waste + Ship
B30: Sell Price | C30: Total Cost × (1 + Margin %)
B33: 💡 QUICK TIPS
B35: ✓ Use dropdowns to avoid typos
B36: ✓ Higher weight = lower cost/Kg (economies of scale)
B37: ✓ Compare margin columns for pricing options
B38: ✓ Density auto-fills based on Film Type

Sheet Converting- Marma & Bastin  (2)
M1: Important notes
A2: Supplier | B2: Bag Type | C2: Converting costs | D2: 25K pouches | E2: 25-50K | F2: 50-100K | G2: 100-250K | H2: 250-500K | I2: 500-1,000K | J2: 1,000K+ | M2: Converting costs include the packing costs - pallets , carton boxes , and does not include the zipper.
A3: Marma | B3: SUP with zipper | C3: 100 MM width | D3: 42.880992 | E3: 38.198066 | F3: 34.555789 | G3: 32.474488 | H3: 31.641968 | I3: 31.017578 | J3: 30.705383 | M3: *Price per 1000 pouch - EUR *
A4: Marma | B4: SUP with zipper | C4: 150 MM width | D4: 48.113821 | E4: 43.430894 | F4: 39.788618 | G4: 37.707317 | H4: 36.874797 | I4: 36.250407 | J4: 35.938211 | M4: 600 & 700 mm width- too wide, can't be done
A5: Marma | B5: SUP with zipper | C5: 200 MM width | D5: 54.713415 | E5: 50.030488 | F5: 46.388211 | G5: 44.306911 | H5: 43.47439 | I5: 42.85 | J5: 42.537805 | M5: 1.3 | N5: Bastin is highger than Marma by 30%- Shay's directive
A6: Marma | B6: SUP with zipper | C6: 300 MM width | D6: 65.816356 | E6: 61.133429 | F6: 57.491153 | G6: 55.409852 | H6: 54.577331 | I6: 53.952941 | J6: 53.640746
A7: Marma | B7: SUP with zipper | C7: 400 MM width | D7: 85.771107 | E7: 81.08818 | F7: 77.445904 | G7: 75.364603 | H7: 74.532083 | I7: 73.907692 | J7: 73.595497
A8: Marma | B8: SUP with zipper | C8: 500 MM width | D8: 116.34959 | E8: 111.66667 | F8: 108.02439 | G8: 105.94309 | H8: 105.11057 | I8: 104.48618 | J8: 104.17398
A9: Marma | B9: Zipper pouch | C9: 100 MM width | D9: 40.311989 | E9: 35.629062 | F9: 31.986785 | G9: 29.905485 | H9: 29.072964 | I9: 28.448574 | J9: 28.136379
A10: Marma | B10: Zipper pouch | C10: 150 MM width | D10: 45.133777 | E10: 40.45085 | F10: 36.808574 | G10: 34.727273 | H10: 33.894752 | I10: 33.270362 | J10: 32.958167
A11: Marma | B11: Zipper pouch | C11: 200 MM width | D11: 51.165743 | E11: 46.482816 | F11: 42.84054 | G11: 40.759239 | H11: 39.926718 | I11: 39.302328 | J11: 38.990133
A12: Marma | B12: Zipper pouch | C12: 300 MM width | D12: 61.433938 | E12: 56.751011 | F12: 53.108734 | G12: 51.027434 | H12: 50.194913 | I12: 49.570523 | J12: 49.258328
A13: Marma | B13: Zipper pouch | C13: 400 MM width | D13: 80.040252 | E13: 75.357326 | F13: 71.715049 | G13: 69.633748 | H13: 68.801228 | I13: 68.176838 | J13: 67.864643
A14: Marma | B14: Zipper pouch | C14: 500 MM width | D14: 108.07169 | E14: 103.38877 | F14: 99.746489 | G14: 97.665188 | H14: 96.832668 | I14: 96.208278 | J14: 95.896083
A15: Marma | B15: Open pouch | C15: 100 MM width | D15: 37.484035 | E15: 32.801109 | F15: 29.158832 | G15: 27.077531 | H15: 26.245011 | I15: 25.620621 | J15: 25.308426
A16: Marma | B16: Open pouch | C16: 150 MM width | D16: 41.767985 | E16: 37.085058 | F16: 33.442782 | G16: 31.361481 | H16: 30.528961 | I16: 29.904571 | J16: 29.592375
A17: Marma | B17: Open pouch | C17: 200 MM width | D17: 47.201844 | E17: 42.518917 | F17: 38.87664 | G17: 36.79534 | H17: 35.962819 | I17: 35.338429 | J17: 35.026234
... A20: Marma | B20: Open pouch | C20: 500 MM width | D20: 97.591356 | E20: 92.908429 | F20: 89.266153 | G20: 87.184852 | H20: 86.352332 | I20: 85.727942 | J20: 85.415746
A21: Bastin | B21: SUP with zipper | C21: 100 MM width | D21: =D3*$M$5 -> 55.74529 | E21: =E3*$M$5 -> 49.657485 | F21: =F3*$M$5 -> 44.922526 | G21: =G3*$M$5 -> 42.216835 | H21: =H3*$M$5 -> 41.134558 | I21: =I3*$M$5 -> 40.322851 | J21: =J3*$M$5 -> 39.916997
A22: Bastin | B22: SUP with zipper | C22: 150 MM width | D22: =D4*$M$5 -> 62.547967 | E22: =E4*$M$5 -> 56.460163 | F22: =F4*$M$5 -> 51.725203 | G22: =G4*$M$5 -> 49.019512 | H22: =H4*$M$5 -> 47.937236 | I22: =I4*$M$5 -> 47.125528 | J22: =J4*$M$5 -> 46.719675
A23: Bastin | B23: SUP with zipper | C23: 200 MM width | D23: =D5*$M$5 -> 71.127439 | E23: =E5*$M$5 -> 65.039634 | F23: =F5*$M$5 -> 60.304675 | G23: =G5*$M$5 -> 57.598984 | H23: =H5*$M$5 -> 56.516707 | I23: =I5*$M$5 -> 55.705 | J23: =J5*$M$5 -> 55.299146
A24: Bastin | B24: SUP with zipper | C24: 300 MM width | D24: =D6*$M$5 -> 85.561263 | E24: =E6*$M$5 -> 79.473458 | F24: =F6*$M$5 -> 74.738498 | G24: =G6*$M$5 -> 72.032807 | H24: =H6*$M$5 -> 70.950531 | I24: =I6*$M$5 -> 70.138824 | J24: =J6*$M$5 -> 69.73297
A25: Bastin | B25: SUP with zipper | C25: 400 MM width | D25: =D7*$M$5 -> 111.50244 | E25: =E7*$M$5 -> 105.41463 | F25: =F7*$M$5 -> 100.67967 | G25: =G7*$M$5 -> 97.973984 | H25: =H7*$M$5 -> 96.891707 | I25: =I7*$M$5 -> 96.08 | J25: =J7*$M$5 -> 95.674146
A26: Bastin | B26: SUP with zipper | C26: 500 MM width | D26: =D8*$M$5 -> 151.25447 | E26: =E8*$M$5 -> 145.16667 | F26: =F8*$M$5 -> 140.43171 | G26: =G8*$M$5 -> 137.72602 | H26: =H8*$M$5 -> 136.64374 | I26: =I8*$M$5 -> 135.83203 | J26: =J8*$M$5 -> 135.42618
A27: Bastin | B27: Zipper pouch | C27: 100 MM width | D27: =D9*$M$5 -> 52.405585 | E27: =E9*$M$5 -> 46.31778 | F27: =F9*$M$5 -> 41.582821 | G27: =G9*$M$5 -> 38.87713 | H27: =H9*$M$5 -> 37.794854 | I27: =I9*$M$5 -> 36.983146 | J27: =J9*$M$5 -> 36.577293
A28: Bastin | B28: Zipper pouch | C28: 150 MM width | D28: =D10*$M$5 -> 58.67391 | E28: =E10*$M$5 -> 52.586105 | F28: =F10*$M$5 -> 47.851146 | G28: =G10*$M$5 -> 45.145455 | H28: =H10*$M$5 -> 44.063178 | I28: =I10*$M$5 -> 43.251471 | J28: =J10*$M$5 -> 42.845617
A29: Bastin | B29: Zipper pouch | C29: 200 MM width | D29: =D11*$M$5 -> 66.515466 | E29: =E11*$M$5 -> 60.427661 | F29: =F11*$M$5 -> 55.692701 | G29: =G11*$M$5 -> 52.98701 | H29: =H11*$M$5 -> 51.904734 | I29: =I11*$M$5 -> 51.093027 | J29: =J11*$M$5 -> 50.687173
A30: Bastin | B30: Zipper pouch | C30: 300 MM width | D30: =D12*$M$5 -> 79.864119 | E30: =E12*$M$5 -> 73.776314 | F30: =F12*$M$5 -> 69.041355 | G30: =G12*$M$5 -> 66.335664 | H30: =H12*$M$5 -> 65.253387 | I30: =I12*$M$5 -> 64.44168 | J30: =J12*$M$5 -> 64.035826
A31: Bastin | B31: Zipper pouch | C31: 400 MM width | D31: =D13*$M$5 -> 104.05233 | E31: =E13*$M$5 -> 97.964523 | F31: =F13*$M$5 -> 93.229564 | G31: =G13*$M$5 -> 90.523873 | H31: =H13*$M$5 -> 89.441596 | I31: =I13*$M$5 -> 88.629889 | J31: =J13*$M$5 -> 88.224035
A32: Bastin | B32: Zipper pouch | C32: 500 MM width | D32: =D14*$M$5 -> 140.4932 | E32: =E14*$M$5 -> 134.4054 | F32: =F14*$M$5 -> 129.67044 | G32: =G14*$M$5 -> 126.96475 | H32: =H14*$M$5 -> 125.88247 | I32: =I14*$M$5 -> 125.07076 | J32: =J14*$M$5 -> 124.66491
... A38: Bastin | B38: Open pouch | C38: 500 MM width | D38: =D20*$M$5 -> 126.86876 | E38: =E20*$M$5 -> 120.78096 | F38: =F20*$M$5 -> 116.046 | G38: =G20*$M$5 -> 113.34031 | H38: =H20*$M$5 -> 112.25803 | I38: =I20*$M$5 -> 111.44632 | J38: =J20*$M$5 -> 111.04047

Sheet Lmntn & Prntng- Marma & Bas (2)
A2: Supplier | B2: Width | C2: Per film cost costs: | D2: up to 3k Meters (*) ( **) | E2: 3-10K | F2: 10-25K | G2: 25K-50 | H2: 50-100K | I2: 100-250K | J2: 250-500K | K2: 500K+ | M2: Important notes
A3: MARMA | B3: linear meters (760 width)- EUR/1000m | C3: Lamination First pass | D3: 83.38 | E3: 74.38 | F3: 65.38 | G3: 61.78 | H3: 60.58 | I3: 59.98 | J3: 59.62 | K3: 59.39 | M3: 1.3 | N3: Bastin prices are 30% higher than Marma for lamination
B4: linear meters (760 width)- EUR/1000m | C4: Lamination First pass (120 m/m) | D4: 116.73 | E4: 104.13 | F4: 91.53 | G4: 86.49 | H4: 84.81 | I4: 83.97 | J4: 83.46 | K4: 83.14 | M4: 1.5 | N4: Bastin prices are 50% higher than Marma for printing
B5: linear meters (760 width)- EUR/1000m | C5: Lamination First pass (90 m/m) | D5: 149.15 | E5: 133.05 | F5: 116.95 | G5: 110.51 | H5: 108.36 | I5: 107.29 | J5: 106.64 | K5: 106.24
B6: linear meters (760 width)- EUR/1000m | C6: Lamination Second pass
B7: linear meters (760 width)- EUR/1000m | C7: Printing (1-2 colors)*** | D7: 196.44 | E7: 154.37 | F7: 112.29 | G7: 95.46 | H7: 89.85 | I7: 87.05 | J7: 85.36 | K7: 84.3
B8: linear meters (760 width)- EUR/1000m | C8: Printing (3-4 colors)*** | D8: 227.42 | E8: 177.02 | F8: 126.62 | G8: 106.46 | H8: 99.74 | I8: 96.38 | J8: 94.36 | K8: 93.09
B9: linear meters (760 width)- EUR/1000m | C9: Printing (5-8 colors)*** | D9: 276.21 | E9: 209.16 | F9: 142.11 | G9: 115.29 | H9: 106.35 | I9: 101.88 | J9: 99.2 | K9: 97.5
B10: linear meters (760 width)- EUR/1000m | C10: Slitting | D10: 34.92 | E10: 30.42 | F10: 25.92 | G10: 24.12 | H10: 23.52 | I10: 23.22 | J10: 23.04 | K10: 22.92
B11: linear meters (1220 width)- EUR/1000m | C11: Lamination First pass | D11: 83.375 | E11: 74.38 | F11: 65.38 | G11: 61.78 | H11: 60.58 | I11: 59.98 | J11: 59.62 | K11: 59.39
B12: linear meters (1220 width)- EUR/1000m | C12: Lamination First pass (120 m/m) | D12: 116.73 | E12: 104.13 | F12: 91.53 | G12: 86.49 | H12: 84.81 | I12: 83.97 | J12: 83.46 | K12: 83.14
B13: linear meters (1220 width)- EUR/1000m | C13: Lamination First pass (90 m/m) | D13: 149.15 | E13: 133.05 | F13: 116.95 | G13: 110.51 | H13: 108.36 | I13: 107.29 | J13: 106.64 | K13: 106.24
B14: linear meters (1220 width)- EUR/1000m | C14: Lamination Second pass
B15: linear meters (1220 width)- EUR/1000m | C15: Printing (1-2 colors)*** | D15: 215.03702 | E15: 172.96202 | F15: 130.88702 | G15: 114.05702 | H15: 108.44702 | I15: 105.64202 | J15: 103.95902 | K15: 102.89312
B16: linear meters (1220 width)- EUR/1000m | C16: Printing (3-4 colors)*** | D16: 251.32802 | E16: 200.92802 | F16: 150.52802 | G16: 130.36802 | H16: 123.64802 | I16: 120.28802 | J16: 118.27202 | K16: 116.99522
B17: linear meters (1220 width)- EUR/1000m | C17: Printing (5-8 colors)*** | D17: 302.77352 | E17: 235.72352 | F17: 168.67352 | G17: 141.85352 | H17: 132.91352 | I17: 128.44352 | J17: 125.76152 | K17: 124.06292
B18: linear meters (1220 width)- EUR/1000m | C18: Slitting | D18: 34.916667 | E18: 30.416667 | F18: 25.916667 | G18: 24.116667 | H18: 23.516667 | I18: 23.216667 | J18: 23.036667 | K18: 22.922667
A19: Bastin | B19: linear meters (760 width)- EUR/1000m | C19: Lamination First pass | D19: =D3*$M$3 -> 108.394 | E19: =E3*$M$3 -> 96.694 | F19: =F3*$M$3 -> 84.994 | G19: =G3*$M$3 -> 80.314 | H19: =H3*$M$3 -> 78.754 | I19: =I3*$M$3 -> 77.974 | J19: =J3*$M$3 -> 77.506 | K19: =K3*$M$3 -> 77.207
B20: linear meters (760 width)- EUR/1000m | C20: Lamination First pass (120 m/m) | D20: =D4*$M$3 -> 151.749 | E20: =E4*$M$3 -> 135.369 | F20: =F4*$M$3 -> 118.989 | G20: =G4*$M$3 -> 112.437 | H20: =H4*$M$3 -> 110.253 | I20: =I4*$M$3 -> 109.161 | J20: =J4*$M$3 -> 108.498 | K20: =K4*$M$3 -> 108.082
B21: linear meters (760 width)- EUR/1000m | C21: Lamination First pass (90 m/m) | D21: =D5*$M$3 -> 193.895 | E21: =E5*$M$3 -> 172.965 | F21: =F5*$M$3 -> 152.035 | G21: =G5*$M$3 -> 143.663 | H21: =H5*$M$3 -> 140.868 | I21: =I5*$M$3 -> 139.477 | J21: =J5*$M$3 -> 138.632 | K21: =K5*$M$3 -> 138.112
B22: linear meters (760 width)- EUR/1000m | C22: Lamination Second pass | D22: =D6*$M$3 -> 0 | E22: =E6*$M$3 -> 0 | F22: =F6*$M$3 -> 0 | G22: =G6*$M$3 -> 0 | H22: =H6*$M$3 -> 0 | I22: =I6*$M$3 -> 0 | J22: =J6*$M$3 -> 0 | K22: =K6*$M$3 -> 0
B23: linear meters (760 width)- EUR/1000m | C23: Printing (1-2 colors)*** | D23: =D7*$M$4 -> 294.66 | E23: =E7*$M$4 -> 231.555 | F23: =F7*$M$4 -> 168.435 | G23: =G7*$M$4 -> 143.19 | H23: =H7*$M$4 -> 134.775 | I23: =I7*$M$4 -> 130.575 | J23: =J7*$M$4 -> 128.04 | K23: =K7*$M$4 -> 126.45
B24: linear meters (760 width)- EUR/1000m | C24: Printing (3-4 colors)*** | D24: =D8*$M$4 -> 341.13 | E24: =E8*$M$4 -> 265.53 | F24: =F8*$M$4 -> 189.93 | G24: =G8*$M$4 -> 159.69 | H24: =H8*$M$4 -> 149.61 | I24: =I8*$M$4 -> 144.57 | J24: =J8*$M$4 -> 141.54 | K24: =K8*$M$4 -> 139.635
B25: linear meters (760 width)- EUR/1000m | C25: Printing (5-8 colors)*** | D25: =D9*$M$4 -> 414.315 | E25: =E9*$M$4 -> 313.74 | F25: =F9*$M$4 -> 213.165 | G25: =G9*$M$4 -> 172.935 | H25: =H9*$M$4 -> 159.525 | I25: =I9*$M$4 -> 152.82 | J25: =J9*$M$4 -> 148.8 | K25: =K9*$M$4 -> 146.25
B26: linear meters (760 width)- EUR/1000m | C26: Slitting | D26: =D10*$M$3 -> 45.396 | E26: =E10*$M$3 -> 39.546 | F26: =F10*$M$3 -> 33.696 | G26: =G10*$M$3 -> 31.356 | H26: =H10*$M$3 -> 30.576 | I26: =I10*$M$3 -> 30.186 | J26: =J10*$M$3 -> 29.952 | K26: =K10*$M$3 -> 29.796
B27: linear meters (1220 width)- EUR/1000m | C27: Lamination First pass | D27: =D11*$M$3 -> 108.3875 | E27: =E11*$M$3 -> 96.694 | F27: =F11*$M$3 -> 84.994 | G27: =G11*$M$3 -> 80.314 | H27: =H11*$M$3 -> 78.754 | I27: =I11*$M$3 -> 77.974 | J27: =J11*$M$3 -> 77.506 | K27: =K11*$M$3 -> 77.207
B28: linear meters (1220 width)- EUR/1000m | C28: Lamination First pass (120 m/m) | D28: =D12*$M$3 -> 151.749 | E28: =E12*$M$3 -> 135.369 | F28: =F12*$M$3 -> 118.989 | G28: =G12*$M$3 -> 112.437 | H28: =H12*$M$3 -> 110.253 | I28: =I12*$M$3 -> 109.161 | J28: =J12*$M$3 -> 108.498 | K28: =K12*$M$3 -> 108.082
B29: linear meters (1220 width)- EUR/1000m | C29: Lamination First pass (90 m/m) | D29: =D13*$M$3 -> 193.895 | E29: =E13*$M$3 -> 172.965 | F29: =F13*$M$3 -> 152.035 | G29: =G13*$M$3 -> 143.663 | H29: =H13*$M$3 -> 140.868 | I29: =I13*$M$3 -> 139.477 | J29: =J13*$M$3 -> 138.632 | K29: =K13*$M$3 -> 138.112
B30: linear meters (1220 width)- EUR/1000m | C30: Lamination Second pass | D30: =D14*$M$3 -> 0 | E30: =E14*$M$3 -> 0 | F30: =F14*$M$3 -> 0 | G30: =G14*$M$3 -> 0 | H30: =H14*$M$3 -> 0 | I30: =I14*$M$3 -> 0 | J30: =J14*$M$3 -> 0 | K30: =K14*$M$3 -> 0
B31: linear meters (1220 width)- EUR/1000m | C31: Printing (1-2 colors)*** | D31: =D15*$M$4 -> 322.55553 | E31: =E15*$M$4 -> 259.44303 | F31: =F15*$M$4 -> 196.33053 | G31: =G15*$M$4 -> 171.08553 | H31: =H15*$M$4 -> 162.67053 | I31: =I15*$M$4 -> 158.46303 | J31: =J15*$M$4 -> 155.93853 | K31: =K15*$M$4 -> 154.33968
B32: linear meters (1220 width)- EUR/1000m | C32: Printing (3-4 colors)*** | D32: =D16*$M$4 -> 376.99203 | E32: =E16*$M$4 -> 301.39203 | F32: =F16*$M$4 -> 225.79203 | G32: =G16*$M$4 -> 195.55203 | H32: =H16*$M$4 -> 185.47203 | I32: =I16*$M$4 -> 180.43203 | J32: =J16*$M$4 -> 177.40803 | K32: =K16*$M$4 -> 175.49283
B33: linear meters (1220 width)- EUR/1000m | C33: Printing (5-8 colors)*** | D33: =D17*$M$4 -> 454.16028 | E33: =E17*$M$4 -> 353.58528 | F33: =F17*$M$4 -> 253.01028 | G33: =G17*$M$4 -> 212.78028 | H33: =H17*$M$4 -> 199.37028 | I33: =I17*$M$4 -> 192.66528 | J33: =J17*$M$4 -> 188.64228 | K33: =K17*$M$4 -> 186.09438
B34: linear meters (1220 width)- EUR/1000m | C34: Slitting | D34: =D18*$M$3 -> 45.391667 | E34: =E18*$M$3 -> 39.541667 | F34: =F18*$M$3 -> 33.691667 | G34: =G18*$M$3 -> 31.351667 | H34: =H18*$M$3 -> 30.571667 | I34: =I18*$M$3 -> 30.181667 | J34: =J18*$M$3 -> 29.947667 | K34: =K18*$M$3 -> 29.799467

Sheet Laminates (2)
A1: From Calculator | B1: From Calculator | C1: Dependent | F1: From Calculator | G1: Calculation | H1: From Calculator | I1: From Calculator | J1: Dependent on Laminate | K1: Calculation | L1: Calculation | M1: Calculation | N1: Calculation | O1: From Calculator | P1: Calculation | Q1: From Calculator | R1: Dependent on Length | S1: Dependent on Length | T1: Calculation | U1: Dependent on Length | V1: Calculation | W1: Calculation | Y1: Calculation | Z1: checking purposes | AA1: From Calculator | AB1: Calculation | AC1: Calculation | AG1: 📊 GROSS PROFIT | AH1: 0.15 | AK1: 📊 GROSS PROFIT | AL1: 0.15 | AO1: 📊 GROSS PROFIT | AP1: 0.15
A2: Amount | B2: Laminate | C2: Laminate structure | D2: Width of reel asked | E2: Width of reel used | F2: Length of impression | G2: Laminate length (m) width asked | H2: PR/ NonPR | I2: No of colors | J2: Lamination Width (mm) | K2: Thickness (µ) | L2: Density | M2: Weight (kg) | N2: Raw material Cost | O2: Shipping Terms | P2: Shipment costs | Q2: Producer | R2: Lamination | S2: Printing | T2: Printing per KG | U2: Slitting | V2: Waste | W2: Printing waste | X2: Cost (€) | Y2: Total Cost per KG | Z2: Cost Per KG (€) | AA2: No. of SKUs | AB2: IMP / SKU | AC2: NK ratio | AG2: ="📊 LAMINATE CALCULATOR 1-"&AH3&" Laminate" -> 📊 LAMINATE CALCULATOR 1-428 Laminate | AK2: ="📊 LAMINATE CALCULATOR 2-"&AL3&" Laminate" -> 📊 LAMINATE CALCULATOR 2-428 Laminate | AO2: ="📊 LAMINATE CALCULATOR 3-"&AP3&" Laminate" -> 📊 LAMINATE CALCULATOR 3-428 Laminate
A3: =IF(AH13="By Length",IF(AH14<>"",IFERROR(AH14*$M$8*($D3/$J3),""),""),IF(OR(AH13="By Imp",AH13="IMP"),IFERROR(AH41*$M$8*($D3/$J3),""),IF(AH6="","",AH6))) -> 503.51513 | B3: =AH3 -> 428 | C3: {=IFERROR(_xlfn.LET(_xlpm.lam,TEXT(B3,"0"),_xlpm.thick,AH4,_xlfn.TAKE(_xlfn._xlws.FILTER([6]HELPER!$BW$2:$BW$250,(TEXT([6]HELPER!$BZ$2:$BZ$250,"0")=_xlpm.lam)*([6]HELPER!$CC$2:$CC$250=_xlpm.thick)*([6]HELPER!$BW$2:$BW$250<>""),"No match"),6)),"")} -> NK | D3: =AH5 -> 352 | E3: =IF(D3="","",_xlfn.LET(_xlpm.cap,IF($Q3="Quantum",760,1220),IF(D3+50>_xlpm.cap,"ERROR: Lamination Width > "&_xlpm.cap,D3*MAX(1,MIN(MAX(2,INT(900/D3)),INT((_xlpm.cap-50)/D3)))))) -> 704 | G3: =IF(OR(AH13="IMP",AH13="By Imp",AH13="By Length"),IFERROR(AH16,""),IFERROR(IF(OR(A3="",A3=0,$D3="",$D3=0,$J3="",$M$8="",$M$8=0,A3<=5),"",(A3-5)/$M$8*($J3/$D3)),"")) -> 13939.2 | H3: =AH7 -> Printed | I3: =IF(H3="Not Printed",0,AH8) -> 3-4 | J3: =IF(C3="","",$E$3+16) -> 720 | K3: {=_xlfn.LET(_xlpm.baseThick,IFERROR(INDEX([6]HELPER!$BX$2:$BX$250,MATCH(1,(TEXT([6]HELPER!$BZ$2:$BZ$250,"0")=TEXT($B$3,"0"))*([6]HELPER!$CC$2:$CC$250=$AH$4)*([6]HELPER!$BW$2:$BW$250=C3),0)),""),IF(_xlpm.baseThick="","",_xlpm.baseThick))} -> 23 | L3: =IFERROR(VLOOKUP(C3,[6]HELPER!$AP$1:$AQ$25,2,FALSE),"") -> 1.44 | M3: =IF(C3="","",IF(ISNUMBER(SEARCH("paper",C3)),42/1000*(J3/1000),IF(OR(L3="",L3=0),"",L3*1000*(K3/1000000)*(J3/1000)))) -> 0.0238464 | N3: {=IF($C3="","",_xlfn.LET( _xlpm.mat,TRIM($C3), _xlpm.matKey,UPPER(SUBSTITUTE(_xlpm.mat," ","")), _xlpm.pr,IFERROR(LOOKUP(2,1/($H$3:H3<>""),$H$3:H3),""), _xlpm.widthActual,IFERROR(LOOKUP(2,1/($E$3:E3<>""),$E$3:E3),$E3), _xlpm.euShip,IFERROR([6]HELPER!$AH$3,0), _xlpm.metSetup,IFERROR([6]HELPER!$CH$2,0), _xlpm.filmNames,[6]!Table1[Film Type], _xlpm.filmCosts,[6]!Table1[For Laminates calculation purposes], _xlpm.printCosts,[6]!Table1[Printing], _xlpm.printWaste,[6]!Table1[Printing Waste], _xlpm.filmCost,IF(LEFT(_xlpm.mat,4)="TIPA",IFERROR(IF(_xlpm.pr="Not Printed",MIN(_xlfn._xlws.FILTER(_xlpm.filmCosts,(UPPER(SUBSTITUTE(_xlpm.filmNames," ",""))=_xlpm.matKey)*(_xlpm.printCosts=0)*(_xlpm.printWaste=0)*(_xlpm.filmCosts>0))),INDEX(_xlfn._xlws.FILTER(_xlpm.filmCosts,(UPPER(SUBSTITUTE(_xlpm.filmNames," ",""))=_xlpm.matKey)*(_xlpm.filmCosts>0)),1)),""),""), _xlpm.summaryNames,"", _xlpm.summaryThick,"", _xlpm.summaryCosts,"", _xlpm.summaryCost,IF(LEFT(_xlpm.mat,4)="TIPA",IFERROR(IF(_xlpm.pr="Not Printed",MIN(_xlfn._xlws.FILTER(_xlpm.summaryCosts,(UPPER(SUBSTITUTE(_xlpm.summaryNames," ",""))=_xlpm.matKey)*(_xlpm.summaryThick=$K3)*(_xlpm.summaryCosts>0))),INDEX(_xlfn._xlws.FILTER(_xlpm.summaryCosts,(UPPER(SUBSTITUTE(_xlpm.summaryNames," ",""))=_xlpm.matKey)*(_xlpm.summaryThick=$K3)*(_xlpm.summaryCosts>0)),1)),""),""), _xlpm.finalFilmCost,IF(_xlpm.filmCost<>"",_xlpm.filmCost,_xlpm.summaryCost), _xlpm.metFilmCost,IFERROR(INDEX(_xlpm.filmCosts,MATCH("TIPA 312 MFG",_xlpm.filmNames,0)),INDEX(_xlpm.filmCosts,1)), _xlpm.tipa312MfgCost,IFERROR(IF(_xlpm.pr="Not Printed",MIN(_xlfn._xlws.FILTER(_xlpm.filmCosts,(UPPER(SUBSTITUTE(_xlpm.filmNames," ",""))="TIPA312MFG")*(_xlpm.printCosts=0)*(_xlpm.printWaste=0)*(_xlpm.filmCosts>0))),INDEX(_xlfn._xlws.FILTER(_xlpm.filmCosts,(UPPER(SUBSTITUTE(_xlpm.filmNames," ",""))="TIPA312MFG")*(_xlpm.filmCosts>0)),1)),0), _xlpm.metluxCost,IFERROR(INDEX([6]HELPER!$E$2:$E$32,MATCH(TRUE,TRIM([6]HELPER!$A$2:$A$32)="MET LUX",0)),IFERROR(INDEX([6]HELPER!$E$2:$E$32,MATCH(TRUE,TRIM([6]HELPER!$B$2:$B$32)="MET LUX",0)),IFERROR(INDEX([6]HELPER!$E$2:$E$32,MATCH(TRUE,TRIM([6]HELPER!$C$2:$C$32)="MET LUX",0)),IFERROR(INDEX([6]HELPER!$E$2:$E$32,MATCH(TRUE,TRIM([6]HELPER!$D$2:$D$32)="MET LUX",0)),0)))), _xlpm.helperCost,IFERROR(INDEX([6]HELPER!$E$2:$E$32,MATCH(TRUE,TRIM([6]HELPER!$A$2:$A$32)=_xlpm.mat,0)),IFERROR(INDEX([6]HELPER!$E$2:$E$32,MATCH(TRUE,TRIM([6]HELPER!$B$2:$B$32)=_xlpm.mat,0)),IFERROR(INDEX([6]HELPER!$E$2:$E$32,MATCH(TRUE,TRIM([6]HELPER!$C$2:$C$32)=_xlpm.mat,0)),IFERROR(INDEX([6]HELPER!$E$2:$E$32,MATCH(TRUE,TRIM([6]HELPER!$D$2:$D$32)=_xlpm.mat,0)),"")))), _xlpm.specialCost,IFERROR(_xlfn.XLOOKUP(_xlpm.mat,[6]HELPER!$CK$2:$CK$105,[6]HELPER!$CO$2:$CO$105,""),""), _xlpm.nkHelperCost,IFERROR(INDEX([6]HELPER!$E$2:$E$32,MATCH(TRUE,TRIM([6]HELPER!$A$2:$A$32)="NK",0)),IFERROR(INDEX([6]HELPER!$E$2:$E$32,MATCH(TRUE,TRIM([6]HELPER!$B$2:$B$32)="NK",0)),IFERROR(INDEX([6]HELPER!$E$2:$E$32,MATCH(TRUE,TRIM([6]HELPER!$C$2:$C$32)="NK",0)),IFERROR(INDEX([6]HELPER!$E$2:$E$32,MATCH(TRUE,TRIM([6]HELPER!$D$2:$D$32)="NK",0)),0)))), _xlpm.baseCost,IF(LEFT(_xlpm.mat,4)="TIPA",IF(_xlpm.finalFilmCost<>"",_xlpm.finalFilmCost,_xlpm.specialCost),_xlpm.helperCost), _xlpm.rawResult,IF(OR(_xlpm.mat="NK",_xlpm.mat="NKR",_xlpm.mat="NVS"),_xlpm.nkHelperCost,IF(_xlpm.baseCost="","",IF(OR(_xlpm.finalFilmCost<>"",LEFT(_xlpm.mat,4)="TIPA"),_xlpm.baseCost,_xlpm.baseCost+_xlpm.euShip))), _xlpm.upliftFilm,ISNUMBER(MATCH(_xlpm.matKey,{"TIPA312MET";"TIPA302FG";"TIPA302FGW";"TIPA306M";"TIPA306W";"TIPA312MFG";"TIPA312MFGW"},0)), _xlpm.rawResult ))} -> 7.95 | O3: =AH11 -> EXW | P3: =IF(OR(C3="",A$3<=0),"",IFERROR(IF(O$3="Europe to US",IF(A$3<500,10,IF(A$3<1000,8,IF(A$3<2500,6,IF(A$3<5000,5,4)))),VLOOKUP(O$3,[6]HELPER!$AF$2:$AH$3,3,FALSE)),0)) -> 0 | Q3: =AH12 -> Marma | R3: {=IF(OR($Q3="",$G3=""),"",IF($J3>IF($Q3="Quantum",760,1220),"Error! lamination width exceeds supplier maximum",_xlfn.LET(_xlpm.struct,$C$3:$C$8,_xlpm.realLayers,SUMPRODUCT(--(_xlpm.struct<>""),--ISERROR(SEARCH("EPOTAL",_xlpm.struct&"")),--ISERROR(SEARCH("BASONAT",_xlpm.struct&"")),--ISERROR(SEARCH("ADH",_xlpm.struct&"")),--ISERROR(SEARCH("HARDENER",_xlpm.struct&""))),_xlpm.lamSteps,MAX(0,_xlpm.realLayers-1),_xlpm.len,$G3,_xlpm.colNum,IF(_xlpm.len<3000,1,IF(_xlpm.len<10000,2,IF(_xlpm.len<25000,3,IF(_xlpm.len<50000,4,IF(_xlpm.len<100000,5,IF(_xlpm.len<250000,6,7)))))),_xlpm.widthRow,IF($E3<900,0,5),_xlpm.supplierRow,IF($Q3="Marma",3,IF(OR($Q3="Bastin",$Q3="Quantum"),13,0)),_xlpm.baseRate,IF(_xlpm.supplierRow=0,"",INDEX('[6]Lmntn & Prntng- Marma & Bastin '!$D$1:$K$22,_xlpm.supplierRow+_xlpm.widthRow,_xlpm.colNum)),IF(_xlpm.realLayers=0,"",_xlpm.baseRate*_xlpm.lamSteps))))} -> 0.18306 | S3: {=IF($Q3="Quantum",IF(OR($Q3="",$I3=0,$I3="0"),"",IF($J3>IF($Q3="Quantum",760,1220),"Error! lamination width exceeds supplier maximum",IF($E3>1200,"Data is missing",_xlfn.LET(_xlpm.len,$G3,_xlpm.colors,$I3,_xlpm.qWidth,IF($E3<=450,450,IF($E3<=760,760,1200)),_xlpm.band,IF(_xlpm.colors=1,"1",IF(OR(_xlpm.colors=2,_xlpm.colors=3),"2-3",IF(OR(_xlpm.colors=4,_xlpm.colors=5),"4-5","6-8"))),_xlpm.widths,'[6]Digital_per_meter- Quantum'!$A$32:$A$91,_xlpm.bands,'[6]Digital_per_meter- Quantum'!$C$32:$C$91,_xlpm.meters,'[6]Digital_per_meter- Quantum'!$D$32:$D$91,_xlpm.rates,'[6]Digital_per_meter- Quantum'!$H$32:$H$91,_xlpm.targetM,IFERROR(MIN(_xlfn._xlws.FILTER(_xlpm.meters,(_xlpm.widths=_xlpm.qWidth)*(_xlpm.bands=_xlpm.band)*(_xlpm.meters>=_xlpm.len))),MAX(_xlfn._xlws.FILTER(_xlpm.meters,(_xlpm.widths=_xlpm.qWidth)*(_xlpm.bands=_xlpm.band)))),INDEX(_xlpm.rates,_xlfn.XMATCH(1,(_xlpm.widths=_xlpm.qWidth)*(_xlpm.bands=_xlpm.band)*(_xlpm.meters=_xlpm.targetM),0))/[6]HELPER!$AK$2)))),IF(OR($Q3="",$I3=0,$I3="0"),"",IF($J3>IF($Q3="Quantum",760,1220),"Error! lamination width exceeds supplier maximum",_xlfn.LET(_xlpm.len,$AH$22,_xlpm.colors,$I3,_xlpm.colNum,IF(_xlpm.len<3000,1,IF(_xlpm.len<10000,2,IF(_xlpm.len<25000,3,IF(_xlpm.len<50000,4,IF(_xlpm.len<100000,5,IF(_xlpm.len<250000,6,IF(_xlpm.len<500000,7,8))))))),_xlpm.widthRow,IF($E3<900,0,5),_xlpm.colorOffset,IF(OR(_xlpm.colors=1,_xlpm.colors=2,_xlpm.colors="1-2"),1,IF(OR(_xlpm.colors=3,_xlpm.colors=4,_xlpm.colors="3-4"),2,IF(OR(_xlpm.colors>=5,_xlpm.colors="5-6",_xlpm.colors="5-8"),3,0))),_xlpm.supplierRow,IF($Q3="Marma",3,IF($Q3="Bastin",13,0)),IF(OR(_xlpm.supplierRow=0,_xlpm.colorOffset=0),"",INDEX('[6]Lmntn & Prntng- Marma & Bastin '!$D$1:$K$22,_xlpm.supplierRow+_xlpm.widthRow+_xlpm.colorOffset,_xlpm.colNum))))))} -> 0.17702 | T3: =IF(OR($S3="",$K3=""),"",IFERROR($S3*(1/$M$8)*($J3/($D3*MAX(1,ROUNDDOWN(760/$D3,0)))),"")) -> 2.450291 | U3: {=IF($Q3="","",IF($J3>IF($Q3="Quantum",760,1220),"Error! lamination width exceeds supplier maximum",_xlfn.LET(_xlpm.len,$G3,_xlpm.colNum,IF(_xlpm.len<3000,1,IF(_xlpm.len<10000,2,IF(_xlpm.len<25000,3,IF(_xlpm.len<50000,4,IF(_xlpm.len<100000,5,IF(_xlpm.len<250000,6,7)))))),_xlpm.widthRow,IF($E3<900,0,5),_xlpm.supplierRow,IF($Q3="Marma",7,IF(OR($Q3="Bastin",$Q3="Quantum"),17,0)),IF(_xlpm.supplierRow=0,"",INDEX('[6]Lmntn & Prntng- Marma & Bastin '!$D$1:$K$22,_xlpm.supplierRow+_xlpm.widthRow,_xlpm.colNum)))))} -> 0.02592 | V3: =IFERROR(IF(AH23="","",IF($K8>31,(5%+250/$G$3)*AH23,VLOOKUP($K8,[6]HELPER!$BH$3:$BI$5,2,TRUE)*AH23)),"") -> 0.54781005 | W3: =IF(OR($H3<>"Printed",$I3=0,$I3="0"),0,IFERROR(AH23*0.028,0)+IFERROR(AH44,0)) -> 1.0517187 | X3: =IF($K3="","",IFERROR($M3*($N3+$P3),"")) -> 0.18957888 | Y3: =IFERROR((SUM(X3:X8)+SUM(R3:S3,U3))*(1/M8)*(J3/E3)+V3+W3,"") -> 15.006232 | Z3: =IF($M3="","",IFERROR(($N3+$P3)*$M3/$M$8,"")) -> 2.5658156 | AA3: =AH9 -> 1 | AB3: =IF(OR(AH13="IMP",AH13="By Imp"),IFERROR(AH14/AA3,""),"") -> 52800 | AC3: =AH43 -> 0.33333333 | AG3: 🏷️ Laminate | AH3: 428 | AK3: 🏷️ Laminate | AL3: 428 | AO3: 🏷️ Laminate | AP3: 428
C4: TIPA 312 MET | J4: =IF(C4="","",$E$3+16) -> 720 | K4: {=_xlfn.LET(_xlpm.baseThick,IFERROR(INDEX([6]HELPER!$BX$2:$BX$250,MATCH(1,(TEXT([6]HELPER!$BZ$2:$BZ$250,"0")=TEXT($B$3,"0"))*([6]HELPER!$CC$2:$CC$250=$AH$4)*([6]HELPER!$BW$2:$BW$250=C4),0)),""),IF(_xlpm.baseThick="","",_xlpm.baseThick))} -> 25 | L4: =IFERROR(VLOOKUP(C4,[6]HELPER!$AP$1:$AQ$25,2,FALSE),"") -> 1.25 | M4: =IF(C4="","",IF(ISNUMBER(SEARCH("paper",C4)),42/1000*(J4/1000),IF(OR(L4="",L4=0),"",L4*1000*(K4/1000000)*(J4/1000)))) -> 0.0225 | N4: {=IF($C4="","",_xlfn.LET( _xlpm.mat,TRIM($C4), _xlpm.matKey,UPPER(SUBSTITUTE(_xlpm.mat," ","")), _xlpm.pr,IFERROR(LOOKUP(2,1/($H$3:H4<>""),$H$3:H4),""), _xlpm.widthActual,IFERROR(LOOKUP(2,1/($E$3:E4<>""),$E$3:E4),$E4), _xlpm.euShip,IFERROR([6]HELPER!$AH$3,0), _xlpm.metSetup,IFERROR([6]HELPER!$CH$2,0), _xlpm.filmNames,[6]!Table1[Film Type], _xlpm.filmCosts,[6]!Table1[For Laminates calculation purposes], _xlpm.printCosts,[6]!Table1[Printing], _xlpm.printWaste,[6]!Table1[Printing Waste], _xlpm.filmCost,IF(LEFT(_xlpm.mat,4)="TIPA",IFERROR(IF(_xlpm.pr="Not Printed",MIN(_xlfn._xlws.FILTER(_xlpm.filmCosts,(UPPER(SUBSTITUTE(_xlpm.filmNames," ",""))=_xlpm.matKey)*(_xlpm.printCosts=0)*(_xlpm.printWaste=0)*(_xlpm.filmCosts>0))),INDEX(_xlfn._xlws.FILTER(_xlpm.filmCosts,(UPPER(SUBSTITUTE(_xlpm.filmNames," ",""))=_xlpm.matKey)*(_xlpm.filmCosts>0)),1)),""),""), _xlpm.summaryNames,"", _xlpm.summaryThick,"", _xlpm.summaryCosts,"", _xlpm.summaryCost,IF(LEFT(_xlpm.mat,4)="TIPA",IFERROR(IF(_xlpm.pr="Not Printed",MIN(_xlfn._xlws.FILTER(_xlpm.summaryCosts,(UPPER(SUBSTITUTE(_xlpm.summaryNames," ",""))=_xlpm.matKey)*(_xlpm.summaryThick=$K4)*(_xlpm.summaryCosts>0))),INDEX(_xlfn._xlws.FILTER(_xlpm.summaryCosts,(UPPER(SUBSTITUTE(_xlpm.summaryNames," ",""))=_xlpm.matKey)*(_xlpm.summaryThick=$K4)*(_xlpm.summaryCosts>0)),1)),""),""), _xlpm.finalFilmCost,IF(_xlpm.filmCost<>"",_xlpm.filmCost,_xlpm.summaryCost), _xlpm.metFilmCost,IFERROR(INDEX(_xlpm.filmCosts,MATCH("TIPA 312 MFG",_xlpm.filmNames,0)),INDEX(_xlpm.filmCosts,1)), _xlpm.tipa312MfgCost,IFERROR(IF(_xlpm.pr="Not Printed",MIN(_xlfn._xlws.FILTER(_xlpm.filmCosts,(UPPER(SUBSTITUTE(_xlpm.filmNames," ",""))="TIPA312MFG")*(_xlpm.printCosts=0)*(_xlpm.printWaste=0)*(_xlpm.filmCosts>0))),INDEX(_xlfn._xlws.FILTER(_xlpm.filmCosts,(UPPER(SUBSTITUTE(_xlpm.filmNames," ",""))="TIPA312MFG")*(_xlpm.filmCosts>0)),1)),0), _xlpm.metluxCost,IFERROR(INDEX([6]HELPER!$E$2:$E$32,MATCH(TRUE,TRIM([6]HELPER!$A$2:$A$32)="MET LUX",0)),IFERROR(INDEX([6]HELPER!$E$2:$E$32,MATCH(TRUE,TRIM([6]HELPER!$B$2:$B$32)="MET LUX",0)),IFERROR(INDEX([6]HELPER!$E$2:$E$32,MATCH(TRUE,TRIM([6]HELPER!$C$2:$C$32)="MET LUX",0)),IFERROR(INDEX([6]HELPER!$E$2:$E$32,MATCH(TRUE,TRIM([6]HELPER!$D$2:$D$32)="MET LUX",0)),0)))), _xlpm.helperCost,IFERROR(INDEX([6]HELPER!$E$2:$E$32,MATCH(TRUE,TRIM([6]HELPER!$A$2:$A$32)=_xlpm.mat,0)),IFERROR(INDEX([6]HELPER!$E$2:$E$32,MATCH(TRUE,TRIM([6]HELPER!$B$2:$B$32)=_xlpm.mat,0)),IFERROR(INDEX([6]HELPER!$E$2:$E$32,MATCH(TRUE,TRIM([6]HELPER!$C$2:$C$32)=_xlpm.mat,0)),IFERROR(INDEX([6]HELPER!$E$2:$E$32,MATCH(TRUE,TRIM([6]HELPER!$D$2:$D$32)=_xlpm.mat,0)),"")))), _xlpm.specialCost,IFERROR(_xlfn.XLOOKUP(_xlpm.mat,[6]HELPER!$CK$2:$CK$105,[6]HELPER!$CO$2:$CO$105,""),""), _xlpm.nkHelperCost,IFERROR(INDEX([6]HELPER!$E$2:$E$32,MATCH(TRUE,TRIM([6]HELPER!$A$2:$A$32)="NK",0)),IFERROR(INDEX([6]HELPER!$E$2:$E$32,MATCH(TRUE,TRIM([6]HELPER!$B$2:$B$32)="NK",0)),IFERROR(INDEX([6]HELPER!$E$2:$E$32,MATCH(TRUE,TRIM([6]HELPER!$C$2:$C$32)="NK",0)),IFERROR(INDEX([6]HELPER!$E$2:$E$32,MATCH(TRUE,TRIM([6]HELPER!$D$2:$D$32)="NK",0)),0)))), _xlpm.baseCost,IF(LEFT(_xlpm.mat,4)="TIPA",IF(_xlpm.finalFilmCost<>"",_xlpm.finalFilmCost,_xlpm.specialCost),_xlpm.helperCost), _xlpm.rawResult,IF(OR(_xlpm.mat="NK",_xlpm.mat="NKR",_xlpm.mat="NVS"),_xlpm.nkHelperCost,IF(_xlpm.baseCost="","",IF(OR(_xlpm.finalFilmCost<>"",LEFT(_xlpm.mat,4)="TIPA"),_xlpm.baseCost,_xlpm.baseCost+_xlpm.euShip))), _xlpm.upliftFilm,ISNUMBER(MATCH(_xlpm.matKey,{"TIPA312MET";"TIPA302FG";"TIPA302FGW";"TIPA306M";"TIPA306W";"TIPA312MFG";"TIPA312MFGW"},0)), _xlpm.rawResult ))} -> 8.1897203 | P4: =IF(OR(C4="",A$3<=0),"",IFERROR(IF(O$3="Europe to US",IF(A$3<500,10,IF(A$3<1000,8,IF(A$3<2500,6,IF(A$3<5000,5,4)))),VLOOKUP(O$3,[6]HELPER!$AF$2:$AH$3,3,FALSE)),0)) -> 0 | X4: =IF($K4="","",IFERROR($M4*($N4+$P4),"")) -> 0.18426871 | Z4: =IF($M4="","",IFERROR(($N4+$P4)*$M4/$M$8,"")) -> 2.4939462 | AG4: 📏 Total Thickness | AH4: 80 | AI4: µ | AK4: 📏 Total Thickness | AL4: 80 | AM4: µ | AO4: 📏 Total Thickness | AP4: 80 | AQ4: µ
C5: TIPA 312 MET | J5: =IF(C5="","",$E$3+16) -> 720 | K5: {=_xlfn.LET(_xlpm.baseThick,IFERROR(INDEX([6]HELPER!$BX$2:$BX$250,MATCH(1,(TEXT([6]HELPER!$BZ$2:$BZ$250,"0")=TEXT($B$3,"0"))*([6]HELPER!$CC$2:$CC$250=$AH$4)*([6]HELPER!$BW$2:$BW$250=C5),0)),""),IF(_xlpm.baseThick="","",_xlpm.baseThick))} -> 25 | L5: =IFERROR(VLOOKUP(C5,[6]HELPER!$AP$1:$AQ$25,2,FALSE),"") -> 1.25 | M5: =IF(C5="","",IF(ISNUMBER(SEARCH("paper",C5)),42/1000*(J5/1000),IF(OR(L5="",L5=0),"",L5*1000*(K5/1000000)*(J5/1000)))) -> 0.0225 | N5: {=IF($C5="","",_xlfn.LET( _xlpm.mat,TRIM($C5), _xlpm.matKey,UPPER(SUBSTITUTE(_xlpm.mat," ","")), _xlpm.pr,IFERROR(LOOKUP(2,1/($H$3:H5<>""),$H$3:H5),""), _xlpm.widthActual,IFERROR(LOOKUP(2,1/($E$3:E5<>""),$E$3:E5),$E5), _xlpm.euShip,IFERROR([6]HELPER!$AH$3,0), _xlpm.metSetup,IFERROR([6]HELPER!$CH$2,0), _xlpm.filmNames,[6]!Table1[Film Type], _xlpm.filmCosts,[6]!Table1[For Laminates calculation purposes], _xlpm.printCosts,[6]!Table1[Printing], _xlpm.printWaste,[6]!Table1[Printing Waste], _xlpm.filmCost,IF(LEFT(_xlpm.mat,4)="TIPA",IFERROR(IF(_xlpm.pr="Not Printed",MIN(_xlfn._xlws.FILTER(_xlpm.filmCosts,(UPPER(SUBSTITUTE(_xlpm.filmNames," ",""))=_xlpm.matKey)*(_xlpm.printCosts=0)*(_xlpm.printWaste=0)*(_xlpm.filmCosts>0))),INDEX(_xlfn._xlws.FILTER(_xlpm.filmCosts,(UPPER(SUBSTITUTE(_xlpm.filmNames," ",""))=_xlpm.matKey)*(_xlpm.filmCosts>0)),1)),""),""), _xlpm.summaryNames,"", _xlpm.summaryThick,"", _xlpm.summaryCosts,"", _xlpm.summaryCost,IF(LEFT(_xlpm.mat,4)="TIPA",IFERROR(IF(_xlpm.pr="Not Printed",MIN(_xlfn._xlws.FILTER(_xlpm.summaryCosts,(UPPER(SUBSTITUTE(_xlpm.summaryNames," ",""))=_xlpm.matKey)*(_xlpm.summaryThick=$K5)*(_xlpm.summaryCosts>0))),INDEX(_xlfn._xlws.FILTER(_xlpm.summaryCosts,(UPPER(SUBSTITUTE(_xlpm.summaryNames," ",""))=_xlpm.matKey)*(_xlpm.summaryThick=$K5)*(_xlpm.summaryCosts>0)),1)),""),""), _xlpm.finalFilmCost,IF(_xlpm.filmCost<>"",_xlpm.filmCost,_xlpm.summaryCost), _xlpm.metFilmCost,IFERROR(INDEX(_xlpm.filmCosts,MATCH("TIPA 312 MFG",_xlpm.filmNames,0)),INDEX(_xlpm.filmCosts,1)), _xlpm.tipa312MfgCost,IFERROR(IF(_xlpm.pr="Not Printed",MIN(_xlfn._xlws.FILTER(_xlpm.filmCosts,(UPPER(SUBSTITUTE(_xlpm.filmNames," ",""))="TIPA312MFG")*(_xlpm.printCosts=0)*(_xlpm.printWaste=0)*(_xlpm.filmCosts>0))),INDEX(_xlfn._xlws.FILTER(_xlpm.filmCosts,(UPPER(SUBSTITUTE(_xlpm.filmNames," ",""))="TIPA312MFG")*(_xlpm.filmCosts>0)),1)),0), _xlpm.metluxCost,IFERROR(INDEX([6]HELPER!$E$2:$E$32,MATCH(TRUE,TRIM([6]HELPER!$A$2:$A$32)="MET LUX",0)),IFERROR(INDEX([6]HELPER!$E$2:$E$32,MATCH(TRUE,TRIM([6]HELPER!$B$2:$B$32)="MET LUX",0)),IFERROR(INDEX([6]HELPER!$E$2:$E$32,MATCH(TRUE,TRIM([6]HELPER!$C$2:$C$32)="MET LUX",0)),IFERROR(INDEX([6]HELPER!$E$2:$E$32,MATCH(TRUE,TRIM([6]HELPER!$D$2:$D$32)="MET LUX",0)),0)))), _xlpm.helperCost,IFERROR(INDEX([6]HELPER!$E$2:$E$32,MATCH(TRUE,TRIM([6]HELPER!$A$2:$A$32)=_xlpm.mat,0)),IFERROR(INDEX([6]HELPER!$E$2:$E$32,MATCH(TRUE,TRIM([6]HELPER!$B$2:$B$32)=_xlpm.mat,0)),IFERROR(INDEX([6]HELPER!$E$2:$E$32,MATCH(TRUE,TRIM([6]HELPER!$C$2:$C$32)=_xlpm.mat,0)),IFERROR(INDEX([6]HELPER!$E$2:$E$32,MATCH(TRUE,TRIM([6]HELPER!$D$2:$D$32)=_xlpm.mat,0)),"")))), _xlpm.specialCost,IFERROR(_xlfn.XLOOKUP(_xlpm.mat,[6]HELPER!$CK$2:$CK$105,[6]HELPER!$CO$2:$CO$105,""),""), _xlpm.nkHelperCost,IFERROR(INDEX([6]HELPER!$E$2:$E$32,MATCH(TRUE,TRIM([6]HELPER!$A$2:$A$32)="NK",0)),IFERROR(INDEX([6]HELPER!$E$2:$E$32,MATCH(TRUE,TRIM([6]HELPER!$B$2:$B$32)="NK",0)),IFERROR(INDEX([6]HELPER!$E$2:$E$32,MATCH(TRUE,TRIM([6]HELPER!$C$2:$C$32)="NK",0)),IFERROR(INDEX([6]HELPER!$E$2:$E$32,MATCH(TRUE,TRIM([6]HELPER!$D$2:$D$32)="NK",0)),0)))), _xlpm.baseCost,IF(LEFT(_xlpm.mat,4)="TIPA",IF(_xlpm.finalFilmCost<>"",_xlpm.finalFilmCost,_xlpm.specialCost),_xlpm.helperCost), _xlpm.rawResult,IF(OR(_xlpm.mat="NK",_xlpm.mat="NKR",_xlpm.mat="NVS"),_xlpm.nkHelperCost,IF(_xlpm.baseCost="","",IF(OR(_xlpm.finalFilmCost<>"",LEFT(_xlpm.mat,4)="TIPA"),_xlpm.baseCost,_xlpm.baseCost+_xlpm.euShip))), _xlpm.upliftFilm,ISNUMBER(MATCH(_xlpm.matKey,{"TIPA312MET";"TIPA302FG";"TIPA302FGW";"TIPA306M";"TIPA306W";"TIPA312MFG";"TIPA312MFGW"},0)), _xlpm.rawResult ))} -> 8.1897203 | P5: =IF(OR(C5="",A$3<=0),"",IFERROR(IF(O$3="Europe to US",IF(A$3<500,10,IF(A$3<1000,8,IF(A$3<2500,6,IF(A$3<5000,5,4)))),VLOOKUP(O$3,[6]HELPER!$AF$2:$AH$3,3,FALSE)),0)) -> 0 | X5: =IF($K5="","",IFERROR($M5*($N5+$P5),"")) -> 0.18426871 | Z5: =IF($M5="","",IFERROR(($N5+$P5)*$M5/$M$8,"")) -> 2.4939462 | AG5: 📐 Width of Reel | AH5: 352 | AI5: mm | AK5: 📐 Width of Reel | AL5: 352 | AM5: mm | AO5: 📐 Width of Reel | AP5: 352 | AQ5: mm
C6: RM G Epotal ECO 3675 | J6: =IF(C6="","",$E$3+16) -> 720 | K6: {=_xlfn.LET(_xlpm.baseThick,IFERROR(INDEX([6]HELPER!$BX$2:$BX$250,MATCH(1,(TEXT([6]HELPER!$BZ$2:$BZ$250,"0")=TEXT($B$3,"0"))*([6]HELPER!$CC$2:$CC$250=$AH$4)*([6]HELPER!$BW$2:$BW$250=C6),0)),""),IF(_xlpm.baseThick="","",_xlpm.baseThick))} -> 7 | L6: =IFERROR(VLOOKUP(C6,[6]HELPER!$AP$1:$AQ$25,2,FALSE),"") -> 1 | M6: =IF(C6="","",IF(ISNUMBER(SEARCH("paper",C6)),42/1000*(J6/1000),IF(OR(L6="",L6=0),"",L6*1000*(K6/1000000)*(J6/1000)))) -> 0.00504 | N6: {=IF($C6="","",_xlfn.LET( _xlpm.mat,TRIM($C6), _xlpm.matKey,UPPER(SUBSTITUTE(_xlpm.mat," ","")), _xlpm.pr,IFERROR(LOOKUP(2,1/($H$3:H6<>""),$H$3:H6),""), _xlpm.widthActual,IFERROR(LOOKUP(2,1/($E$3:E6<>""),$E$3:E6),$E6), _xlpm.euShip,IFERROR([6]HELPER!$AH$3,0), _xlpm.metSetup,IFERROR([6]HELPER!$CH$2,0), _xlpm.filmNames,[6]!Table1[Film Type], _xlpm.filmCosts,[6]!Table1[For Laminates calculation purposes], _xlpm.printCosts,[6]!Table1[Printing], _xlpm.printWaste,[6]!Table1[Printing Waste], _xlpm.filmCost,IF(LEFT(_xlpm.mat,4)="TIPA",IFERROR(IF(_xlpm.pr="Not Printed",MIN(_xlfn._xlws.FILTER(_xlpm.filmCosts,(UPPER(SUBSTITUTE(_xlpm.filmNames," ",""))=_xlpm.matKey)*(_xlpm.printCosts=0)*(_xlpm.printWaste=0)*(_xlpm.filmCosts>0))),INDEX(_xlfn._xlws.FILTER(_xlpm.filmCosts,(UPPER(SUBSTITUTE(_xlpm.filmNames," ",""))=_xlpm.matKey)*(_xlpm.filmCosts>0)),1)),""),""), _xlpm.summaryNames,"", _xlpm.summaryThick,"", _xlpm.summaryCosts,"", _xlpm.summaryCost,IF(LEFT(_xlpm.mat,4)="TIPA",IFERROR(IF(_xlpm.pr="Not Printed",MIN(_xlfn._xlws.FILTER(_xlpm.summaryCosts,(UPPER(SUBSTITUTE(_xlpm.summaryNames," ",""))=_xlpm.matKey)*(_xlpm.summaryThick=$K6)*(_xlpm.summaryCosts>0))),INDEX(_xlfn._xlws.FILTER(_xlpm.summaryCosts,(UPPER(SUBSTITUTE(_xlpm.summaryNames," ",""))=_xlpm.matKey)*(_xlpm.summaryThick=$K6)*(_xlpm.summaryCosts>0)),1)),""),""), _xlpm.finalFilmCost,IF(_xlpm.filmCost<>"",_xlpm.filmCost,_xlpm.summaryCost), _xlpm.metFilmCost,IFERROR(INDEX(_xlpm.filmCosts,MATCH("TIPA 312 MFG",_xlpm.filmNames,0)),INDEX(_xlpm.filmCosts,1)), _xlpm.tipa312MfgCost,IFERROR(IF(_xlpm.pr="Not Printed",MIN(_xlfn._xlws.FILTER(_xlpm.filmCosts,(UPPER(SUBSTITUTE(_xlpm.filmNames," ",""))="TIPA312MFG")*(_xlpm.printCosts=0)*(_xlpm.printWaste=0)*(_xlpm.filmCosts>0))),INDEX(_xlfn._xlws.FILTER(_xlpm.filmCosts,(UPPER(SUBSTITUTE(_xlpm.filmNames," ",""))="TIPA312MFG")*(_xlpm.filmCosts>0)),1)),0), _xlpm.metluxCost,IFERROR(INDEX([6]HELPER!$E$2:$E$32,MATCH(TRUE,TRIM([6]HELPER!$A$2:$A$32)="MET LUX",0)),IFERROR(INDEX([6]HELPER!$E$2:$E$32,MATCH(TRUE,TRIM([6]HELPER!$B$2:$B$32)="MET LUX",0)),IFERROR(INDEX([6]HELPER!$E$2:$E$32,MATCH(TRUE,TRIM([6]HELPER!$C$2:$C$32)="MET LUX",0)),IFERROR(INDEX([6]HELPER!$E$2:$E$32,MATCH(TRUE,TRIM([6]HELPER!$D$2:$D$32)="MET LUX",0)),0)))), _xlpm.helperCost,IFERROR(INDEX([6]HELPER!$E$2:$E$32,MATCH(TRUE,TRIM([6]HELPER!$A$2:$A$32)=_xlpm.mat,0)),IFERROR(INDEX([6]HELPER!$E$2:$E$32,MATCH(TRUE,TRIM([6]HELPER!$B$2:$B$32)=_xlpm.mat,0)),IFERROR(INDEX([6]HELPER!$E$2:$E$32,MATCH(TRUE,TRIM([6]HELPER!$C$2:$C$32)=_xlpm.mat,0)),IFERROR(INDEX([6]HELPER!$E$2:$E$32,MATCH(TRUE,TRIM([6]HELPER!$D$2:$D$32)=_xlpm.mat,0)),"")))), _xlpm.specialCost,IFERROR(_xlfn.XLOOKUP(_xlpm.mat,[6]HELPER!$CK$2:$CK$105,[6]HELPER!$CO$2:$CO$105,""),""), _xlpm.nkHelperCost,IFERROR(INDEX([6]HELPER!$E$2:$E$32,MATCH(TRUE,TRIM([6]HELPER!$A$2:$A$32)="NK",0)),IFERROR(INDEX([6]HELPER!$E$2:$E$32,MATCH(TRUE,TRIM([6]HELPER!$B$2:$B$32)="NK",0)),IFERROR(INDEX([6]HELPER!$E$2:$E$32,MATCH(TRUE,TRIM([6]HELPER!$C$2:$C$32)="NK",0)),IFERROR(INDEX([6]HELPER!$E$2:$E$32,MATCH(TRUE,TRIM([6]HELPER!$D$2:$D$32)="NK",0)),0)))), _xlpm.baseCost,IF(LEFT(_xlpm.mat,4)="TIPA",IF(_xlpm.finalFilmCost<>"",_xlpm.finalFilmCost,_xlpm.specialCost),_xlpm.helperCost), _xlpm.rawResult,IF(OR(_xlpm.mat="NK",_xlpm.mat="NKR",_xlpm.mat="NVS"),_xlpm.nkHelperCost,IF(_xlpm.baseCost="","",IF(OR(_xlpm.finalFilmCost<>"",LEFT(_xlpm.mat,4)="TIPA"),_xlpm.baseCost,_xlpm.baseCost+_xlpm.euShip))), _xlpm.upliftFilm,ISNUMBER(MATCH(_xlpm.matKey,{"TIPA312MET";"TIPA302FG";"TIPA302FGW";"TIPA306M";"TIPA306W";"TIPA312MFG";"TIPA312MFGW"},0)), _xlpm.rawResult ))} -> 4.85 | P6: =IF(OR(C6="",A$3<=0),"",IFERROR(IF(O$3="Europe to US",IF(A$3<500,10,IF(A$3<1000,8,IF(A$3<2500,6,IF(A$3<5000,5,4)))),VLOOKUP(O$3,[6]HELPER!$AF$2:$AH$3,3,FALSE)),0)) -> 0 | X6: =IF($K6="","",IFERROR($M6*($N6+$P6),"")) -> 0.024444 | Z6: =IF($M6="","",IFERROR(($N6+$P6)*$M6/$M$8,"")) -> 0.3308322 | AG6: ⚖️ Amount (Kg) | AI6: Kg | AK6: ⚖️ Amount (Kg) | AM6: Kg | AO6: ⚖️ Amount (Kg) | AQ6: Kg
J7: =IF(C7="","",$E$3+16) | K7: {=_xlfn.LET(_xlpm.baseThick,IFERROR(INDEX([6]HELPER!$BX$2:$BX$250,MATCH(1,(TEXT([6]HELPER!$BZ$2:$BZ$250,"0")=TEXT($B$3,"0"))*([6]HELPER!$CC$2:$CC$250=$AH$4)*([6]HELPER!$BW$2:$BW$250=C7),0)),""),IF(_xlpm.baseThick="","",_xlpm.baseThick))} | L7: =IFERROR(VLOOKUP(C7,[6]HELPER!$AP$1:$AQ$25,2,FALSE),"") | M7: =IF(C7="","",IF(ISNUMBER(SEARCH("paper",C7)),42/1000*(J7/1000),IF(OR(L7="",L7=0),"",L7*1000*(K7/1000000)*(J7/1000)))) | N7: {=IF($C7="","",_xlfn.LET( _xlpm.mat,TRIM($C7), _xlpm.matKey,UPPER(SUBSTITUTE(_xlpm.mat," ","")), _xlpm.pr,IFERROR(LOOKUP(2,1/($H$3:H7<>""),$H$3:H7),""), _xlpm.widthActual,IFERROR(LOOKUP(2,1/($E$3:E7<>""),$E$3:E7),$E7), _xlpm.euShip,IFERROR([6]HELPER!$AH$3,0), _xlpm.metSetup,IFERROR([6]HELPER!$CH$2,0), _xlpm.filmNames,[6]!Table1[Film Type], _xlpm.filmCosts,[6]!Table1[For Laminates calculation purposes], _xlpm.printCosts,[6]!Table1[Printing], _xlpm.printWaste,[6]!Table1[Printing Waste], _xlpm.filmCost,IF(LEFT(_xlpm.mat,4)="TIPA",IFERROR(IF(_xlpm.pr="Not Printed",MIN(_xlfn._xlws.FILTER(_xlpm.filmCosts,(UPPER(SUBSTITUTE(_xlpm.filmNames," ",""))=_xlpm.matKey)*(_xlpm.printCosts=0)*(_xlpm.printWaste=0)*(_xlpm.filmCosts>0))),INDEX(_xlfn._xlws.FILTER(_xlpm.filmCosts,(UPPER(SUBSTITUTE(_xlpm.filmNames," ",""))=_xlpm.matKey)*(_xlpm.filmCosts>0)),1)),""),""), _xlpm.summaryNames,"", _xlpm.summaryThick,"", _xlpm.summaryCosts,"", _xlpm.summaryCost,IF(LEFT(_xlpm.mat,4)="TIPA",IFERROR(IF(_xlpm.pr="Not Printed",MIN(_xlfn._xlws.FILTER(_xlpm.summaryCosts,(UPPER(SUBSTITUTE(_xlpm.summaryNames," ",""))=_xlpm.matKey)*(_xlpm.summaryThick=$K7)*(_xlpm.summaryCosts>0))),INDEX(_xlfn._xlws.FILTER(_xlpm.summaryCosts,(UPPER(SUBSTITUTE(_xlpm.summaryNames," ",""))=_xlpm.matKey)*(_xlpm.summaryThick=$K7)*(_xlpm.summaryCosts>0)),1)),""),""), _xlpm.finalFilmCost,IF(_xlpm.filmCost<>"",_xlpm.filmCost,_xlpm.summaryCost), _xlpm.metFilmCost,IFERROR(INDEX(_xlpm.filmCosts,MATCH("TIPA 312 MFG",_xlpm.filmNames,0)),INDEX(_xlpm.filmCosts,1)), _xlpm.tipa312MfgCost,IFERROR(IF(_xlpm.pr="Not Printed",MIN(_xlfn._xlws.FILTER(_xlpm.filmCosts,(UPPER(SUBSTITUTE(_xlpm.filmNames," ",""))="TIPA312MFG")*(_xlpm.printCosts=0)*(_xlpm.printWaste=0)*(_xlpm.filmCosts>0))),INDEX(_xlfn._xlws.FILTER(_xlpm.filmCosts,(UPPER(SUBSTITUTE(_xlpm.filmNames," ",""))="TIPA312MFG")*(_xlpm.filmCosts>0)),1)),0), _xlpm.metluxCost,IFERROR(INDEX([6]HELPER!$E$2:$E$32,MATCH(TRUE,TRIM([6]HELPER!$A$2:$A$32)="MET LUX",0)),IFERROR(INDEX([6]HELPER!$E$2:$E$32,MATCH(TRUE,TRIM([6]HELPER!$B$2:$B$32)="MET LUX",0)),IFERROR(INDEX([6]HELPER!$E$2:$E$32,MATCH(TRUE,TRIM([6]HELPER!$C$2:$C$32)="MET LUX",0)),IFERROR(INDEX([6]HELPER!$E$2:$E$32,MATCH(TRUE,TRIM([6]HELPER!$D$2:$D$32)="MET LUX",0)),0)))), _xlpm.helperCost,IFERROR(INDEX([6]HELPER!$E$2:$E$32,MATCH(TRUE,TRIM([6]HELPER!$A$2:$A$32)=_xlpm.mat,0)),IFERROR(INDEX([6]HELPER!$E$2:$E$32,MATCH(TRUE,TRIM([6]HELPER!$B$2:$B$32)=_xlpm.mat,0)),IFERROR(INDEX([6]HELPER!$E$2:$E$32,MATCH(TRUE,TRIM([6]HELPER!$C$2:$C$32)=_xlpm.mat,0)),IFERROR(INDEX([6]HELPER!$E$2:$E$32,MATCH(TRUE,TRIM([6]HELPER!$D$2:$D$32)=_xlpm.mat,0)),"")))), _xlpm.specialCost,IFERROR(_xlfn.XLOOKUP(_xlpm.mat,[6]HELPER!$CK$2:$CK$105,[6]HELPER!$CO$2:$CO$105,""),""), _xlpm.nkHelperCost,IFERROR(INDEX([6]HELPER!$E$2:$E$32,MATCH(TRUE,TRIM([6]HELPER!$A$2:$A$32)="NK",0)),IFERROR(INDEX([6]HELPER!$E$2:$E$32,MATCH(TRUE,TRIM([6]HELPER!$B$2:$B$32)="NK",0)),IFERROR(INDEX([6]HELPER!$E$2:$E$32,MATCH(TRUE,TRIM([6]HELPER!$C$2:$C$32)="NK",0)),IFERROR(INDEX([6]HELPER!$E$2:$E$32,MATCH(TRUE,TRIM([6]HELPER!$D$2:$D$32)="NK",0)),0)))), _xlpm.baseCost,IF(LEFT(_xlpm.mat,4)="TIPA",IF(_xlpm.finalFilmCost<>"",_xlpm.finalFilmCost,_xlpm.specialCost),_xlpm.helperCost), _xlpm.rawResult,IF(OR(_xlpm.mat="NK",_xlpm.mat="NKR",_xlpm.mat="NVS"),_xlpm.nkHelperCost,IF(_xlpm.baseCost="","",IF(OR(_xlpm.finalFilmCost<>"",LEFT(_xlpm.mat,4)="TIPA"),_xlpm.baseCost,_xlpm.baseCost+_xlpm.euShip))), _xlpm.upliftFilm,ISNUMBER(MATCH(_xlpm.matKey,{"TIPA312MET";"TIPA302FG";"TIPA302FGW";"TIPA306M";"TIPA306W";"TIPA312MFG";"TIPA312MFGW"},0)), _xlpm.rawResult ))} | P7: =IF(OR(C7="",A$3<=0),"",IFERROR(IF(O$3="Europe to US",IF(A$3<500,10,IF(A$3<1000,8,IF(A$3<2500,6,IF(A$3<5000,5,4)))),VLOOKUP(O$3,[6]HELPER!$AF$2:$AH$3,3,FALSE)),0)) | X7: =IF($K7="","",IFERROR($M7*($N7+$P7),"")) | Z7: =IF($M7="","",IFERROR(($N7+$P7)*$M7/$M$8,"")) | AG7: 🖨️ PR/NonPR | AH7: Printed | AK7: 🖨️ PR/NonPR | AL7: Printed | AO7: 🖨️ PR/NonPR | AP7: Printed
J8: =IF(C8="","",$E$3+16) | K8: =AH4 -> 80 | L8: =IFERROR(VLOOKUP(C8,[6]HELPER!$AP$1:$AQ$25,2,FALSE),"") | M8: =SUM(M3:M7) -> 0.0738864 | N8: {=IF($C8="","",_xlfn.LET( _xlpm.mat,TRIM($C8), _xlpm.matKey,UPPER(SUBSTITUTE(_xlpm.mat," ","")), _xlpm.pr,IFERROR(LOOKUP(2,1/($H$3:H8<>""),$H$3:H8),""), _xlpm.widthActual,IFERROR(LOOKUP(2,1/($E$3:E8<>""),$E$3:E8),$E8), _xlpm.euShip,IFERROR([6]HELPER!$AH$3,0), _xlpm.metSetup,IFERROR([6]HELPER!$CH$2,0), _xlpm.filmNames,[6]!Table1[Film Type], _xlpm.filmCosts,[6]!Table1[For Laminates calculation purposes], _xlpm.printCosts,[6]!Table1[Printing], _xlpm.printWaste,[6]!Table1[Printing Waste], _xlpm.filmCost,IF(LEFT(_xlpm.mat,4)="TIPA",IFERROR(IF(_xlpm.pr="Not Printed",MIN(_xlfn._xlws.FILTER(_xlpm.filmCosts,(UPPER(SUBSTITUTE(_xlpm.filmNames," ",""))=_xlpm.matKey)*(_xlpm.printCosts=0)*(_xlpm.printWaste=0)*(_xlpm.filmCosts>0))),INDEX(_xlfn._xlws.FILTER(_xlpm.filmCosts,(UPPER(SUBSTITUTE(_xlpm.filmNames," ",""))=_xlpm.matKey)*(_xlpm.filmCosts>0)),1)),""),""), _xlpm.summaryNames,"", _xlpm.summaryThick,"", _xlpm.summaryCosts,"", _xlpm.summaryCost,IF(LEFT(_xlpm.mat,4)="TIPA",IFERROR(IF(_xlpm.pr="Not Printed",MIN(_xlfn._xlws.FILTER(_xlpm.summaryCosts,(UPPER(SUBSTITUTE(_xlpm.summaryNames," ",""))=_xlpm.matKey)*(_xlpm.summaryThick=$K8)*(_xlpm.summaryCosts>0))),INDEX(_xlfn._xlws.FILTER(_xlpm.summaryCosts,(UPPER(SUBSTITUTE(_xlpm.summaryNames," ",""))=_xlpm.matKey)*(_xlpm.summaryThick=$K8)*(_xlpm.summaryCosts>0)),1)),""),""), _xlpm.finalFilmCost,IF(_xlpm.filmCost<>"",_xlpm.filmCost,_xlpm.summaryCost), _xlpm.metFilmCost,IFERROR(INDEX(_xlpm.filmCosts,MATCH("TIPA 312 MFG",_xlpm.filmNames,0)),INDEX(_xlpm.filmCosts,1)), _xlpm.tipa312MfgCost,IFERROR(IF(_xlpm.pr="Not Printed",MIN(_xlfn._xlws.FILTER(_xlpm.filmCosts,(UPPER(SUBSTITUTE(_xlpm.filmNames," ",""))="TIPA312MFG")*(_xlpm.printCosts=0)*(_xlpm.printWaste=0)*(_xlpm.filmCosts>0))),INDEX(_xlfn._xlws.FILTER(_xlpm.filmCosts,(UPPER(SUBSTITUTE(_xlpm.filmNames," ",""))="TIPA312MFG")*(_xlpm.filmCosts>0)),1)),0), _xlpm.metluxCost,IFERROR(INDEX([6]HELPER!$E$2:$E$32,MATCH(TRUE,TRIM([6]HELPER!$A$2:$A$32)="MET LUX",0)),IFERROR(INDEX([6]HELPER!$E$2:$E$32,MATCH(TRUE,TRIM([6]HELPER!$B$2:$B$32)="MET LUX",0)),IFERROR(INDEX([6]HELPER!$E$2:$E$32,MATCH(TRUE,TRIM([6]HELPER!$C$2:$C$32)="MET LUX",0)),IFERROR(INDEX([6]HELPER!$E$2:$E$32,MATCH(TRUE,TRIM([6]HELPER!$D$2:$D$32)="MET LUX",0)),0)))), _xlpm.helperCost,IFERROR(INDEX([6]HELPER!$E$2:$E$32,MATCH(TRUE,TRIM([6]HELPER!$A$2:$A$32)=_xlpm.mat,0)),IFERROR(INDEX([6]HELPER!$E$2:$E$32,MATCH(TRUE,TRIM([6]HELPER!$B$2:$B$32)=_xlpm.mat,0)),IFERROR(INDEX([6]HELPER!$E$2:$E$32,MATCH(TRUE,TRIM([6]HELPER!$C$2:$C$32)=_xlpm.mat,0)),IFERROR(INDEX([6]HELPER!$E$2:$E$32,MATCH(TRUE,TRIM([6]HELPER!$D$2:$D$32)=_xlpm.mat,0)),"")))), _xlpm.specialCost,IFERROR(_xlfn.XLOOKUP(_xlpm.mat,[6]HELPER!$CK$2:$CK$105,[6]HELPER!$CO$2:$CO$105,""),""), _xlpm.nkHelperCost,IFERROR(INDEX([6]HELPER!$E$2:$E$32,MATCH(TRUE,TRIM([6]HELPER!$A$2:$A$32)="NK",0)),IFERROR(INDEX([6]HELPER!$E$2:$E$32,MATCH(TRUE,TRIM([6]HELPER!$B$2:$B$32)="NK",0)),IFERROR(INDEX([6]HELPER!$E$2:$E$32,MATCH(TRUE,TRIM([6]HELPER!$C$2:$C$32)="NK",0)),IFERROR(INDEX([6]HELPER!$E$2:$E$32,MATCH(TRUE,TRIM([6]HELPER!$D$2:$D$32)="NK",0)),0)))), _xlpm.baseCost,IF(LEFT(_xlpm.mat,4)="TIPA",IF(_xlpm.finalFilmCost<>"",_xlpm.finalFilmCost,_xlpm.specialCost),_xlpm.helperCost), _xlpm.rawResult,IF(OR(_xlpm.mat="NK",_xlpm.mat="NKR",_xlpm.mat="NVS"),_xlpm.nkHelperCost,IF(_xlpm.baseCost="","",IF(OR(_xlpm.finalFilmCost<>"",LEFT(_xlpm.mat,4)="TIPA"),_xlpm.baseCost,_xlpm.baseCost+_xlpm.euShip))), _xlpm.upliftFilm,ISNUMBER(MATCH(_xlpm.matKey,{"TIPA312MET";"TIPA302FG";"TIPA302FGW";"TIPA306M";"TIPA306W";"TIPA312MFG";"TIPA312MFGW"},0)), _xlpm.rawResult ))} | P8: =IF(OR(C8="",A$3<=0),"",IFERROR(IF(O$3="Europe to US",IF(A$3<500,10,IF(A$3<1000,8,IF(A$3<2500,6,IF(A$3<5000,5,4)))),VLOOKUP(O$3,[6]HELPER!$AF$2:$AH$3,3,FALSE)),0)) | X8: =IF($K8="","",IFERROR($M8*($N8+$P8),"")) | AG8: 🎨 No of colors | AH8: 3-4 | AK8: 🎨 No of colors | AL8: 3-4 | AO8: 🎨 No of colors | AP8: 3-4
A9: =IF(AL13="By Length",IF(AL14<>"",IFERROR(AL14*$M$14*($D9/$J9),""),""),IF(OR(AL13="By Imp",AL13="IMP"),IFERROR(AL41*$M$14*($D9/$J9),""),IF(AL6="","",AL6))) -> 2517.5756 | B9: =AL3 -> 428 | C9: {=IFERROR(_xlfn.LET(_xlpm.lam,TEXT(B9,"0"),_xlpm.thick,AL4,_xlfn.TAKE(_xlfn._xlws.FILTER([6]HELPER!$BW$2:$BW$250,(TEXT([6]HELPER!$BZ$2:$BZ$250,"0")=_xlpm.lam)*([6]HELPER!$CC$2:$CC$250=_xlpm.thick)*([6]HELPER!$BW$2:$BW$250<>""),"No match"),6)),"")} -> NK | D9: =AL5 -> 352 | E9: =IF(D9="","",_xlfn.LET(_xlpm.cap,IF($Q9="Quantum",760,1220),IF(D9+50>_xlpm.cap,"ERROR: Lamination Width > "&_xlpm.cap,D9*MAX(1,MIN(MAX(2,INT(900/D9)),INT((_xlpm.cap-50)/D9)))))) -> 704 | G9: =IF(OR(AL13="IMP",AL13="By Imp",AL13="By Length"),IFERROR(AL16,""),IFERROR(IF(OR(A9="",A9=0,$D9="",$D9=0,$J9="",$M$14="",$M$14=0,A9<=5),"",(A9-5)/$M$14*($J9/$D9)),"")) -> 69696 | H9: =AL7 -> Printed | I9: =IF(H9="Not Printed",0,AL8) -> 3-4 | J9: =IF(C9="","",$E$9+16) -> 720 | K9: {=_xlfn.LET(_xlpm.baseThick,IFERROR(INDEX([6]HELPER!$BX$2:$BX$250,MATCH(1,(TEXT([6]HELPER!$BZ$2:$BZ$250,"0")=TEXT($B$9,"0"))*([6]HELPER!$CC$2:$CC$250=$AL$4)*([6]HELPER!$BW$2:$BW$250=C9),0)),""),IF(_xlpm.baseThick="","",_xlpm.baseThick))} -> 23 | L9: =IFERROR(VLOOKUP(C9,[6]HELPER!$AP$1:$AQ$25,2,FALSE),"") -> 1.44 | M9: =IF(C9="","",IF(ISNUMBER(SEARCH("paper",C9)),42/1000*(J9/1000),IF(OR(L9="",L9=0),"",L9*1000*(K9/1000000)*(J9/1000)))) -> 0.0238464 | N9: {=IF($C9="","",_xlfn.LET( _xlpm.mat,TRIM($C9), _xlpm.matKey,UPPER(SUBSTITUTE(_xlpm.mat," ","")), _xlpm.pr,IFERROR(LOOKUP(2,1/($H$3:H9<>""),$H$3:H9),""), _xlpm.widthActual,IFERROR(LOOKUP(2,1/($E$3:E9<>""),$E$3:E9),$E9), _xlpm.euShip,IFERROR([6]HELPER!$AH$3,0), _xlpm.metSetup,IFERROR([6]HELPER!$CH$2,0), _xlpm.filmNames,[6]!Table1[Film Type], _xlpm.filmCosts,[6]!Table1[For Laminates calculation purposes], _xlpm.printCosts,[6]!Table1[Printing], _xlpm.printWaste,[6]!Table1[Printing Waste], _xlpm.filmCost,IF(LEFT(_xlpm.mat,4)="TIPA",IFERROR(IF(_xlpm.pr="Not Printed",MIN(_xlfn._xlws.FILTER(_xlpm.filmCosts,(UPPER(SUBSTITUTE(_xlpm.filmNames," ",""))=_xlpm.matKey)*(_xlpm.printCosts=0)*(_xlpm.printWaste=0)*(_xlpm.filmCosts>0))),INDEX(_xlfn._xlws.FILTER(_xlpm.filmCosts,(UPPER(SUBSTITUTE(_xlpm.filmNames," ",""))=_xlpm.matKey)*(_xlpm.filmCosts>0)),1)),""),""), _xlpm.summaryNames,"", _xlpm.summaryThick,"", _xlpm.summaryCosts,"", _xlpm.summaryCost,IF(LEFT(_xlpm.mat,4)="TIPA",IFERROR(IF(_xlpm.pr="Not Printed",MIN(_xlfn._xlws.FILTER(_xlpm.summaryCosts,(UPPER(SUBSTITUTE(_xlpm.summaryNames," ",""))=_xlpm.matKey)*(_xlpm.summaryThick=$K9)*(_xlpm.summaryCosts>0))),INDEX(_xlfn._xlws.FILTER(_xlpm.summaryCosts,(UPPER(SUBSTITUTE(_xlpm.summaryNames," ",""))=_xlpm.matKey)*(_xlpm.summaryThick=$K9)*(_xlpm.summaryCosts>0)),1)),""),""), _xlpm.finalFilmCost,IF(_xlpm.filmCost<>"",_xlpm.filmCost,_xlpm.summaryCost), _xlpm.metFilmCost,IFERROR(INDEX(_xlpm.filmCosts,MATCH("TIPA 312 MFG",_xlpm.filmNames,0)),INDEX(_xlpm.filmCosts,1)), _xlpm.tipa312MfgCost,IFERROR(IF(_xlpm.pr="Not Printed",MIN(_xlfn._xlws.FILTER(_xlpm.filmCosts,(UPPER(SUBSTITUTE(_xlpm.filmNames," ",""))="TIPA312MFG")*(_xlpm.printCosts=0)*(_xlpm.printWaste=0)*(_xlpm.filmCosts>0))),INDEX(_xlfn._xlws.FILTER(_xlpm.filmCosts,(UPPER(SUBSTITUTE(_xlpm.filmNames," ",""))="TIPA312MFG")*(_xlpm.filmCosts>0)),1)),0), _xlpm.metluxCost,IFERROR(INDEX([6]HELPER!$E$2:$E$32,MATCH(TRUE,TRIM([6]HELPER!$A$2:$A$32)="MET LUX",0)),IFERROR(INDEX([6]HELPER!$E$2:$E$32,MATCH(TRUE,TRIM([6]HELPER!$B$2:$B$32)="MET LUX",0)),IFERROR(INDEX([6]HELPER!$E$2:$E$32,MATCH(TRUE,TRIM([6]HELPER!$C$2:$C$32)="MET LUX",0)),IFERROR(INDEX([6]HELPER!$E$2:$E$32,MATCH(TRUE,TRIM([6]HELPER!$D$2:$D$32)="MET LUX",0)),0)))), _xlpm.helperCost,IFERROR(INDEX([6]HELPER!$E$2:$E$32,MATCH(TRUE,TRIM([6]HELPER!$A$2:$A$32)=_xlpm.mat,0)),IFERROR(INDEX([6]HELPER!$E$2:$E$32,MATCH(TRUE,TRIM([6]HELPER!$B$2:$B$32)=_xlpm.mat,0)),IFERROR(INDEX([6]HELPER!$E$2:$E$32,MATCH(TRUE,TRIM([6]HELPER!$C$2:$C$32)=_xlpm.mat,0)),IFERROR(INDEX([6]HELPER!$E$2:$E$32,MATCH(TRUE,TRIM([6]HELPER!$D$2:$D$32)=_xlpm.mat,0)),"")))), _xlpm.specialCost,IFERROR(_xlfn.XLOOKUP(_xlpm.mat,[6]HELPER!$CK$2:$CK$105,[6]HELPER!$CO$2:$CO$105,""),""), _xlpm.nkHelperCost,IFERROR(INDEX([6]HELPER!$E$2:$E$32,MATCH(TRUE,TRIM([6]HELPER!$A$2:$A$32)="NK",0)),IFERROR(INDEX([6]HELPER!$E$2:$E$32,MATCH(TRUE,TRIM([6]HELPER!$B$2:$B$32)="NK",0)),IFERROR(INDEX([6]HELPER!$E$2:$E$32,MATCH(TRUE,TRIM([6]HELPER!$C$2:$C$32)="NK",0)),IFERROR(INDEX([6]HELPER!$E$2:$E$32,MATCH(TRUE,TRIM([6]HELPER!$D$2:$D$32)="NK",0)),0)))), _xlpm.baseCost,IF(LEFT(_xlpm.mat,4)="TIPA",IF(_xlpm.finalFilmCost<>"",_xlpm.finalFilmCost,_xlpm.specialCost),_xlpm.helperCost), _xlpm.rawResult,IF(OR(_xlpm.mat="NK",_xlpm.mat="NKR",_xlpm.mat="NVS"),_xlpm.nkHelperCost,IF(_xlpm.baseCost="","",IF(OR(_xlpm.finalFilmCost<>"",LEFT(_xlpm.mat,4)="TIPA"),_xlpm.baseCost,_xlpm.baseCost+_xlpm.euShip))), _xlpm.upliftFilm,ISNUMBER(MATCH(_xlpm.matKey,{"TIPA312MET";"TIPA302FG";"TIPA302FGW";"TIPA306M";"TIPA306W";"TIPA312MFG";"TIPA312MFGW"},0)), _xlpm.rawResult ))} -> 7.95 | O9: =AL11 -> EXW | P9: =IF(OR(C9="",A$9<=0),"",IFERROR(IF(O$9="Europe to US",IF(A$9<500,10,IF(A$9<1000,8,IF(A$9<2500,6,IF(A$9<5000,5,4)))),VLOOKUP(O$9,[6]HELPER!$AF$2:$AH$3,3,FALSE)),0)) -> 0 | Q9: =AL12 -> Marma | R9: {=IF(OR($Q9="",$G9=""),"",IF($J9>IF($Q9="Quantum",760,1220),"Error! lamination width exceeds supplier maximum",_xlfn.LET(_xlpm.struct,$C$9:$C$14,_xlpm.realLayers,SUMPRODUCT(--(_xlpm.struct<>""),--ISERROR(SEARCH("EPOTAL",_xlpm.struct&"")),--ISERROR(SEARCH("BASONAT",_xlpm.struct&"")),--ISERROR(SEARCH("ADH",_xlpm.struct&"")),--ISERROR(SEARCH("HARDENER",_xlpm.struct&""))),_xlpm.lamSteps,MAX(0,_xlpm.realLayers-1),_xlpm.len,$G9,_xlpm.colNum,IF(_xlpm.len<3000,1,IF(_xlpm.len<10000,2,IF(_xlpm.len<25000,3,IF(_xlpm.len<50000,4,IF(_xlpm.len<100000,5,IF(_xlpm.len<250000,6,7)))))),_xlpm.widthRow,IF($E9<900,0,5),_xlpm.supplierRow,IF($Q9="Marma",3,IF(OR($Q9="Bastin",$Q9="Quantum"),13,0)),_xlpm.baseRate,IF(_xlpm.supplierRow=0,"",INDEX('[6]Lmntn & Prntng- Marma & Bastin '!$D$1:$K$22,_xlpm.supplierRow+_xlpm.widthRow,_xlpm.colNum)),IF(_xlpm.realLayers=0,"",_xlpm.baseRate*_xlpm.lamSteps))))} -> 0.16962 | S9: {=IF($Q9="Quantum",IF(OR($Q9="",$I9=0,$I9="0"),"",IF($J9>IF($Q9="Quantum",760,1220),"Error! lamination width exceeds supplier maximum",IF($E9>1200,"Data is missing",_xlfn.LET(_xlpm.len,$G9,_xlpm.colors,$I9,_xlpm.qWidth,IF($E9<=450,450,IF($E9<=760,760,1200)),_xlpm.band,IF(_xlpm.colors=1,"1",IF(OR(_xlpm.colors=2,_xlpm.colors=3),"2-3",IF(OR(_xlpm.colors=4,_xlpm.colors=5),"4-5","6-8"))),_xlpm.widths,'[6]Digital_per_meter- Quantum'!$A$32:$A$91,_xlpm.bands,'[6]Digital_per_meter- Quantum'!$C$32:$C$91,_xlpm.meters,'[6]Digital_per_meter- Quantum'!$D$32:$D$91,_xlpm.rates,'[6]Digital_per_meter- Quantum'!$H$32:$H$91,_xlpm.targetM,IFERROR(MIN(_xlfn._xlws.FILTER(_xlpm.meters,(_xlpm.widths=_xlpm.qWidth)*(_xlpm.bands=_xlpm.band)*(_xlpm.meters>=_xlpm.len))),MAX(_xlfn._xlws.FILTER(_xlpm.meters,(_xlpm.widths=_xlpm.qWidth)*(_xlpm.bands=_xlpm.band)))),INDEX(_xlpm.rates,_xlfn.XMATCH(1,(_xlpm.widths=_xlpm.qWidth)*(_xlpm.bands=_xlpm.band)*(_xlpm.meters=_xlpm.targetM),0))/[6]HELPER!$AK$2)))),IF(OR($Q9="",$I9=0,$I9="0"),"",IF($J9>IF($Q9="Quantum",760,1220),"Error! lamination width exceeds supplier maximum",_xlfn.LET(_xlpm.len,$AL$22,_xlpm.colors,$I9,_xlpm.colNum,IF(_xlpm.len<3000,1,IF(_xlpm.len<10000,2,IF(_xlpm.len<25000,3,IF(_xlpm.len<50000,4,IF(_xlpm.len<100000,5,IF(_xlpm.len<250000,6,IF(_xlpm.len<500000,7,8))))))),_xlpm.widthRow,IF($E9<900,0,5),_xlpm.colorOffset,IF(OR(_xlpm.colors=1,_xlpm.colors=2,_xlpm.colors="1-2"),1,IF(OR(_xlpm.colors=3,_xlpm.colors=4,_xlpm.colors="3-4"),2,IF(OR(_xlpm.colors>=5,_xlpm.colors="5-6",_xlpm.colors="5-8"),3,0))),_xlpm.supplierRow,IF($Q9="Marma",3,IF($Q9="Bastin",13,0)),IF(OR(_xlpm.supplierRow=0,_xlpm.colorOffset=0),"",INDEX('[6]Lmntn & Prntng- Marma & Bastin '!$D$1:$K$22,_xlpm.supplierRow+_xlpm.widthRow+_xlpm.colorOffset,_xlpm.colNum))))))} -> 0.12662 | T9: =IF(OR($S9="",$K9=""),"",IFERROR($S9*(1/$M$14)*($J9/($D9*MAX(1,ROUNDDOWN(760/$D9,0)))),"")) -> 1.7526599 | U9: {=IF($Q9="","",IF($J9>IF($Q9="Quantum",760,1220),"Error! lamination width exceeds supplier maximum",_xlfn.LET(_xlpm.len,$G9,_xlpm.colNum,IF(_xlpm.len<3000,1,IF(_xlpm.len<10000,2,IF(_xlpm.len<25000,3,IF(_xlpm.len<50000,4,IF(_xlpm.len<100000,5,IF(_xlpm.len<250000,6,7)))))),_xlpm.widthRow,IF($E9<900,0,5),_xlpm.supplierRow,IF($Q9="Marma",7,IF(OR($Q9="Bastin",$Q9="Quantum"),17,0)),IF(_xlpm.supplierRow=0,"",INDEX('[6]Lmntn & Prntng- Marma & Bastin '!$D$1:$K$22,_xlpm.supplierRow+_xlpm.widthRow,_xlpm.colNum)))))} -> 0.02352 | V9: =IFERROR(IF(AL23="","",IF($K14>31,(5%+250/$G$9)*AL23,VLOOKUP($K14,[6]HELPER!$BH$3:$BI$5,2,TRUE)*AL23)),"") -> 0.43211138 | W9: =IF(OR($H9<>"Printed",$I9=0,$I9="0"),0,IFERROR(AL23*0.028,0)+IFERROR(AL44,0)) -> 0.39228106 | X9: =IF($K9="","",IFERROR($M9*($N9+$P9),"")) -> 0.18957888 | Y9: =IFERROR((SUM(X9:X14)+SUM(R9:S9,U9))*(1/M14)*(J9/E9)+V9+W9,"") -> 13.314209 | Z9: =IF($M9="","",IFERROR(($N9+$P9)*$M9/$M$14,"")) -> 2.5658156 | AA9: =AL9 -> 1 | AB9: =IF(OR(AL13="IMP",AL13="By Imp"),IFERROR(AL14/AA9,""),"") -> 264000 | AC9: =AL43 -> 0.33333333 | AG9: 🎨 No. of SKUs | AH9: 1 | AK9: 🎨 No. of SKUs | AL9: 1 | AO9: 🎨 No. of SKUs | AP9: 1
C10: TIPA 312 MET | J10: =IF(C10="","",$E$9+16) -> 720 | K10: {=_xlfn.LET(_xlpm.baseThick,IFERROR(INDEX([6]HELPER!$BX$2:$BX$250,MATCH(1,(TEXT([6]HELPER!$BZ$2:$BZ$250,"0")=TEXT($B$9,"0"))*([6]HELPER!$CC$2:$CC$250=$AL$4)*([6]HELPER!$BW$2:$BW$250=C10),0)),""),IF(_xlpm.baseThick="","",_xlpm.baseThick))} -> 25 | L10: =IFERROR(VLOOKUP(C10,[6]HELPER!$AP$1:$AQ$25,2,FALSE),"") -> 1.25 | M10: =IF(C10="","",IF(ISNUMBER(SEARCH("paper",C10)),42/1000*(J10/1000),IF(OR(L10="",L10=0),"",L10*1000*(K10/1000000)*(J10/1000)))) -> 0.0225 | N10: {=IF($C10="","",_xlfn.LET( _xlpm.mat,TRIM($C10), _xlpm.matKey,UPPER(SUBSTITUTE(_xlpm.mat," ","")), _xlpm.pr,IFERROR(LOOKUP(2,1/($H$3:H10<>""),$H$3:H10),""), _xlpm.widthActual,IFERROR(LOOKUP(2,1/($E$3:E10<>""),$E$3:E10),$E10), _xlpm.euShip,IFERROR([6]HELPER!$AH$3,0), _xlpm.metSetup,IFERROR([6]HELPER!$CH$2,0), _xlpm.filmNames,[6]!Table1[Film Type], _xlpm.filmCosts,[6]!Table1[For Laminates calculation purposes], _xlpm.printCosts,[6]!Table1[Printing], _xlpm.printWaste,[6]!Table1[Printing Waste], _xlpm.filmCost,IF(LEFT(_xlpm.mat,4)="TIPA",IFERROR(IF(_xlpm.pr="Not Printed",MIN(_xlfn._xlws.FILTER(_xlpm.filmCosts,(UPPER(SUBSTITUTE(_xlpm.filmNames," ",""))=_xlpm.matKey)*(_xlpm.printCosts=0)*(_xlpm.printWaste=0)*(_xlpm.filmCosts>0))),INDEX(_xlfn._xlws.FILTER(_xlpm.filmCosts,(UPPER(SUBSTITUTE(_xlpm.filmNames," ",""))=_xlpm.matKey)*(_xlpm.filmCosts>0)),1)),""),""), _xlpm.summaryNames,"", _xlpm.summaryThick,"", _xlpm.summaryCosts,"", _xlpm.summaryCost,IF(LEFT(_xlpm.mat,4)="TIPA",IFERROR(IF(_xlpm.pr="Not Printed",MIN(_xlfn._xlws.FILTER(_xlpm.summaryCosts,(UPPER(SUBSTITUTE(_xlpm.summaryNames," ",""))=_xlpm.matKey)*(_xlpm.summaryThick=$K10)*(_xlpm.summaryCosts>0))),INDEX(_xlfn._xlws.FILTER(_xlpm.summaryCosts,(UPPER(SUBSTITUTE(_xlpm.summaryNames," ",""))=_xlpm.matKey)*(_xlpm.summaryThick=$K10)*(_xlpm.summaryCosts>0)),1)),""),""), _xlpm.finalFilmCost,IF(_xlpm.filmCost<>"",_xlpm.filmCost,_xlpm.summaryCost), _xlpm.metFilmCost,IFERROR(INDEX(_xlpm.filmCosts,MATCH("TIPA 312 MFG",_xlpm.filmNames,0)),INDEX(_xlpm.filmCosts,1)), _xlpm.tipa312MfgCost,IFERROR(IF(_xlpm.pr="Not Printed",MIN(_xlfn._xlws.FILTER(_xlpm.filmCosts,(UPPER(SUBSTITUTE(_xlpm.filmNames," ",""))="TIPA312MFG")*(_xlpm.printCosts=0)*(_xlpm.printWaste=0)*(_xlpm.filmCosts>0))),INDEX(_xlfn._xlws.FILTER(_xlpm.filmCosts,(UPPER(SUBSTITUTE(_xlpm.filmNames," ",""))="TIPA312MFG")*(_xlpm.filmCosts>0)),1)),0), _xlpm.metluxCost,IFERROR(INDEX([6]HELPER!$E$2:$E$32,MATCH(TRUE,TRIM([6]HELPER!$A$2:$A$32)="MET LUX",0)),IFERROR(INDEX([6]HELPER!$E$2:$E$32,MATCH(TRUE,TRIM([6]HELPER!$B$2:$B$32)="MET LUX",0)),IFERROR(INDEX([6]HELPER!$E$2:$E$32,MATCH(TRUE,TRIM([6]HELPER!$C$2:$C$32)="MET LUX",0)),IFERROR(INDEX([6]HELPER!$E$2:$E$32,MATCH(TRUE,TRIM([6]HELPER!$D$2:$D$32)="MET LUX",0)),0)))), _xlpm.helperCost,IFERROR(INDEX([6]HELPER!$E$2:$E$32,MATCH(TRUE,TRIM([6]HELPER!$A$2:$A$32)=_xlpm.mat,0)),IFERROR(INDEX([6]HELPER!$E$2:$E$32,MATCH(TRUE,TRIM([6]HELPER!$B$2:$B$32)=_xlpm.mat,0)),IFERROR(INDEX([6]HELPER!$E$2:$E$32,MATCH(TRUE,TRIM([6]HELPER!$C$2:$C$32)=_xlpm.mat,0)),IFERROR(INDEX([6]HELPER!$E$2:$E$32,MATCH(TRUE,TRIM([6]HELPER!$D$2:$D$32)=_xlpm.mat,0)),"")))), _xlpm.specialCost,IFERROR(_xlfn.XLOOKUP(_xlpm.mat,[6]HELPER!$CK$2:$CK$105,[6]HELPER!$CO$2:$CO$105,""),""), _xlpm.nkHelperCost,IFERROR(INDEX([6]HELPER!$E$2:$E$32,MATCH(TRUE,TRIM([6]HELPER!$A$2:$A$32)="NK",0)),IFERROR(INDEX([6]HELPER!$E$2:$E$32,MATCH(TRUE,TRIM([6]HELPER!$B$2:$B$32)="NK",0)),IFERROR(INDEX([6]HELPER!$E$2:$E$32,MATCH(TRUE,TRIM([6]HELPER!$C$2:$C$32)="NK",0)),IFERROR(INDEX([6]HELPER!$E$2:$E$32,MATCH(TRUE,TRIM([6]HELPER!$D$2:$D$32)="NK",0)),0)))), _xlpm.baseCost,IF(LEFT(_xlpm.mat,4)="TIPA",IF(_xlpm.finalFilmCost<>"",_xlpm.finalFilmCost,_xlpm.specialCost),_xlpm.helperCost), _xlpm.rawResult,IF(OR(_xlpm.mat="NK",_xlpm.mat="NKR",_xlpm.mat="NVS"),_xlpm.nkHelperCost,IF(_xlpm.baseCost="","",IF(OR(_xlpm.finalFilmCost<>"",LEFT(_xlpm.mat,4)="TIPA"),_xlpm.baseCost,_xlpm.baseCost+_xlpm.euShip))), _xlpm.upliftFilm,ISNUMBER(MATCH(_xlpm.matKey,{"TIPA312MET";"TIPA302FG";"TIPA302FGW";"TIPA306M";"TIPA306W";"TIPA312MFG";"TIPA312MFGW"},0)), _xlpm.rawResult ))} -> 8.1897203 | P10: =IF(OR(C10="",A$9<=0),"",IFERROR(IF(O$9="Europe to US",IF(A$9<500,10,IF(A$9<1000,8,IF(A$9<2500,6,IF(A$9<5000,5,4)))),VLOOKUP(O$9,[6]HELPER!$AF$2:$AH$3,3,FALSE)),0)) -> 0 | X10: =IF($K10="","",IFERROR($M10*($N10+$P10),"")) -> 0.18426871 | Z10: =IF($M10="","",IFERROR(($N10+$P10)*$M10/$M$14,"")) -> 2.4939462 | AG10: 🔄 Core size | AH10: 6'' | AK10: 🔄 Core size | AL10: 6'' | AO10: 🔄 Core size | AP10: 6'' | AS10: =100/(1-15%) -> 117.64706
C11: TIPA 312 MET | J11: =IF(C11="","",$E$9+16) -> 720 | K11: {=_xlfn.LET(_xlpm.baseThick,IFERROR(INDEX([6]HELPER!$BX$2:$BX$250,MATCH(1,(TEXT([6]HELPER!$BZ$2:$BZ$250,"0")=TEXT($B$9,"0"))*([6]HELPER!$CC$2:$CC$250=$AL$4)*([6]HELPER!$BW$2:$BW$250=C11),0)),""),IF(_xlpm.baseThick="","",_xlpm.baseThick))} -> 25 | L11: =IFERROR(VLOOKUP(C11,[6]HELPER!$AP$1:$AQ$25,2,FALSE),"") -> 1.25 | M11: =IF(C11="","",IF(ISNUMBER(SEARCH("paper",C11)),42/1000*(J11/1000),IF(OR(L11="",L11=0),"",L11*1000*(K11/1000000)*(J11/1000)))) -> 0.0225 | N11: {=IF($C11="","",_xlfn.LET( _xlpm.mat,TRIM($C11), _xlpm.matKey,UPPER(SUBSTITUTE(_xlpm.mat," ","")), _xlpm.pr,IFERROR(LOOKUP(2,1/($H$3:H11<>""),$H$3:H11),""), _xlpm.widthActual,IFERROR(LOOKUP(2,1/($E$3:E11<>""),$E$3:E11),$E11), _xlpm.euShip,IFERROR([6]HELPER!$AH$3,0), _xlpm.metSetup,IFERROR([6]HELPER!$CH$2,0), _xlpm.filmNames,[6]!Table1[Film Type], _xlpm.filmCosts,[6]!Table1[For Laminates calculation purposes], _xlpm.printCosts,[6]!Table1[Printing], _xlpm.printWaste,[6]!Table1[Printing Waste], _xlpm.filmCost,IF(LEFT(_xlpm.mat,4)="TIPA",IFERROR(IF(_xlpm.pr="Not Printed",MIN(_xlfn._xlws.FILTER(_xlpm.filmCosts,(UPPER(SUBSTITUTE(_xlpm.filmNames," ",""))=_xlpm.matKey)*(_xlpm.printCosts=0)*(_xlpm.printWaste=0)*(_xlpm.filmCosts>0))),INDEX(_xlfn._xlws.FILTER(_xlpm.filmCosts,(UPPER(SUBSTITUTE(_xlpm.filmNames," ",""))=_xlpm.matKey)*(_xlpm.filmCosts>0)),1)),""),""), _xlpm.summaryNames,"", _xlpm.summaryThick,"", _xlpm.summaryCosts,"", _xlpm.summaryCost,IF(LEFT(_xlpm.mat,4)="TIPA",IFERROR(IF(_xlpm.pr="Not Printed",MIN(_xlfn._xlws.FILTER(_xlpm.summaryCosts,(UPPER(SUBSTITUTE(_xlpm.summaryNames," ",""))=_xlpm.matKey)*(_xlpm.summaryThick=$K11)*(_xlpm.summaryCosts>0))),INDEX(_xlfn._xlws.FILTER(_xlpm.summaryCosts,(UPPER(SUBSTITUTE(_xlpm.summaryNames," ",""))=_xlpm.matKey)*(_xlpm.summaryThick=$K11)*(_xlpm.summaryCosts>0)),1)),""),""), _xlpm.finalFilmCost,IF(_xlpm.filmCost<>"",_xlpm.filmCost,_xlpm.summaryCost), _xlpm.metFilmCost,IFERROR(INDEX(_xlpm.filmCosts,MATCH("TIPA 312 MFG",_xlpm.filmNames,0)),INDEX(_xlpm.filmCosts,1)), _xlpm.tipa312MfgCost,IFERROR(IF(_xlpm.pr="Not Printed",MIN(_xlfn._xlws.FILTER(_xlpm.filmCosts,(UPPER(SUBSTITUTE(_xlpm.filmNames," ",""))="TIPA312MFG")*(_xlpm.printCosts=0)*(_xlpm.printWaste=0)*(_xlpm.filmCosts>0))),INDEX(_xlfn._xlws.FILTER(_xlpm.filmCosts,(UPPER(SUBSTITUTE(_xlpm.filmNames," ",""))="TIPA312MFG")*(_xlpm.filmCosts>0)),1)),0), _xlpm.metluxCost,IFERROR(INDEX([6]HELPER!$E$2:$E$32,MATCH(TRUE,TRIM([6]HELPER!$A$2:$A$32)="MET LUX",0)),IFERROR(INDEX([6]HELPER!$E$2:$E$32,MATCH(TRUE,TRIM([6]HELPER!$B$2:$B$32)="MET LUX",0)),IFERROR(INDEX([6]HELPER!$E$2:$E$32,MATCH(TRUE,TRIM([6]HELPER!$C$2:$C$32)="MET LUX",0)),IFERROR(INDEX([6]HELPER!$E$2:$E$32,MATCH(TRUE,TRIM([6]HELPER!$D$2:$D$32)="MET LUX",0)),0)))), _xlpm.helperCost,IFERROR(INDEX([6]HELPER!$E$2:$E$32,MATCH(TRUE,TRIM([6]HELPER!$A$2:$A$32)=_xlpm.mat,0)),IFERROR(INDEX([6]HELPER!$E$2:$E$32,MATCH(TRUE,TRIM([6]HELPER!$B$2:$B$32)=_xlpm.mat,0)),IFERROR(INDEX([6]HELPER!$E$2:$E$32,MATCH(TRUE,TRIM([6]HELPER!$C$2:$C$32)=_xlpm.mat,0)),IFERROR(INDEX([6]HELPER!$E$2:$E$32,MATCH(TRUE,TRIM([6]HELPER!$D$2:$D$32)=_xlpm.mat,0)),"")))), _xlpm.specialCost,IFERROR(_xlfn.XLOOKUP(_xlpm.mat,[6]HELPER!$CK$2:$CK$105,[6]HELPER!$CO$2:$CO$105,""),""), _xlpm.nkHelperCost,IFERROR(INDEX([6]HELPER!$E$2:$E$32,MATCH(TRUE,TRIM([6]HELPER!$A$2:$A$32)="NK",0)),IFERROR(INDEX([6]HELPER!$E$2:$E$32,MATCH(TRUE,TRIM([6]HELPER!$B$2:$B$32)="NK",0)),IFERROR(INDEX([6]HELPER!$E$2:$E$32,MATCH(TRUE,TRIM([6]HELPER!$C$2:$C$32)="NK",0)),IFERROR(INDEX([6]HELPER!$E$2:$E$32,MATCH(TRUE,TRIM([6]HELPER!$D$2:$D$32)="NK",0)),0)))), _xlpm.baseCost,IF(LEFT(_xlpm.mat,4)="TIPA",IF(_xlpm.finalFilmCost<>"",_xlpm.finalFilmCost,_xlpm.specialCost),_xlpm.helperCost), _xlpm.rawResult,IF(OR(_xlpm.mat="NK",_xlpm.mat="NKR",_xlpm.mat="NVS"),_xlpm.nkHelperCost,IF(_xlpm.baseCost="","",IF(OR(_xlpm.finalFilmCost<>"",LEFT(_xlpm.mat,4)="TIPA"),_xlpm.baseCost,_xlpm.baseCost+_xlpm.euShip))), _xlpm.upliftFilm,ISNUMBER(MATCH(_xlpm.matKey,{"TIPA312MET";"TIPA302FG";"TIPA302FGW";"TIPA306M";"TIPA306W";"TIPA312MFG";"TIPA312MFGW"},0)), _xlpm.rawResult ))} -> 8.1897203 | P11: =IF(OR(C11="",A$9<=0),"",IFERROR(IF(O$9="Europe to US",IF(A$9<500,10,IF(A$9<1000,8,IF(A$9<2500,6,IF(A$9<5000,5,4)))),VLOOKUP(O$9,[6]HELPER!$AF$2:$AH$3,3,FALSE)),0)) -> 0 | X11: =IF($K11="","",IFERROR($M11*($N11+$P11),"")) -> 0.18426871 | Z11: =IF($M11="","",IFERROR(($N11+$P11)*$M11/$M$14,"")) -> 2.4939462 | AG11: 🚚 Shipping Terms | AH11: EXW | AK11: 🚚 Shipping Terms | AL11: EXW | AO11: 🚚 Shipping Terms | AP11: EXW
C12: RM G Epotal ECO 3675 | J12: =IF(C12="","",$E$9+16) -> 720 | K12: {=_xlfn.LET(_xlpm.baseThick,IFERROR(INDEX([6]HELPER!$BX$2:$BX$250,MATCH(1,(TEXT([6]HELPER!$BZ$2:$BZ$250,"0")=TEXT($B$9,"0"))*([6]HELPER!$CC$2:$CC$250=$AL$4)*([6]HELPER!$BW$2:$BW$250=C12),0)),""),IF(_xlpm.baseThick="","",_xlpm.baseThick))} -> 7 | L12: =IFERROR(VLOOKUP(C12,[6]HELPER!$AP$1:$AQ$25,2,FALSE),"") -> 1 | M12: =IF(C12="","",IF(ISNUMBER(SEARCH("paper",C12)),42/1000*(J12/1000),IF(OR(L12="",L12=0),"",L12*1000*(K12/1000000)*(J12/1000)))) -> 0.00504 | N12: {=IF($C12="","",_xlfn.LET( _xlpm.mat,TRIM($C12), _xlpm.matKey,UPPER(SUBSTITUTE(_xlpm.mat," ","")), _xlpm.pr,IFERROR(LOOKUP(2,1/($H$3:H12<>""),$H$3:H12),""), _xlpm.widthActual,IFERROR(LOOKUP(2,1/($E$3:E12<>""),$E$3:E12),$E12), _xlpm.euShip,IFERROR([6]HELPER!$AH$3,0), _xlpm.metSetup,IFERROR([6]HELPER!$CH$2,0), _xlpm.filmNames,[6]!Table1[Film Type], _xlpm.filmCosts,[6]!Table1[For Laminates calculation purposes], _xlpm.printCosts,[6]!Table1[Printing], _xlpm.printWaste,[6]!Table1[Printing Waste], _xlpm.filmCost,IF(LEFT(_xlpm.mat,4)="TIPA",IFERROR(IF(_xlpm.pr="Not Printed",MIN(_xlfn._xlws.FILTER(_xlpm.filmCosts,(UPPER(SUBSTITUTE(_xlpm.filmNames," ",""))=_xlpm.matKey)*(_xlpm.printCosts=0)*(_xlpm.printWaste=0)*(_xlpm.filmCosts>0))),INDEX(_xlfn._xlws.FILTER(_xlpm.filmCosts,(UPPER(SUBSTITUTE(_xlpm.filmNames," ",""))=_xlpm.matKey)*(_xlpm.filmCosts>0)),1)),""),""), _xlpm.summaryNames,"", _xlpm.summaryThick,"", _xlpm.summaryCosts,"", _xlpm.summaryCost,IF(LEFT(_xlpm.mat,4)="TIPA",IFERROR(IF(_xlpm.pr="Not Printed",MIN(_xlfn._xlws.FILTER(_xlpm.summaryCosts,(UPPER(SUBSTITUTE(_xlpm.summaryNames," ",""))=_xlpm.matKey)*(_xlpm.summaryThick=$K12)*(_xlpm.summaryCosts>0))),INDEX(_xlfn._xlws.FILTER(_xlpm.summaryCosts,(UPPER(SUBSTITUTE(_xlpm.summaryNames," ",""))=_xlpm.matKey)*(_xlpm.summaryThick=$K12)*(_xlpm.summaryCosts>0)),1)),""),""), _xlpm.finalFilmCost,IF(_xlpm.filmCost<>"",_xlpm.filmCost,_xlpm.summaryCost), _xlpm.metFilmCost,IFERROR(INDEX(_xlpm.filmCosts,MATCH("TIPA 312 MFG",_xlpm.filmNames,0)),INDEX(_xlpm.filmCosts,1)), _xlpm.tipa312MfgCost,IFERROR(IF(_xlpm.pr="Not Printed",MIN(_xlfn._xlws.FILTER(_xlpm.filmCosts,(UPPER(SUBSTITUTE(_xlpm.filmNames," ",""))="TIPA312MFG")*(_xlpm.printCosts=0)*(_xlpm.printWaste=0)*(_xlpm.filmCosts>0))),INDEX(_xlfn._xlws.FILTER(_xlpm.filmCosts,(UPPER(SUBSTITUTE(_xlpm.filmNames," ",""))="TIPA312MFG")*(_xlpm.filmCosts>0)),1)),0), _xlpm.metluxCost,IFERROR(INDEX([6]HELPER!$E$2:$E$32,MATCH(TRUE,TRIM([6]HELPER!$A$2:$A$32)="MET LUX",0)),IFERROR(INDEX([6]HELPER!$E$2:$E$32,MATCH(TRUE,TRIM([6]HELPER!$B$2:$B$32)="MET LUX",0)),IFERROR(INDEX([6]HELPER!$E$2:$E$32,MATCH(TRUE,TRIM([6]HELPER!$C$2:$C$32)="MET LUX",0)),IFERROR(INDEX([6]HELPER!$E$2:$E$32,MATCH(TRUE,TRIM([6]HELPER!$D$2:$D$32)="MET LUX",0)),0)))), _xlpm.helperCost,IFERROR(INDEX([6]HELPER!$E$2:$E$32,MATCH(TRUE,TRIM([6]HELPER!$A$2:$A$32)=_xlpm.mat,0)),IFERROR(INDEX([6]HELPER!$E$2:$E$32,MATCH(TRUE,TRIM([6]HELPER!$B$2:$B$32)=_xlpm.mat,0)),IFERROR(INDEX([6]HELPER!$E$2:$E$32,MATCH(TRUE,TRIM([6]HELPER!$C$2:$C$32)=_xlpm.mat,0)),IFERROR(INDEX([6]HELPER!$E$2:$E$32,MATCH(TRUE,TRIM([6]HELPER!$D$2:$D$32)=_xlpm.mat,0)),"")))), _xlpm.specialCost,IFERROR(_xlfn.XLOOKUP(_xlpm.mat,[6]HELPER!$CK$2:$CK$105,[6]HELPER!$CO$2:$CO$105,""),""), _xlpm.nkHelperCost,IFERROR(INDEX([6]HELPER!$E$2:$E$32,MATCH(TRUE,TRIM([6]HELPER!$A$2:$A$32)="NK",0)),IFERROR(INDEX([6]HELPER!$E$2:$E$32,MATCH(TRUE,TRIM([6]HELPER!$B$2:$B$32)="NK",0)),IFERROR(INDEX([6]HELPER!$E$2:$E$32,MATCH(TRUE,TRIM([6]HELPER!$C$2:$C$32)="NK",0)),IFERROR(INDEX([6]HELPER!$E$2:$E$32,MATCH(TRUE,TRIM([6]HELPER!$D$2:$D$32)="NK",0)),0)))), _xlpm.baseCost,IF(LEFT(_xlpm.mat,4)="TIPA",IF(_xlpm.finalFilmCost<>"",_xlpm.finalFilmCost,_xlpm.specialCost),_xlpm.helperCost), _xlpm.rawResult,IF(OR(_xlpm.mat="NK",_xlpm.mat="NKR",_xlpm.mat="NVS"),_xlpm.nkHelperCost,IF(_xlpm.baseCost="","",IF(OR(_xlpm.finalFilmCost<>"",LEFT(_xlpm.mat,4)="TIPA"),_xlpm.baseCost,_xlpm.baseCost+_xlpm.euShip))), _xlpm.upliftFilm,ISNUMBER(MATCH(_xlpm.matKey,{"TIPA312MET";"TIPA302FG";"TIPA302FGW";"TIPA306M";"TIPA306W";"TIPA312MFG";"TIPA312MFGW"},0)), _xlpm.rawResult ))} -> 4.85 | P12: =IF(OR(C12="",A$9<=0),"",IFERROR(IF(O$9="Europe to US",IF(A$9<500,10,IF(A$9<1000,8,IF(A$9<2500,6,IF(A$9<5000,5,4)))),VLOOKUP(O$9,[6]HELPER!$AF$2:$AH$3,3,FALSE)),0)) -> 0 | X12: =IF($K12="","",IFERROR($M12*($N12+$P12),"")) -> 0.024444 | Z12: =IF($M12="","",IFERROR(($N12+$P12)*$M12/$M$14,"")) -> 0.3308322 | AG12: 💼 Producer | AH12: Marma | AK12: 💼 Producer | AL12: Marma | AO12: 💼 Producer | AP12: Marma
J13: =IF(C13="","",$E$9+16) | K13: {=_xlfn.LET(_xlpm.baseThick,IFERROR(INDEX([6]HELPER!$BX$2:$BX$250,MATCH(1,(TEXT([6]HELPER!$BZ$2:$BZ$250,"0")=TEXT($B$9,"0"))*([6]HELPER!$CC$2:$CC$250=$AL$4)*([6]HELPER!$BW$2:$BW$250=C13),0)),""),IF(_xlpm.baseThick="","",_xlpm.baseThick))} | L13: =IFERROR(VLOOKUP(C13,[6]HELPER!$AP$1:$AQ$25,2,FALSE),"") | M13: =IF(C13="","",IF(ISNUMBER(SEARCH("paper",C13)),42/1000*(J13/1000),IF(OR(L13="",L13=0),"",L13*1000*(K13/1000000)*(J13/1000)))) | N13: {=IF($C13="","",_xlfn.LET( _xlpm.mat,TRIM($C13), _xlpm.matKey,UPPER(SUBSTITUTE(_xlpm.mat," ","")), _xlpm.pr,IFERROR(LOOKUP(2,1/($H$3:H13<>""),$H$3:H13),""), _xlpm.widthActual,IFERROR(LOOKUP(2,1/($E$3:E13<>""),$E$3:E13),$E13), _xlpm.euShip,IFERROR([6]HELPER!$AH$3,0), _xlpm.metSetup,IFERROR([6]HELPER!$CH$2,0), _xlpm.filmNames,[6]!Table1[Film Type], _xlpm.filmCosts,[6]!Table1[For Laminates calculation purposes], _xlpm.printCosts,[6]!Table1[Printing], _xlpm.printWaste,[6]!Table1[Printing Waste], _xlpm.filmCost,IF(LEFT(_xlpm.mat,4)="TIPA",IFERROR(IF(_xlpm.pr="Not Printed",MIN(_xlfn._xlws.FILTER(_xlpm.filmCosts,(UPPER(SUBSTITUTE(_xlpm.filmNames," ",""))=_xlpm.matKey)*(_xlpm.printCosts=0)*(_xlpm.printWaste=0)*(_xlpm.filmCosts>0))),INDEX(_xlfn._xlws.FILTER(_xlpm.filmCosts,(UPPER(SUBSTITUTE(_xlpm.filmNames," ",""))=_xlpm.matKey)*(_xlpm.filmCosts>0)),1)),""),""), _xlpm.summaryNames,"", _xlpm.summaryThick,"", _xlpm.summaryCosts,"", _xlpm.summaryCost,IF(LEFT(_xlpm.mat,4)="TIPA",IFERROR(IF(_xlpm.pr="Not Printed",MIN(_xlfn._xlws.FILTER(_xlpm.summaryCosts,(UPPER(SUBSTITUTE(_xlpm.summaryNames," ",""))=_xlpm.matKey)*(_xlpm.summaryThick=$K13)*(_xlpm.summaryCosts>0))),INDEX(_xlfn._xlws.FILTER(_xlpm.summaryCosts,(UPPER(SUBSTITUTE(_xlpm.summaryNames," ",""))=_xlpm.matKey)*(_xlpm.summaryThick=$K13)*(_xlpm.summaryCosts>0)),1)),""),""), _xlpm.finalFilmCost,IF(_xlpm.filmCost<>"",_xlpm.filmCost,_xlpm.summaryCost), _xlpm.metFilmCost,IFERROR(INDEX(_xlpm.filmCosts,MATCH("TIPA 312 MFG",_xlpm.filmNames,0)),INDEX(_xlpm.filmCosts,1)), _xlpm.tipa312MfgCost,IFERROR(IF(_xlpm.pr="Not Printed",MIN(_xlfn._xlws.FILTER(_xlpm.filmCosts,(UPPER(SUBSTITUTE(_xlpm.filmNames," ",""))="TIPA312MFG")*(_xlpm.printCosts=0)*(_xlpm.printWaste=0)*(_xlpm.filmCosts>0))),INDEX(_xlfn._xlws.FILTER(_xlpm.filmCosts,(UPPER(SUBSTITUTE(_xlpm.filmNames," ",""))="TIPA312MFG")*(_xlpm.filmCosts>0)),1)),0), _xlpm.metluxCost,IFERROR(INDEX([6]HELPER!$E$2:$E$32,MATCH(TRUE,TRIM([6]HELPER!$A$2:$A$32)="MET LUX",0)),IFERROR(INDEX([6]HELPER!$E$2:$E$32,MATCH(TRUE,TRIM([6]HELPER!$B$2:$B$32)="MET LUX",0)),IFERROR(INDEX([6]HELPER!$E$2:$E$32,MATCH(TRUE,TRIM([6]HELPER!$C$2:$C$32)="MET LUX",0)),IFERROR(INDEX([6]HELPER!$E$2:$E$32,MATCH(TRUE,TRIM([6]HELPER!$D$2:$D$32)="MET LUX",0)),0)))), _xlpm.helperCost,IFERROR(INDEX([6]HELPER!$E$2:$E$32,MATCH(TRUE,TRIM([6]HELPER!$A$2:$A$32)=_xlpm.mat,0)),IFERROR(INDEX([6]HELPER!$E$2:$E$32,MATCH(TRUE,TRIM([6]HELPER!$B$2:$B$32)=_xlpm.mat,0)),IFERROR(INDEX([6]HELPER!$E$2:$E$32,MATCH(TRUE,TRIM([6]HELPER!$C$2:$C$32)=_xlpm.mat,0)),IFERROR(INDEX([6]HELPER!$E$2:$E$32,MATCH(TRUE,TRIM([6]HELPER!$D$2:$D$32)=_xlpm.mat,0)),"")))), _xlpm.specialCost,IFERROR(_xlfn.XLOOKUP(_xlpm.mat,[6]HELPER!$CK$2:$CK$105,[6]HELPER!$CO$2:$CO$105,""),""), _xlpm.nkHelperCost,IFERROR(INDEX([6]HELPER!$E$2:$E$32,MATCH(TRUE,TRIM([6]HELPER!$A$2:$A$32)="NK",0)),IFERROR(INDEX([6]HELPER!$E$2:$E$32,MATCH(TRUE,TRIM([6]HELPER!$B$2:$B$32)="NK",0)),IFERROR(INDEX([6]HELPER!$E$2:$E$32,MATCH(TRUE,TRIM([6]HELPER!$C$2:$C$32)="NK",0)),IFERROR(INDEX([6]HELPER!$E$2:$E$32,MATCH(TRUE,TRIM([6]HELPER!$D$2:$D$32)="NK",0)),0)))), _xlpm.baseCost,IF(LEFT(_xlpm.mat,4)="TIPA",IF(_xlpm.finalFilmCost<>"",_xlpm.finalFilmCost,_xlpm.specialCost),_xlpm.helperCost), _xlpm.rawResult,IF(OR(_xlpm.mat="NK",_xlpm.mat="NKR",_xlpm.mat="NVS"),_xlpm.nkHelperCost,IF(_xlpm.baseCost="","",IF(OR(_xlpm.finalFilmCost<>"",LEFT(_xlpm.mat,4)="TIPA"),_xlpm.baseCost,_xlpm.baseCost+_xlpm.euShip))), _xlpm.upliftFilm,ISNUMBER(MATCH(_xlpm.matKey,{"TIPA312MET";"TIPA302FG";"TIPA302FGW";"TIPA306M";"TIPA306W";"TIPA312MFG";"TIPA312MFGW"},0)), _xlpm.rawResult ))} | P13: =IF(OR(C13="",A$9<=0),"",IFERROR(IF(O$9="Europe to US",IF(A$9<500,10,IF(A$9<1000,8,IF(A$9<2500,6,IF(A$9<5000,5,4)))),VLOOKUP(O$9,[6]HELPER!$AF$2:$AH$3,3,FALSE)),0)) | X13: =IF($K13="","",IFERROR($M13*($N13+$P13),"")) | AG13: ⚙️ Units | AH13: By Imp | AK13: ⚙️ Units | AL13: By Imp | AO13: ⚙️ Units | AP13: By Imp
J14: =IF(C14="","",$E$9+16) | K14: =AL4 -> 80 | L14: =IFERROR(VLOOKUP(C14,[6]HELPER!$AP$1:$AQ$25,2,FALSE),"") | M14: =SUM(M9:M13) -> 0.0738864 | N14: {=IF($C14="","",_xlfn.LET( _xlpm.mat,TRIM($C14), _xlpm.matKey,UPPER(SUBSTITUTE(_xlpm.mat," ","")), _xlpm.pr,IFERROR(LOOKUP(2,1/($H$3:H14<>""),$H$3:H14),""), _xlpm.widthActual,IFERROR(LOOKUP(2,1/($E$3:E14<>""),$E$3:E14),$E14), _xlpm.euShip,IFERROR([6]HELPER!$AH$3,0), _xlpm.metSetup,IFERROR([6]HELPER!$CH$2,0), _xlpm.filmNames,[6]!Table1[Film Type], _xlpm.filmCosts,[6]!Table1[For Laminates calculation purposes], _xlpm.printCosts,[6]!Table1[Printing], _xlpm.printWaste,[6]!Table1[Printing Waste], _xlpm.filmCost,IF(LEFT(_xlpm.mat,4)="TIPA",IFERROR(IF(_xlpm.pr="Not Printed",MIN(_xlfn._xlws.FILTER(_xlpm.filmCosts,(UPPER(SUBSTITUTE(_xlpm.filmNames," ",""))=_xlpm.matKey)*(_xlpm.printCosts=0)*(_xlpm.printWaste=0)*(_xlpm.filmCosts>0))),INDEX(_xlfn._xlws.FILTER(_xlpm.filmCosts,(UPPER(SUBSTITUTE(_xlpm.filmNames," ",""))=_xlpm.matKey)*(_xlpm.filmCosts>0)),1)),""),""), _xlpm.summaryNames,"", _xlpm.summaryThick,"", _xlpm.summaryCosts,"", _xlpm.summaryCost,IF(LEFT(_xlpm.mat,4)="TIPA",IFERROR(IF(_xlpm.pr="Not Printed",MIN(_xlfn._xlws.FILTER(_xlpm.summaryCosts,(UPPER(SUBSTITUTE(_xlpm.summaryNames," ",""))=_xlpm.matKey)*(_xlpm.summaryThick=$K14)*(_xlpm.summaryCosts>0))),INDEX(_xlfn._xlws.FILTER(_xlpm.summaryCosts,(UPPER(SUBSTITUTE(_xlpm.summaryNames," ",""))=_xlpm.matKey)*(_xlpm.summaryThick=$K14)*(_xlpm.summaryCosts>0)),1)),""),""), _xlpm.finalFilmCost,IF(_xlpm.filmCost<>"",_xlpm.filmCost,_xlpm.summaryCost), _xlpm.metFilmCost,IFERROR(INDEX(_xlpm.filmCosts,MATCH("TIPA 312 MFG",_xlpm.filmNames,0)),INDEX(_xlpm.filmCosts,1)), _xlpm.tipa312MfgCost,IFERROR(IF(_xlpm.pr="Not Printed",MIN(_xlfn._xlws.FILTER(_xlpm.filmCosts,(UPPER(SUBSTITUTE(_xlpm.filmNames," ",""))="TIPA312MFG")*(_xlpm.printCosts=0)*(_xlpm.printWaste=0)*(_xlpm.filmCosts>0))),INDEX(_xlfn._xlws.FILTER(_xlpm.filmCosts,(UPPER(SUBSTITUTE(_xlpm.filmNames," ",""))="TIPA312MFG")*(_xlpm.filmCosts>0)),1)),0), _xlpm.metluxCost,IFERROR(INDEX([6]HELPER!$E$2:$E$32,MATCH(TRUE,TRIM([6]HELPER!$A$2:$A$32)="MET LUX",0)),IFERROR(INDEX([6]HELPER!$E$2:$E$32,MATCH(TRUE,TRIM([6]HELPER!$B$2:$B$32)="MET LUX",0)),IFERROR(INDEX([6]HELPER!$E$2:$E$32,MATCH(TRUE,TRIM([6]HELPER!$C$2:$C$32)="MET LUX",0)),IFERROR(INDEX([6]HELPER!$E$2:$E$32,MATCH(TRUE,TRIM([6]HELPER!$D$2:$D$32)="MET LUX",0)),0)))), _xlpm.helperCost,IFERROR(INDEX([6]HELPER!$E$2:$E$32,MATCH(TRUE,TRIM([6]HELPER!$A$2:$A$32)=_xlpm.mat,0)),IFERROR(INDEX([6]HELPER!$E$2:$E$32,MATCH(TRUE,TRIM([6]HELPER!$B$2:$B$32)=_xlpm.mat,0)),IFERROR(INDEX([6]HELPER!$E$2:$E$32,MATCH(TRUE,TRIM([6]HELPER!$C$2:$C$32)=_xlpm.mat,0)),IFERROR(INDEX([6]HELPER!$E$2:$E$32,MATCH(TRUE,TRIM([6]HELPER!$D$2:$D$32)=_xlpm.mat,0)),"")))), _xlpm.specialCost,IFERROR(_xlfn.XLOOKUP(_xlpm.mat,[6]HELPER!$CK$2:$CK$105,[6]HELPER!$CO$2:$CO$105,""),""), _xlpm.nkHelperCost,IFERROR(INDEX([6]HELPER!$E$2:$E$32,MATCH(TRUE,TRIM([6]HELPER!$A$2:$A$32)="NK",0)),IFERROR(INDEX([6]HELPER!$E$2:$E$32,MATCH(TRUE,TRIM([6]HELPER!$B$2:$B$32)="NK",0)),IFERROR(INDEX([6]HELPER!$E$2:$E$32,MATCH(TRUE,TRIM([6]HELPER!$C$2:$C$32)="NK",0)),IFERROR(INDEX([6]HELPER!$E$2:$E$32,MATCH(TRUE,TRIM([6]HELPER!$D$2:$D$32)="NK",0)),0)))), _xlpm.baseCost,IF(LEFT(_xlpm.mat,4)="TIPA",IF(_xlpm.finalFilmCost<>"",_xlpm.finalFilmCost,_xlpm.specialCost),_xlpm.helperCost), _xlpm.rawResult,IF(OR(_xlpm.mat="NK",_xlpm.mat="NKR",_xlpm.mat="NVS"),_xlpm.nkHelperCost,IF(_xlpm.baseCost="","",IF(OR(_xlpm.finalFilmCost<>"",LEFT(_xlpm.mat,4)="TIPA"),_xlpm.baseCost,_xlpm.baseCost+_xlpm.euShip))), _xlpm.upliftFilm,ISNUMBER(MATCH(_xlpm.matKey,{"TIPA312MET";"TIPA302FG";"TIPA302FGW";"TIPA306M";"TIPA306W";"TIPA312MFG";"TIPA312MFGW"},0)), _xlpm.rawResult ))} | P14: =IF(OR(C14="",A$9<=0),"",IFERROR(IF(O$9="Europe to US",IF(A$9<500,10,IF(A$9<1000,8,IF(A$9<2500,6,IF(A$9<5000,5,4)))),VLOOKUP(O$9,[6]HELPER!$AF$2:$AH$3,3,FALSE)),0)) | X14: =IF($K14="","",IFERROR($M14*($N14+$P14),"")) | AG14: 🔢 Total Quantity | AH14: 52800 | AI14: =IF(AH13="IMP","IMP",IF(AH13="By Length","m","")) | AK14: 🔢 Total Quantity | AL14: 264000 | AM14: =IF(AL13="IMP","IMP",IF(AL13="By Length","m","")) | AO14: 🔢 Total Quantity | AP14: 528000 | AQ14: =IF(AP13="IMP","IMP",IF(AP13="By Length","m",""))
A15: =IF(AP13="By Length",IF(AP14<>"",IFERROR(AP14*$M$20*($D15/$J15),""),""),IF(OR(AP13="By Imp",AP13="IMP"),IFERROR(AP41*$M$20*($D15/$J15),""),IF(AP6="","",AP6))) -> 5035.1513 | B15: =AP3 -> 428 | C15: {=IFERROR(_xlfn.LET(_xlpm.lam,TEXT(B15,"0"),_xlpm.thick,AP4,_xlfn.TAKE(_xlfn._xlws.FILTER([6]HELPER!$BW$2:$BW$250,(TEXT([6]HELPER!$BZ$2:$BZ$250,"0")=_xlpm.lam)*([6]HELPER!$CC$2:$CC$250=_xlpm.thick)*([6]HELPER!$BW$2:$BW$250<>""),"No match"),6)),"")} -> NK | D15: =AP5 -> 352 | E15: =IF(D15="","",_xlfn.LET(_xlpm.cap,IF($Q15="Quantum",760,1220),IF(D15+50>_xlpm.cap,"ERROR: Lamination Width > "&_xlpm.cap,D15*MAX(1,MIN(MAX(2,INT(900/D15)),INT((_xlpm.cap-50)/D15)))))) -> 704 | G15: =IF(OR(AP13="IMP",AP13="By Imp",AP13="By Length"),IFERROR(AP16,""),IFERROR(IF(OR(A15="",A15=0,$D15="",$D15=0,$J15="",$M$20="",$M$20=0,A15<=5),"",(A15-5)/$M$20*($J15/$D15)),"")) -> 139392 | H15: =AP7 -> Printed | I15: =IF(H15="Not Printed",0,AP8) -> 3-4 | J15: =IF(C15="","",$E$15+16) -> 720 | K15: {=_xlfn.LET(_xlpm.baseThick,IFERROR(INDEX([6]HELPER!$BX$2:$BX$250,MATCH(1,(TEXT([6]HELPER!$BZ$2:$BZ$250,"0")=TEXT($B$15,"0"))*([6]HELPER!$CC$2:$CC$250=$AP$4)*([6]HELPER!$BW$2:$BW$250=C15),0)),""),IF(_xlpm.baseThick="","",_xlpm.baseThick))} -> 23 | L15: =IFERROR(VLOOKUP(C15,[6]HELPER!$AP$1:$AQ$25,2,FALSE),"") -> 1.44 | M15: =IF(C15="","",IF(ISNUMBER(SEARCH("paper",C15)),42/1000*(J15/1000),IF(OR(L15="",L15=0),"",L15*1000*(K15/1000000)*(J15/1000)))) -> 0.0238464 | N15: {=IF($C15="","",_xlfn.LET( _xlpm.mat,TRIM($C15), _xlpm.matKey,UPPER(SUBSTITUTE(_xlpm.mat," ","")), _xlpm.pr,IFERROR(LOOKUP(2,1/($H$3:H15<>""),$H$3:H15),""), _xlpm.widthActual,IFERROR(LOOKUP(2,1/($E$3:E15<>""),$E$3:E15),$E15), _xlpm.euShip,IFERROR([6]HELPER!$AH$3,0), _xlpm.metSetup,IFERROR([6]HELPER!$CH$2,0), _xlpm.filmNames,[6]!Table1[Film Type], _xlpm.filmCosts,[6]!Table1[For Laminates calculation purposes], _xlpm.printCosts,[6]!Table1[Printing], _xlpm.printWaste,[6]!Table1[Printing Waste], _xlpm.filmCost,IF(LEFT(_xlpm.mat,4)="TIPA",IFERROR(IF(_xlpm.pr="Not Printed",MIN(_xlfn._xlws.FILTER(_xlpm.filmCosts,(UPPER(SUBSTITUTE(_xlpm.filmNames," ",""))=_xlpm.matKey)*(_xlpm.printCosts=0)*(_xlpm.printWaste=0)*(_xlpm.filmCosts>0))),INDEX(_xlfn._xlws.FILTER(_xlpm.filmCosts,(UPPER(SUBSTITUTE(_xlpm.filmNames," ",""))=_xlpm.matKey)*(_xlpm.filmCosts>0)),1)),""),""), _xlpm.summaryNames,"", _xlpm.summaryThick,"", _xlpm.summaryCosts,"", _xlpm.summaryCost,IF(LEFT(_xlpm.mat,4)="TIPA",IFERROR(IF(_xlpm.pr="Not Printed",MIN(_xlfn._xlws.FILTER(_xlpm.summaryCosts,(UPPER(SUBSTITUTE(_xlpm.summaryNames," ",""))=_xlpm.matKey)*(_xlpm.summaryThick=$K15)*(_xlpm.summaryCosts>0))),INDEX(_xlfn._xlws.FILTER(_xlpm.summaryCosts,(UPPER(SUBSTITUTE(_xlpm.summaryNames," ",""))=_xlpm.matKey)*(_xlpm.summaryThick=$K15)*(_xlpm.summaryCosts>0)),1)),""),""), _xlpm.finalFilmCost,IF(_xlpm.filmCost<>"",_xlpm.filmCost,_xlpm.summaryCost), _xlpm.metFilmCost,IFERROR(INDEX(_xlpm.filmCosts,MATCH("TIPA 312 MFG",_xlpm.filmNames,0)),INDEX(_xlpm.filmCosts,1)), _xlpm.tipa312MfgCost,IFERROR(IF(_xlpm.pr="Not Printed",MIN(_xlfn._xlws.FILTER(_xlpm.filmCosts,(UPPER(SUBSTITUTE(_xlpm.filmNames," ",""))="TIPA312MFG")*(_xlpm.printCosts=0)*(_xlpm.printWaste=0)*(_xlpm.filmCosts>0))),INDEX(_xlfn._xlws.FILTER(_xlpm.filmCosts,(UPPER(SUBSTITUTE(_xlpm.filmNames," ",""))="TIPA312MFG")*(_xlpm.filmCosts>0)),1)),0), _xlpm.metluxCost,IFERROR(INDEX([6]HELPER!$E$2:$E$32,MATCH(TRUE,TRIM([6]HELPER!$A$2:$A$32)="MET LUX",0)),IFERROR(INDEX([6]HELPER!$E$2:$E$32,MATCH(TRUE,TRIM([6]HELPER!$B$2:$B$32)="MET LUX",0)),IFERROR(INDEX([6]HELPER!$E$2:$E$32,MATCH(TRUE,TRIM([6]HELPER!$C$2:$C$32)="MET LUX",0)),IFERROR(INDEX([6]HELPER!$E$2:$E$32,MATCH(TRUE,TRIM([6]HELPER!$D$2:$D$32)="MET LUX",0)),0)))), _xlpm.helperCost,IFERROR(INDEX([6]HELPER!$E$2:$E$32,MATCH(TRUE,TRIM([6]HELPER!$A$2:$A$32)=_xlpm.mat,0)),IFERROR(INDEX([6]HELPER!$E$2:$E$32,MATCH(TRUE,TRIM([6]HELPER!$B$2:$B$32)=_xlpm.mat,0)),IFERROR(INDEX([6]HELPER!$E$2:$E$32,MATCH(TRUE,TRIM([6]HELPER!$C$2:$C$32)=_xlpm.mat,0)),IFERROR(INDEX([6]HELPER!$E$2:$E$32,MATCH(TRUE,TRIM([6]HELPER!$D$2:$D$32)=_xlpm.mat,0)),"")))), _xlpm.specialCost,IFERROR(_xlfn.XLOOKUP(_xlpm.mat,[6]HELPER!$CK$2:$CK$105,[6]HELPER!$CO$2:$CO$105,""),""), _xlpm.nkHelperCost,IFERROR(INDEX([6]HELPER!$E$2:$E$32,MATCH(TRUE,TRIM([6]HELPER!$A$2:$A$32)="NK",0)),IFERROR(INDEX([6]HELPER!$E$2:$E$32,MATCH(TRUE,TRIM([6]HELPER!$B$2:$B$32)="NK",0)),IFERROR(INDEX([6]HELPER!$E$2:$E$32,MATCH(TRUE,TRIM([6]HELPER!$C$2:$C$32)="NK",0)),IFERROR(INDEX([6]HELPER!$E$2:$E$32,MATCH(TRUE,TRIM([6]HELPER!$D$2:$D$32)="NK",0)),0)))), _xlpm.baseCost,IF(LEFT(_xlpm.mat,4)="TIPA",IF(_xlpm.finalFilmCost<>"",_xlpm.finalFilmCost,_xlpm.specialCost),_xlpm.helperCost), _xlpm.rawResult,IF(OR(_xlpm.mat="NK",_xlpm.mat="NKR",_xlpm.mat="NVS"),_xlpm.nkHelperCost,IF(_xlpm.baseCost="","",IF(OR(_xlpm.finalFilmCost<>"",LEFT(_xlpm.mat,4)="TIPA"),_xlpm.baseCost,_xlpm.baseCost+_xlpm.euShip))), _xlpm.upliftFilm,ISNUMBER(MATCH(_xlpm.matKey,{"TIPA312MET";"TIPA302FG";"TIPA302FGW";"TIPA306M";"TIPA306W";"TIPA312MFG";"TIPA312MFGW"},0)), _xlpm.rawResult ))} -> 7.95 | O15: =AP11 -> EXW | P15: =IF(OR(C15="",A$15<=0),"",IFERROR(IF(O$15="Europe to US",IF(A$15<500,10,IF(A$15<1000,8,IF(A$15<2500,6,IF(A$15<5000,5,4)))),VLOOKUP(O$15,[6]HELPER!$AF$2:$AH$3,3,FALSE)),0)) -> 0 | Q15: =AP12 -> Marma | R15: {=IF(OR($Q15="",$G15=""),"",IF($J15>IF($Q15="Quantum",760,1220),"Error! lamination width exceeds supplier maximum",_xlfn.LET(_xlpm.struct,$C$15:$C$20,_xlpm.realLayers,SUMPRODUCT(--(_xlpm.struct<>""),--ISERROR(SEARCH("EPOTAL",_xlpm.struct&"")),--ISERROR(SEARCH("BASONAT",_xlpm.struct&"")),--ISERROR(SEARCH("ADH",_xlpm.struct&"")),--ISERROR(SEARCH("HARDENER",_xlpm.struct&""))),_xlpm.lamSteps,MAX(0,_xlpm.realLayers-1),_xlpm.len,$G15,_xlpm.colNum,IF(_xlpm.len<3000,1,IF(_xlpm.len<10000,2,IF(_xlpm.len<25000,3,IF(_xlpm.len<50000,4,IF(_xlpm.len<100000,5,IF(_xlpm.len<250000,6,7)))))),_xlpm.widthRow,IF($E15<900,0,5),_xlpm.supplierRow,IF($Q15="Marma",3,IF(OR($Q15="Bastin",$Q15="Quantum"),13,0)),_xlpm.baseRate,IF(_xlpm.supplierRow=0,"",INDEX('[6]Lmntn & Prntng- Marma & Bastin '!$D$1:$K$22,_xlpm.supplierRow+_xlpm.widthRow,_xlpm.colNum)),IF(_xlpm.realLayers=0,"",_xlpm.baseRate*_xlpm.lamSteps))))} -> 0.16794 | S15: {=IF($Q15="Quantum",IF(OR($Q15="",$I15=0,$I15="0"),"",IF($J15>IF($Q15="Quantum",760,1220),"Error! lamination width exceeds supplier maximum",IF($E15>1200,"Data is missing",_xlfn.LET(_xlpm.len,$G15,_xlpm.colors,$I15,_xlpm.qWidth,IF($E15<=450,450,IF($E15<=760,760,1200)),_xlpm.band,IF(_xlpm.colors=1,"1",IF(OR(_xlpm.colors=2,_xlpm.colors=3),"2-3",IF(OR(_xlpm.colors=4,_xlpm.colors=5),"4-5","6-8"))),_xlpm.widths,'[6]Digital_per_meter- Quantum'!$A$32:$A$91,_xlpm.bands,'[6]Digital_per_meter- Quantum'!$C$32:$C$91,_xlpm.meters,'[6]Digital_per_meter- Quantum'!$D$32:$D$91,_xlpm.rates,'[6]Digital_per_meter- Quantum'!$H$32:$H$91,_xlpm.targetM,IFERROR(MIN(_xlfn._xlws.FILTER(_xlpm.meters,(_xlpm.widths=_xlpm.qWidth)*(_xlpm.bands=_xlpm.band)*(_xlpm.meters>=_xlpm.len))),MAX(_xlfn._xlws.FILTER(_xlpm.meters,(_xlpm.widths=_xlpm.qWidth)*(_xlpm.bands=_xlpm.band)))),INDEX(_xlpm.rates,_xlfn.XMATCH(1,(_xlpm.widths=_xlpm.qWidth)*(_xlpm.bands=_xlpm.band)*(_xlpm.meters=_xlpm.targetM),0))/[6]HELPER!$AK$2)))),IF(OR($Q15="",$I15=0,$I15="0"),"",IF($J15>IF($Q15="Quantum",760,1220),"Error! lamination width exceeds supplier maximum",_xlfn.LET(_xlpm.len,$G15,_xlpm.colors,$I15,_xlpm.colNum,IF(_xlpm.len<3000,1,IF(_xlpm.len<10000,2,IF(_xlpm.len<25000,3,IF(_xlpm.len<50000,4,IF(_xlpm.len<100000,5,IF(_xlpm.len<250000,6,IF(_xlpm.len<500000,7,8))))))),_xlpm.widthRow,IF($E15<900,0,5),_xlpm.colorOffset,IF(OR(_xlpm.colors=1,_xlpm.colors=2,_xlpm.colors="1-2"),1,IF(OR(_xlpm.colors=3,_xlpm.colors=4,_xlpm.colors="3-4"),2,IF(OR(_xlpm.colors>=5,_xlpm.colors="5-6",_xlpm.colors="5-8"),3,0))),_xlpm.supplierRow,IF($Q15="Marma",3,IF($Q15="Bastin",13,0)),IF(OR(_xlpm.supplierRow=0,_xlpm.colorOffset=0),"",INDEX('[6]Lmntn & Prntng- Marma & Bastin '!$D$1:$K$22,_xlpm.supplierRow+_xlpm.widthRow+_xlpm.colorOffset,_xlpm.colNum))))))} -> 0.09638 | T15: =IF(OR($S15="",$K15=""),"",IFERROR($S15*(1/$M$20)*($J15/($D15*MAX(1,ROUNDDOWN(760/$D15,0)))),"")) -> 1.3340812 | U15: {=IF($Q15="","",IF($J15>IF($Q15="Quantum",760,1220),"Error! lamination width exceeds supplier maximum",_xlfn.LET(_xlpm.len,$G15,_xlpm.colNum,IF(_xlpm.len<3000,1,IF(_xlpm.len<10000,2,IF(_xlpm.len<25000,3,IF(_xlpm.len<50000,4,IF(_xlpm.len<100000,5,IF(_xlpm.len<250000,6,7)))))),_xlpm.widthRow,IF($E15<900,0,5),_xlpm.supplierRow,IF($Q15="Marma",7,IF(OR($Q15="Bastin",$Q15="Quantum"),17,0)),IF(_xlpm.supplierRow=0,"",INDEX('[6]Lmntn & Prntng- Marma & Bastin '!$D$1:$K$22,_xlpm.supplierRow+_xlpm.widthRow,_xlpm.colNum)))))} -> 0.02322 | V15: =IFERROR(IF(AP23="","",IF($K20>31,(5%+250/$G$15)*AP23,VLOOKUP($K20,[6]HELPER!$BH$3:$BI$5,2,TRUE)*AP23)),"") -> 0.41764905 | W15: =IF(OR($H15<>"Printed",$I15=0,$I15="0"),0,IFERROR(AP23*0.028,0)+IFERROR(AP44,0)) -> 0.30911539 | X15: =IF($K15="","",IFERROR($M15*($N15+$P15),"")) -> 0.18957888 | Y15: =IFERROR((SUM(X15:X20)+SUM(R15:S15,U15))*(1/M20)*(J15/E15)+V15+W15,"") -> 12.770595 | Z15: =IF(OR($M15="",$M$20=""),"",IFERROR(($N15+$P15)*$M15/$M$20,"")) -> 2.5658156 | AA15: =AP9 -> 1 | AB15: =IF(OR(AP13="IMP",AP13="By Imp"),IFERROR(AP14/AA15,""),"") -> 528000 | AC15: =AP43 -> 0.33333333 | AG15: 📐 IMP Height / Width | AH15: 528 | AI15: 352 | AK15: 📐 IMP Height / Width | AL15: 528 | AM15: 352 | AO15: 📐 IMP Height / Width | AP15: 528 | AQ15: 352
C16: TIPA 312 MET | J16: =IF(C16="","",$E$15+16) -> 720 | K16: {=_xlfn.LET(_xlpm.baseThick,IFERROR(INDEX([6]HELPER!$BX$2:$BX$250,MATCH(1,(TEXT([6]HELPER!$BZ$2:$BZ$250,"0")=TEXT($B$15,"0"))*([6]HELPER!$CC$2:$CC$250=$AP$4)*([6]HELPER!$BW$2:$BW$250=C16),0)),""),IF(_xlpm.baseThick="","",_xlpm.baseThick))} -> 25 | L16: =IFERROR(VLOOKUP(C16,[6]HELPER!$AP$1:$AQ$25,2,FALSE),"") -> 1.25 | M16: =IF(C16="","",IF(ISNUMBER(SEARCH("paper",C16)),42/1000*(J16/1000),IF(OR(L16="",L16=0),"",L16*1000*(K16/1000000)*(J16/1000)))) -> 0.0225 | N16: {=IF($C16="","",_xlfn.LET( _xlpm.mat,TRIM($C16), _xlpm.matKey,UPPER(SUBSTITUTE(_xlpm.mat," ","")), _xlpm.pr,IFERROR(LOOKUP(2,1/($H$3:H16<>""),$H$3:H16),""), _xlpm.widthActual,IFERROR(LOOKUP(2,1/($E$3:E16<>""),$E$3:E16),$E16), _xlpm.euShip,IFERROR([6]HELPER!$AH$3,0), _xlpm.metSetup,IFERROR([6]HELPER!$CH$2,0), _xlpm.filmNames,[6]!Table1[Film Type], _xlpm.filmCosts,[6]!Table1[For Laminates calculation purposes], _xlpm.printCosts,[6]!Table1[Printing], _xlpm.printWaste,[6]!Table1[Printing Waste], _xlpm.filmCost,IF(LEFT(_xlpm.mat,4)="TIPA",IFERROR(IF(_xlpm.pr="Not Printed",MIN(_xlfn._xlws.FILTER(_xlpm.filmCosts,(UPPER(SUBSTITUTE(_xlpm.filmNames," ",""))=_xlpm.matKey)*(_xlpm.printCosts=0)*(_xlpm.printWaste=0)*(_xlpm.filmCosts>0))),INDEX(_xlfn._xlws.FILTER(_xlpm.filmCosts,(UPPER(SUBSTITUTE(_xlpm.filmNames," ",""))=_xlpm.matKey)*(_xlpm.filmCosts>0)),1)),""),""), _xlpm.summaryNames,"", _xlpm.summaryThick,"", _xlpm.summaryCosts,"", _xlpm.summaryCost,IF(LEFT(_xlpm.mat,4)="TIPA",IFERROR(IF(_xlpm.pr="Not Printed",MIN(_xlfn._xlws.FILTER(_xlpm.summaryCosts,(UPPER(SUBSTITUTE(_xlpm.summaryNames," ",""))=_xlpm.matKey)*(_xlpm.summaryThick=$K16)*(_xlpm.summaryCosts>0))),INDEX(_xlfn._xlws.FILTER(_xlpm.summaryCosts,(UPPER(SUBSTITUTE(_xlpm.summaryNames," ",""))=_xlpm.matKey)*(_xlpm.summaryThick=$K16)*(_xlpm.summaryCosts>0)),1)),""),""), _xlpm.finalFilmCost,IF(_xlpm.filmCost<>"",_xlpm.filmCost,_xlpm.summaryCost), _xlpm.metFilmCost,IFERROR(INDEX(_xlpm.filmCosts,MATCH("TIPA 312 MFG",_xlpm.filmNames,0)),INDEX(_xlpm.filmCosts,1)), _xlpm.tipa312MfgCost,IFERROR(IF(_xlpm.pr="Not Printed",MIN(_xlfn._xlws.FILTER(_xlpm.filmCosts,(UPPER(SUBSTITUTE(_xlpm.filmNames," ",""))="TIPA312MFG")*(_xlpm.printCosts=0)*(_xlpm.printWaste=0)*(_xlpm.filmCosts>0))),INDEX(_xlfn._xlws.FILTER(_xlpm.filmCosts,(UPPER(SUBSTITUTE(_xlpm.filmNames," ",""))="TIPA312MFG")*(_xlpm.filmCosts>0)),1)),0), _xlpm.metluxCost,IFERROR(INDEX([6]HELPER!$E$2:$E$32,MATCH(TRUE,TRIM([6]HELPER!$A$2:$A$32)="MET LUX",0)),IFERROR(INDEX([6]HELPER!$E$2:$E$32,MATCH(TRUE,TRIM([6]HELPER!$B$2:$B$32)="MET LUX",0)),IFERROR(INDEX([6]HELPER!$E$2:$E$32,MATCH(TRUE,TRIM([6]HELPER!$C$2:$C$32)="MET LUX",0)),IFERROR(INDEX([6]HELPER!$E$2:$E$32,MATCH(TRUE,TRIM([6]HELPER!$D$2:$D$32)="MET LUX",0)),0)))), _xlpm.helperCost,IFERROR(INDEX([6]HELPER!$E$2:$E$32,MATCH(TRUE,TRIM([6]HELPER!$A$2:$A$32)=_xlpm.mat,0)),IFERROR(INDEX([6]HELPER!$E$2:$E$32,MATCH(TRUE,TRIM([6]HELPER!$B$2:$B$32)=_xlpm.mat,0)),IFERROR(INDEX([6]HELPER!$E$2:$E$32,MATCH(TRUE,TRIM([6]HELPER!$C$2:$C$32)=_xlpm.mat,0)),IFERROR(INDEX([6]HELPER!$E$2:$E$32,MATCH(TRUE,TRIM([6]HELPER!$D$2:$D$32)=_xlpm.mat,0)),"")))), _xlpm.specialCost,IFERROR(_xlfn.XLOOKUP(_xlpm.mat,[6]HELPER!$CK$2:$CK$105,[6]HELPER!$CO$2:$CO$105,""),""), _xlpm.nkHelperCost,IFERROR(INDEX([6]HELPER!$E$2:$E$32,MATCH(TRUE,TRIM([6]HELPER!$A$2:$A$32)="NK",0)),IFERROR(INDEX([6]HELPER!$E$2:$E$32,MATCH(TRUE,TRIM([6]HELPER!$B$2:$B$32)="NK",0)),IFERROR(INDEX([6]HELPER!$E$2:$E$32,MATCH(TRUE,TRIM([6]HELPER!$C$2:$C$32)="NK",0)),IFERROR(INDEX([6]HELPER!$E$2:$E$32,MATCH(TRUE,TRIM([6]HELPER!$D$2:$D$32)="NK",0)),0)))), _xlpm.baseCost,IF(LEFT(_xlpm.mat,4)="TIPA",IF(_xlpm.finalFilmCost<>"",_xlpm.finalFilmCost,_xlpm.specialCost),_xlpm.helperCost), _xlpm.rawResult,IF(OR(_xlpm.mat="NK",_xlpm.mat="NKR",_xlpm.mat="NVS"),_xlpm.nkHelperCost,IF(_xlpm.baseCost="","",IF(OR(_xlpm.finalFilmCost<>"",LEFT(_xlpm.mat,4)="TIPA"),_xlpm.baseCost,_xlpm.baseCost+_xlpm.euShip))), _xlpm.upliftFilm,ISNUMBER(MATCH(_xlpm.matKey,{"TIPA312MET";"TIPA302FG";"TIPA302FGW";"TIPA306M";"TIPA306W";"TIPA312MFG";"TIPA312MFGW"},0)), _xlpm.rawResult ))} -> 8.1897203 | P16: =IF(OR(C16="",A$15<=0),"",IFERROR(IF(O$15="Europe to US",IF(A$15<500,10,IF(A$15<1000,8,IF(A$15<2500,6,IF(A$15<5000,5,4)))),VLOOKUP(O$15,[6]HELPER!$AF$2:$AH$3,3,FALSE)),0)) -> 0 | X16: =IF($K16="","",IFERROR($M16*($N16+$P16),"")) -> 0.18426871 | Z16: =IF(OR($M16="",$M$20=""),"",IFERROR(($N16+$P16)*$M16/$M$20,"")) -> 2.4939462 | AG16: 📏 Laminate Length | AH16: {=IF(OR(AH13="IMP",AH13="By Imp"),IFERROR(AH14/2*(AH15/1000),""),IF(AH13="By Length",IFERROR(AH14,""),IF(AH13="By Weight",IFERROR(ROUND(INDEX($G$3:$G$20,MATCH(1,($B$3:$B$20=AH3)*($D$3:$D$20=AH5)*($A$3:$A$20=IF(AH6<>"",AH6,A3))*($O$3:$O$20=AH11)*($K$8:$K$25=AH4),0)),0),""),"")))} -> 13939.2 | AI16: m | AK16: 📏 Laminate Length | AL16: {=IF(OR(AL13="IMP",AL13="By Imp"),IFERROR(AL14/2*(AL15/1000),""),IF(AL13="By Length",IFERROR(AL14,""),IF(AL13="By Weight",IFERROR(ROUND(INDEX($G$3:$G$20,MATCH(1,($B$3:$B$20=AL3)*($D$3:$D$20=AL5)*($A$3:$A$20=IF(AL6<>"",AL6,A9))*($O$3:$O$20=AL11)*($K$8:$K$25=AL4),0)),0),""),"")))} -> 69696 | AM16: m | AO16: 📏 Laminate Length | AP16: {=IF(OR(AP13="IMP",AP13="By Imp"),IFERROR(AP14/2*(AP15/1000),""),IF(AP13="By Length",IFERROR(AP14,""),IF(AP13="By Weight",IFERROR(ROUND(INDEX($G$3:$G$20,MATCH(1,($B$3:$B$20=AP3)*($D$3:$D$20=AP5)*($A$3:$A$20=IF(AP6<>"",AP6,A15))*($O$3:$O$20=AP11),0)),0),""),"")))} -> 139392 | AQ16: m
C17: TIPA 312 MET | J17: =IF(C17="","",$E$15+16) -> 720 | K17: {=_xlfn.LET(_xlpm.baseThick,IFERROR(INDEX([6]HELPER!$BX$2:$BX$250,MATCH(1,(TEXT([6]HELPER!$BZ$2:$BZ$250,"0")=TEXT($B$15,"0"))*([6]HELPER!$CC$2:$CC$250=$AP$4)*([6]HELPER!$BW$2:$BW$250=C17),0)),""),IF(_xlpm.baseThick="","",_xlpm.baseThick))} -> 25 | L17: =IFERROR(VLOOKUP(C17,[6]HELPER!$AP$1:$AQ$25,2,FALSE),"") -> 1.25 | M17: =IF(C17="","",IF(ISNUMBER(SEARCH("paper",C17)),42/1000*(J17/1000),IF(OR(L17="",L17=0),"",L17*1000*(K17/1000000)*(J17/1000)))) -> 0.0225 | N17: {=IF($C17="","",_xlfn.LET( _xlpm.mat,TRIM($C17), _xlpm.matKey,UPPER(SUBSTITUTE(_xlpm.mat," ","")), _xlpm.pr,IFERROR(LOOKUP(2,1/($H$3:H17<>""),$H$3:H17),""), _xlpm.widthActual,IFERROR(LOOKUP(2,1/($E$3:E17<>""),$E$3:E17),$E17), _xlpm.euShip,IFERROR([6]HELPER!$AH$3,0), _xlpm.metSetup,IFERROR([6]HELPER!$CH$2,0), _xlpm.filmNames,[6]!Table1[Film Type], _xlpm.filmCosts,[6]!Table1[For Laminates calculation purposes], _xlpm.printCosts,[6]!Table1[Printing], _xlpm.printWaste,[6]!Table1[Printing Waste], _xlpm.filmCost,IF(LEFT(_xlpm.mat,4)="TIPA",IFERROR(IF(_xlpm.pr="Not Printed",MIN(_xlfn._xlws.FILTER(_xlpm.filmCosts,(UPPER(SUBSTITUTE(_xlpm.filmNames," ",""))=_xlpm.matKey)*(_xlpm.printCosts=0)*(_xlpm.printWaste=0)*(_xlpm.filmCosts>0))),INDEX(_xlfn._xlws.FILTER(_xlpm.filmCosts,(UPPER(SUBSTITUTE(_xlpm.filmNames," ",""))=_xlpm.matKey)*(_xlpm.filmCosts>0)),1)),""),""), _xlpm.summaryNames,"", _xlpm.summaryThick,"", _xlpm.summaryCosts,"", _xlpm.summaryCost,IF(LEFT(_xlpm.mat,4)="TIPA",IFERROR(IF(_xlpm.pr="Not Printed",MIN(_xlfn._xlws.FILTER(_xlpm.summaryCosts,(UPPER(SUBSTITUTE(_xlpm.summaryNames," ",""))=_xlpm.matKey)*(_xlpm.summaryThick=$K17)*(_xlpm.summaryCosts>0))),INDEX(_xlfn._xlws.FILTER(_xlpm.summaryCosts,(UPPER(SUBSTITUTE(_xlpm.summaryNames," ",""))=_xlpm.matKey)*(_xlpm.summaryThick=$K17)*(_xlpm.summaryCosts>0)),1)),""),""), _xlpm.finalFilmCost,IF(_xlpm.filmCost<>"",_xlpm.filmCost,_xlpm.summaryCost), _xlpm.metFilmCost,IFERROR(INDEX(_xlpm.filmCosts,MATCH("TIPA 312 MFG",_xlpm.filmNames,0)),INDEX(_xlpm.filmCosts,1)), _xlpm.tipa312MfgCost,IFERROR(IF(_xlpm.pr="Not Printed",MIN(_xlfn._xlws.FILTER(_xlpm.filmCosts,(UPPER(SUBSTITUTE(_xlpm.filmNames," ",""))="TIPA312MFG")*(_xlpm.printCosts=0)*(_xlpm.printWaste=0)*(_xlpm.filmCosts>0))),INDEX(_xlfn._xlws.FILTER(_xlpm.filmCosts,(UPPER(SUBSTITUTE(_xlpm.filmNames," ",""))="TIPA312MFG")*(_xlpm.filmCosts>0)),1)),0), _xlpm.metluxCost,IFERROR(INDEX([6]HELPER!$E$2:$E$32,MATCH(TRUE,TRIM([6]HELPER!$A$2:$A$32)="MET LUX",0)),IFERROR(INDEX([6]HELPER!$E$2:$E$32,MATCH(TRUE,TRIM([6]HELPER!$B$2:$B$32)="MET LUX",0)),IFERROR(INDEX([6]HELPER!$E$2:$E$32,MATCH(TRUE,TRIM([6]HELPER!$C$2:$C$32)="MET LUX",0)),IFERROR(INDEX([6]HELPER!$E$2:$E$32,MATCH(TRUE,TRIM([6]HELPER!$D$2:$D$32)="MET LUX",0)),0)))), _xlpm.helperCost,IFERROR(INDEX([6]HELPER!$E$2:$E$32,MATCH(TRUE,TRIM([6]HELPER!$A$2:$A$32)=_xlpm.mat,0)),IFERROR(INDEX([6]HELPER!$E$2:$E$32,MATCH(TRUE,TRIM([6]HELPER!$B$2:$B$32)=_xlpm.mat,0)),IFERROR(INDEX([6]HELPER!$E$2:$E$32,MATCH(TRUE,TRIM([6]HELPER!$C$2:$C$32)=_xlpm.mat,0)),IFERROR(INDEX([6]HELPER!$E$2:$E$32,MATCH(TRUE,TRIM([6]HELPER!$D$2:$D$32)=_xlpm.mat,0)),"")))), _xlpm.specialCost,IFERROR(_xlfn.XLOOKUP(_xlpm.mat,[6]HELPER!$CK$2:$CK$105,[6]HELPER!$CO$2:$CO$105,""),""), _xlpm.nkHelperCost,IFERROR(INDEX([6]HELPER!$E$2:$E$32,MATCH(TRUE,TRIM([6]HELPER!$A$2:$A$32)="NK",0)),IFERROR(INDEX([6]HELPER!$E$2:$E$32,MATCH(TRUE,TRIM([6]HELPER!$B$2:$B$32)="NK",0)),IFERROR(INDEX([6]HELPER!$E$2:$E$32,MATCH(TRUE,TRIM([6]HELPER!$C$2:$C$32)="NK",0)),IFERROR(INDEX([6]HELPER!$E$2:$E$32,MATCH(TRUE,TRIM([6]HELPER!$D$2:$D$32)="NK",0)),0)))), _xlpm.baseCost,IF(LEFT(_xlpm.mat,4)="TIPA",IF(_xlpm.finalFilmCost<>"",_xlpm.finalFilmCost,_xlpm.specialCost),_xlpm.helperCost), _xlpm.rawResult,IF(OR(_xlpm.mat="NK",_xlpm.mat="NKR",_xlpm.mat="NVS"),_xlpm.nkHelperCost,IF(_xlpm.baseCost="","",IF(OR(_xlpm.finalFilmCost<>"",LEFT(_xlpm.mat,4)="TIPA"),_xlpm.baseCost,_xlpm.baseCost+_xlpm.euShip))), _xlpm.upliftFilm,ISNUMBER(MATCH(_xlpm.matKey,{"TIPA312MET";"TIPA302FG";"TIPA302FGW";"TIPA306M";"TIPA306W";"TIPA312MFG";"TIPA312MFGW"},0)), _xlpm.rawResult ))} -> 8.1897203 | P17: =IF(OR(C17="",A$15<=0),"",IFERROR(IF(O$15="Europe to US",IF(A$15<500,10,IF(A$15<1000,8,IF(A$15<2500,6,IF(A$15<5000,5,4)))),VLOOKUP(O$15,[6]HELPER!$AF$2:$AH$3,3,FALSE)),0)) -> 0 | X17: =IF($K17="","",IFERROR($M17*($N17+$P17),"")) -> 0.18426871 | Z17: =IF(OR($M17="",$M$20=""),"",IFERROR(($N17+$P17)*$M17/$M$20,"")) -> 2.4939462 | AG17: 💶 Total Cost (€) | AH17: =IF(AH39<>"",IFERROR(AH39*AH19,""),"") -> 7630.8959 | AI17: € | AK17: 💶 Total Cost (€) | AL17: =IF(AL39<>"",IFERROR(AL39*AL19,""),"") -> 33586.099 | AM17: € | AO17: 💶 Total Cost (€) | AP17: =IF(AP39<>"",IFERROR(AP39*AP19,""),"") -> 64365.732 | AQ17: €
C18: RM G Epotal ECO 3675 | J18: =IF(C18="","",$E$15+16) -> 720 | K18: {=_xlfn.LET(_xlpm.baseThick,IFERROR(INDEX([6]HELPER!$BX$2:$BX$250,MATCH(1,(TEXT([6]HELPER!$BZ$2:$BZ$250,"0")=TEXT($B$15,"0"))*([6]HELPER!$CC$2:$CC$250=$AP$4)*([6]HELPER!$BW$2:$BW$250=C18),0)),""),IF(_xlpm.baseThick="","",_xlpm.baseThick))} -> 7 | L18: =IFERROR(VLOOKUP(C18,[6]HELPER!$AP$1:$AQ$25,2,FALSE),"") -> 1 | M18: =IF(C18="","",IF(ISNUMBER(SEARCH("paper",C18)),42/1000*(J18/1000),IF(OR(L18="",L18=0),"",L18*1000*(K18/1000000)*(J18/1000)))) -> 0.00504 | N18: {=IF($C18="","",_xlfn.LET( _xlpm.mat,TRIM($C18), _xlpm.matKey,UPPER(SUBSTITUTE(_xlpm.mat," ","")), _xlpm.pr,IFERROR(LOOKUP(2,1/($H$3:H18<>""),$H$3:H18),""), _xlpm.widthActual,IFERROR(LOOKUP(2,1/($E$3:E18<>""),$E$3:E18),$E18), _xlpm.euShip,IFERROR([6]HELPER!$AH$3,0), _xlpm.metSetup,IFERROR([6]HELPER!$CH$2,0), _xlpm.filmNames,[6]!Table1[Film Type], _xlpm.filmCosts,[6]!Table1[For Laminates calculation purposes], _xlpm.printCosts,[6]!Table1[Printing], _xlpm.printWaste,[6]!Table1[Printing Waste], _xlpm.filmCost,IF(LEFT(_xlpm.mat,4)="TIPA",IFERROR(IF(_xlpm.pr="Not Printed",MIN(_xlfn._xlws.FILTER(_xlpm.filmCosts,(UPPER(SUBSTITUTE(_xlpm.filmNames," ",""))=_xlpm.matKey)*(_xlpm.printCosts=0)*(_xlpm.printWaste=0)*(_xlpm.filmCosts>0))),INDEX(_xlfn._xlws.FILTER(_xlpm.filmCosts,(UPPER(SUBSTITUTE(_xlpm.filmNames," ",""))=_xlpm.matKey)*(_xlpm.filmCosts>0)),1)),""),""), _xlpm.summaryNames,"", _xlpm.summaryThick,"", _xlpm.summaryCosts,"", _xlpm.summaryCost,IF(LEFT(_xlpm.mat,4)="TIPA",IFERROR(IF(_xlpm.pr="Not Printed",MIN(_xlfn._xlws.FILTER(_xlpm.summaryCosts,(UPPER(SUBSTITUTE(_xlpm.summaryNames," ",""))=_xlpm.matKey)*(_xlpm.summaryThick=$K18)*(_xlpm.summaryCosts>0))),INDEX(_xlfn._xlws.FILTER(_xlpm.summaryCosts,(UPPER(SUBSTITUTE(_xlpm.summaryNames," ",""))=_xlpm.matKey)*(_xlpm.summaryThick=$K18)*(_xlpm.summaryCosts>0)),1)),""),""), _xlpm.finalFilmCost,IF(_xlpm.filmCost<>"",_xlpm.filmCost,_xlpm.summaryCost), _xlpm.metFilmCost,IFERROR(INDEX(_xlpm.filmCosts,MATCH("TIPA 312 MFG",_xlpm.filmNames,0)),INDEX(_xlpm.filmCosts,1)), _xlpm.tipa312MfgCost,IFERROR(IF(_xlpm.pr="Not Printed",MIN(_xlfn._xlws.FILTER(_xlpm.filmCosts,(UPPER(SUBSTITUTE(_xlpm.filmNames," ",""))="TIPA312MFG")*(_xlpm.printCosts=0)*(_xlpm.printWaste=0)*(_xlpm.filmCosts>0))),INDEX(_xlfn._xlws.FILTER(_xlpm.filmCosts,(UPPER(SUBSTITUTE(_xlpm.filmNames," ",""))="TIPA312MFG")*(_xlpm.filmCosts>0)),1)),0), _xlpm.metluxCost,IFERROR(INDEX([6]HELPER!$E$2:$E$32,MATCH(TRUE,TRIM([6]HELPER!$A$2:$A$32)="MET LUX",0)),IFERROR(INDEX([6]HELPER!$E$2:$E$32,MATCH(TRUE,TRIM([6]HELPER!$B$2:$B$32)="MET LUX",0)),IFERROR(INDEX([6]HELPER!$E$2:$E$32,MATCH(TRUE,TRIM([6]HELPER!$C$2:$C$32)="MET LUX",0)),IFERROR(INDEX([6]HELPER!$E$2:$E$32,MATCH(TRUE,TRIM([6]HELPER!$D$2:$D$32)="MET LUX",0)),0)))), _xlpm.helperCost,IFERROR(INDEX([6]HELPER!$E$2:$E$32,MATCH(TRUE,TRIM([6]HELPER!$A$2:$A$32)=_xlpm.mat,0)),IFERROR(INDEX([6]HELPER!$E$2:$E$32,MATCH(TRUE,TRIM([6]HELPER!$B$2:$B$32)=_xlpm.mat,0)),IFERROR(INDEX([6]HELPER!$E$2:$E$32,MATCH(TRUE,TRIM([6]HELPER!$C$2:$C$32)=_xlpm.mat,0)),IFERROR(INDEX([6]HELPER!$E$2:$E$32,MATCH(TRUE,TRIM([6]HELPER!$D$2:$D$32)=_xlpm.mat,0)),"")))), _xlpm.specialCost,IFERROR(_xlfn.XLOOKUP(_xlpm.mat,[6]HELPER!$CK$2:$CK$105,[6]HELPER!$CO$2:$CO$105,""),""), _xlpm.nkHelperCost,IFERROR(INDEX([6]HELPER!$E$2:$E$32,MATCH(TRUE,TRIM([6]HELPER!$A$2:$A$32)="NK",0)),IFERROR(INDEX([6]HELPER!$E$2:$E$32,MATCH(TRUE,TRIM([6]HELPER!$B$2:$B$32)="NK",0)),IFERROR(INDEX([6]HELPER!$E$2:$E$32,MATCH(TRUE,TRIM([6]HELPER!$C$2:$C$32)="NK",0)),IFERROR(INDEX([6]HELPER!$E$2:$E$32,MATCH(TRUE,TRIM([6]HELPER!$D$2:$D$32)="NK",0)),0)))), _xlpm.baseCost,IF(LEFT(_xlpm.mat,4)="TIPA",IF(_xlpm.finalFilmCost<>"",_xlpm.finalFilmCost,_xlpm.specialCost),_xlpm.helperCost), _xlpm.rawResult,IF(OR(_xlpm.mat="NK",_xlpm.mat="NKR",_xlpm.mat="NVS"),_xlpm.nkHelperCost,IF(_xlpm.baseCost="","",IF(OR(_xlpm.finalFilmCost<>"",LEFT(_xlpm.mat,4)="TIPA"),_xlpm.baseCost,_xlpm.baseCost+_xlpm.euShip))), _xlpm.upliftFilm,ISNUMBER(MATCH(_xlpm.matKey,{"TIPA312MET";"TIPA302FG";"TIPA302FGW";"TIPA306M";"TIPA306W";"TIPA312MFG";"TIPA312MFGW"},0)), _xlpm.rawResult ))} -> 4.85 | P18: =IF(OR(C18="",A$15<=0),"",IFERROR(IF(O$15="Europe to US",IF(A$15<500,10,IF(A$15<1000,8,IF(A$15<2500,6,IF(A$15<5000,5,4)))),VLOOKUP(O$15,[6]HELPER!$AF$2:$AH$3,3,FALSE)),0)) -> 0 | X18: =IF($K18="","",IFERROR($M18*($N18+$P18),"")) -> 0.024444 | Z18: =IF(OR($M18="",$M$20=""),"",IFERROR(($N18+$P18)*$M18/$M$20,"")) -> 0.3308322 | AG18: 💵 Total Cost ($) | AH18: =IF(AH17<>"",IFERROR(AH17*1.16,""),"") -> 8851.8392 | AI18: $ | AK18: 💵 Total Cost ($) | AL18: =IF(AL17<>"",IFERROR(AL17*1.16,""),"") -> 38959.875 | AM18: $ | AO18: 💵 Total Cost ($) | AP18: =IF(AP17<>"",IFERROR(AP17*1.16,""),"") -> 74664.249 | AQ18: $
J19: =IF(C19="","",$E$15+16) | K19: {=_xlfn.LET(_xlpm.baseThick,IFERROR(INDEX([6]HELPER!$BX$2:$BX$250,MATCH(1,(TEXT([6]HELPER!$BZ$2:$BZ$250,"0")=TEXT($B$15,"0"))*([6]HELPER!$CC$2:$CC$250=$AP$4)*([6]HELPER!$BW$2:$BW$250=C19),0)),""),IF(_xlpm.baseThick="","",_xlpm.baseThick))} | L19: =IFERROR(VLOOKUP(C19,[6]HELPER!$AP$1:$AQ$25,2,FALSE),"") | M19: =IF(C19="","",IF(ISNUMBER(SEARCH("paper",C19)),42/1000*(J19/1000),IF(OR(L19="",L19=0),"",L19*1000*(K19/1000000)*(J19/1000)))) | N19: {=IF($C19="","",_xlfn.LET( _xlpm.mat,TRIM($C19), _xlpm.matKey,UPPER(SUBSTITUTE(_xlpm.mat," ","")), _xlpm.pr,IFERROR(LOOKUP(2,1/($H$3:H19<>""),$H$3:H19),""), _xlpm.widthActual,IFERROR(LOOKUP(2,1/($E$3:E19<>""),$E$3:E19),$E19), _xlpm.euShip,IFERROR([6]HELPER!$AH$3,0), _xlpm.metSetup,IFERROR([6]HELPER!$CH$2,0), _xlpm.filmNames,[6]!Table1[Film Type], _xlpm.filmCosts,[6]!Table1[For Laminates calculation purposes], _xlpm.printCosts,[6]!Table1[Printing], _xlpm.printWaste,[6]!Table1[Printing Waste], _xlpm.filmCost,IF(LEFT(_xlpm.mat,4)="TIPA",IFERROR(IF(_xlpm.pr="Not Printed",MIN(_xlfn._xlws.FILTER(_xlpm.filmCosts,(UPPER(SUBSTITUTE(_xlpm.filmNames," ",""))=_xlpm.matKey)*(_xlpm.printCosts=0)*(_xlpm.printWaste=0)*(_xlpm.filmCosts>0))),INDEX(_xlfn._xlws.FILTER(_xlpm.filmCosts,(UPPER(SUBSTITUTE(_xlpm.filmNames," ",""))=_xlpm.matKey)*(_xlpm.filmCosts>0)),1)),""),""), _xlpm.summaryNames,"", _xlpm.summaryThick,"", _xlpm.summaryCosts,"", _xlpm.summaryCost,IF(LEFT(_xlpm.mat,4)="TIPA",IFERROR(IF(_xlpm.pr="Not Printed",MIN(_xlfn._xlws.FILTER(_xlpm.summaryCosts,(UPPER(SUBSTITUTE(_xlpm.summaryNames," ",""))=_xlpm.matKey)*(_xlpm.summaryThick=$K19)*(_xlpm.summaryCosts>0))),INDEX(_xlfn._xlws.FILTER(_xlpm.summaryCosts,(UPPER(SUBSTITUTE(_xlpm.summaryNames," ",""))=_xlpm.matKey)*(_xlpm.summaryThick=$K19)*(_xlpm.summaryCosts>0)),1)),""),""), _xlpm.finalFilmCost,IF(_xlpm.filmCost<>"",_xlpm.filmCost,_xlpm.summaryCost), _xlpm.metFilmCost,IFERROR(INDEX(_xlpm.filmCosts,MATCH("TIPA 312 MFG",_xlpm.filmNames,0)),INDEX(_xlpm.filmCosts,1)), _xlpm.tipa312MfgCost,IFERROR(IF(_xlpm.pr="Not Printed",MIN(_xlfn._xlws.FILTER(_xlpm.filmCosts,(UPPER(SUBSTITUTE(_xlpm.filmNames," ",""))="TIPA312MFG")*(_xlpm.printCosts=0)*(_xlpm.printWaste=0)*(_xlpm.filmCosts>0))),INDEX(_xlfn._xlws.FILTER(_xlpm.filmCosts,(UPPER(SUBSTITUTE(_xlpm.filmNames," ",""))="TIPA312MFG")*(_xlpm.filmCosts>0)),1)),0), _xlpm.metluxCost,IFERROR(INDEX([6]HELPER!$E$2:$E$32,MATCH(TRUE,TRIM([6]HELPER!$A$2:$A$32)="MET LUX",0)),IFERROR(INDEX([6]HELPER!$E$2:$E$32,MATCH(TRUE,TRIM([6]HELPER!$B$2:$B$32)="MET LUX",0)),IFERROR(INDEX([6]HELPER!$E$2:$E$32,MATCH(TRUE,TRIM([6]HELPER!$C$2:$C$32)="MET LUX",0)),IFERROR(INDEX([6]HELPER!$E$2:$E$32,MATCH(TRUE,TRIM([6]HELPER!$D$2:$D$32)="MET LUX",0)),0)))), _xlpm.helperCost,IFERROR(INDEX([6]HELPER!$E$2:$E$32,MATCH(TRUE,TRIM([6]HELPER!$A$2:$A$32)=_xlpm.mat,0)),IFERROR(INDEX([6]HELPER!$E$2:$E$32,MATCH(TRUE,TRIM([6]HELPER!$B$2:$B$32)=_xlpm.mat,0)),IFERROR(INDEX([6]HELPER!$E$2:$E$32,MATCH(TRUE,TRIM([6]HELPER!$C$2:$C$32)=_xlpm.mat,0)),IFERROR(INDEX([6]HELPER!$E$2:$E$32,MATCH(TRUE,TRIM([6]HELPER!$D$2:$D$32)=_xlpm.mat,0)),"")))), _xlpm.specialCost,IFERROR(_xlfn.XLOOKUP(_xlpm.mat,[6]HELPER!$CK$2:$CK$105,[6]HELPER!$CO$2:$CO$105,""),""), _xlpm.nkHelperCost,IFERROR(INDEX([6]HELPER!$E$2:$E$32,MATCH(TRUE,TRIM([6]HELPER!$A$2:$A$32)="NK",0)),IFERROR(INDEX([6]HELPER!$E$2:$E$32,MATCH(TRUE,TRIM([6]HELPER!$B$2:$B$32)="NK",0)),IFERROR(INDEX([6]HELPER!$E$2:$E$32,MATCH(TRUE,TRIM([6]HELPER!$C$2:$C$32)="NK",0)),IFERROR(INDEX([6]HELPER!$E$2:$E$32,MATCH(TRUE,TRIM([6]HELPER!$D$2:$D$32)="NK",0)),0)))), _xlpm.baseCost,IF(LEFT(_xlpm.mat,4)="TIPA",IF(_xlpm.finalFilmCost<>"",_xlpm.finalFilmCost,_xlpm.specialCost),_xlpm.helperCost), _xlpm.rawResult,IF(OR(_xlpm.mat="NK",_xlpm.mat="NKR",_xlpm.mat="NVS"),_xlpm.nkHelperCost,IF(_xlpm.baseCost="","",IF(OR(_xlpm.finalFilmCost<>"",LEFT(_xlpm.mat,4)="TIPA"),_xlpm.baseCost,_xlpm.baseCost+_xlpm.euShip))), _xlpm.upliftFilm,ISNUMBER(MATCH(_xlpm.matKey,{"TIPA312MET";"TIPA302FG";"TIPA302FGW";"TIPA306M";"TIPA306W";"TIPA312MFG";"TIPA312MFGW"},0)), _xlpm.rawResult ))} | P19: =IF(OR(C19="",A$15<=0),"",IFERROR(IF(O$15="Europe to US",IF(A$15<500,10,IF(A$15<1000,8,IF(A$15<2500,6,IF(A$15<5000,5,4)))),VLOOKUP(O$15,[6]HELPER!$AF$2:$AH$3,3,FALSE)),0)) | X19: =IF($K19="","",IFERROR($M19*($N19+$P19),"")) | AG19: 💶 Cost/Kg (€) | AH19: {=_xlfn.LET(_xlpm.base,IF(OR(AND(AH13="By Weight",AH6<>""),AND(AH13="By Length",AH14<>""),AND(OR(AH13="IMP",AH13="By Imp"),AH14<>"",AH15<>"")),IFERROR(_xlfn.LET(_xlpm.r,MATCH(1,($B$3:$B$20=AH3)*($D$3:$D$20=AH5)*($A$3:$A$20=IF(AH6<>"",AH6,A3))*($O$3:$O$20=AH11)*($K$8:$K$25=AH4),0)+2,SUM(AH23:AH24,AH26)+INDEX($V$3:$V$20,_xlpm.r-2)),""),""),IF(_xlpm.base="","",_xlpm.base+IF(AH10="3''",[6]HELPER!$DQ$1,0)))} -> 15.006232 | AI19: € | AK19: 💶 Cost/Kg (€) | AL19: {=_xlfn.LET(_xlpm.base,IF(OR(AND(AL13="By Weight",AL6<>""),AND(AL13="By Length",AL14<>""),AND(OR(AL13="IMP",AL13="By Imp"),AL14<>"",AL15<>"")),IFERROR(_xlfn.LET(_xlpm.r,MATCH(1,($B$3:$B$20=AL3)*($D$3:$D$20=AL5)*($A$3:$A$20=IF(AL6<>"",AL6,A9))*($O$3:$O$20=AL11)*($K$8:$K$25=AL4),0)+2,SUM(AL23:AL24,AL26)+INDEX($V$3:$V$20,_xlpm.r-2)),""),""),IF(_xlpm.base="","",_xlpm.base+IF(AL10="3''",[6]HELPER!$DQ$1,0)))} -> 13.314209 | AM19: € | AO19: 💶 Cost/Kg (€) | AP19: {=_xlfn.LET(_xlpm.base,IF(OR(AND(AP13="By Weight",AP6<>""),AND(AP13="By Length",AP14<>""),AND(OR(AP13="IMP",AP13="By Imp"),AP14<>"",AP15<>"")),IFERROR(_xlfn.LET(_xlpm.r,MATCH(1,($B$3:$B$20=AP3)*($D$3:$D$20=AP5)*($A$3:$A$20=IF(AP6<>"",AP6,A15))*($O$3:$O$20=AP11),0)+2,SUM(AP23:AP24,AP26)+INDEX($V$3:$V$20,_xlpm.r-2)),""),""),IF(_xlpm.base="","",_xlpm.base+IF(AP10="3''",[6]HELPER!$DQ$1,0)))} -> 12.770595 | AQ19: €
J20: =IF(C20="","",$E$15+16) | K20: =AP4 -> 80 | L20: =IFERROR(VLOOKUP(C20,[6]HELPER!$AP$1:$AQ$25,2,FALSE),"") | M20: =SUM(M15:M19) -> 0.0738864 | N20: {=IF($C20="","",_xlfn.LET( _xlpm.mat,TRIM($C20), _xlpm.matKey,UPPER(SUBSTITUTE(_xlpm.mat," ","")), _xlpm.pr,IFERROR(LOOKUP(2,1/($H$3:H20<>""),$H$3:H20),""), _xlpm.widthActual,IFERROR(LOOKUP(2,1/($E$3:E20<>""),$E$3:E20),$E20), _xlpm.euShip,IFERROR([6]HELPER!$AH$3,0), _xlpm.metSetup,IFERROR([6]HELPER!$CH$2,0), _xlpm.filmNames,[6]!Table1[Film Type], _xlpm.filmCosts,[6]!Table1[For Laminates calculation purposes], _xlpm.printCosts,[6]!Table1[Printing], _xlpm.printWaste,[6]!Table1[Printing Waste], _xlpm.filmCost,IF(LEFT(_xlpm.mat,4)="TIPA",IFERROR(IF(_xlpm.pr="Not Printed",MIN(_xlfn._xlws.FILTER(_xlpm.filmCosts,(UPPER(SUBSTITUTE(_xlpm.filmNames," ",""))=_xlpm.matKey)*(_xlpm.printCosts=0)*(_xlpm.printWaste=0)*(_xlpm.filmCosts>0))),INDEX(_xlfn._xlws.FILTER(_xlpm.filmCosts,(UPPER(SUBSTITUTE(_xlpm.filmNames," ",""))=_xlpm.matKey)*(_xlpm.filmCosts>0)),1)),""),""), _xlpm.summaryNames,"", _xlpm.summaryThick,"", _xlpm.summaryCosts,"", _xlpm.summaryCost,IF(LEFT(_xlpm.mat,4)="TIPA",IFERROR(IF(_xlpm.pr="Not Printed",MIN(_xlfn._xlws.FILTER(_xlpm.summaryCosts,(UPPER(SUBSTITUTE(_xlpm.summaryNames," ",""))=_xlpm.matKey)*(_xlpm.summaryThick=$K20)*(_xlpm.summaryCosts>0))),INDEX(_xlfn._xlws.FILTER(_xlpm.summaryCosts,(UPPER(SUBSTITUTE(_xlpm.summaryNames," ",""))=_xlpm.matKey)*(_xlpm.summaryThick=$K20)*(_xlpm.summaryCosts>0)),1)),""),""), _xlpm.finalFilmCost,IF(_xlpm.filmCost<>"",_xlpm.filmCost,_xlpm.summaryCost), _xlpm.metFilmCost,IFERROR(INDEX(_xlpm.filmCosts,MATCH("TIPA 312 MFG",_xlpm.filmNames,0)),INDEX(_xlpm.filmCosts,1)), _xlpm.tipa312MfgCost,IFERROR(IF(_xlpm.pr="Not Printed",MIN(_xlfn._xlws.FILTER(_xlpm.filmCosts,(UPPER(SUBSTITUTE(_xlpm.filmNames," ",""))="TIPA312MFG")*(_xlpm.printCosts=0)*(_xlpm.printWaste=0)*(_xlpm.filmCosts>0))),INDEX(_xlfn._xlws.FILTER(_xlpm.filmCosts,(UPPER(SUBSTITUTE(_xlpm.filmNames," ",""))="TIPA312MFG")*(_xlpm.filmCosts>0)),1)),0), _xlpm.metluxCost,IFERROR(INDEX([6]HELPER!$E$2:$E$32,MATCH(TRUE,TRIM([6]HELPER!$A$2:$A$32)="MET LUX",0)),IFERROR(INDEX([6]HELPER!$E$2:$E$32,MATCH(TRUE,TRIM([6]HELPER!$B$2:$B$32)="MET LUX",0)),IFERROR(INDEX([6]HELPER!$E$2:$E$32,MATCH(TRUE,TRIM([6]HELPER!$C$2:$C$32)="MET LUX",0)),IFERROR(INDEX([6]HELPER!$E$2:$E$32,MATCH(TRUE,TRIM([6]HELPER!$D$2:$D$32)="MET LUX",0)),0)))), _xlpm.helperCost,IFERROR(INDEX([6]HELPER!$E$2:$E$32,MATCH(TRUE,TRIM([6]HELPER!$A$2:$A$32)=_xlpm.mat,0)),IFERROR(INDEX([6]HELPER!$E$2:$E$32,MATCH(TRUE,TRIM([6]HELPER!$B$2:$B$32)=_xlpm.mat,0)),IFERROR(INDEX([6]HELPER!$E$2:$E$32,MATCH(TRUE,TRIM([6]HELPER!$C$2:$C$32)=_xlpm.mat,0)),IFERROR(INDEX([6]HELPER!$E$2:$E$32,MATCH(TRUE,TRIM([6]HELPER!$D$2:$D$32)=_xlpm.mat,0)),"")))), _xlpm.specialCost,IFERROR(_xlfn.XLOOKUP(_xlpm.mat,[6]HELPER!$CK$2:$CK$105,[6]HELPER!$CO$2:$CO$105,""),""), _xlpm.nkHelperCost,IFERROR(INDEX([6]HELPER!$E$2:$E$32,MATCH(TRUE,TRIM([6]HELPER!$A$2:$A$32)="NK",0)),IFERROR(INDEX([6]HELPER!$E$2:$E$32,MATCH(TRUE,TRIM([6]HELPER!$B$2:$B$32)="NK",0)),IFERROR(INDEX([6]HELPER!$E$2:$E$32,MATCH(TRUE,TRIM([6]HELPER!$C$2:$C$32)="NK",0)),IFERROR(INDEX([6]HELPER!$E$2:$E$32,MATCH(TRUE,TRIM([6]HELPER!$D$2:$D$32)="NK",0)),0)))), _xlpm.baseCost,IF(LEFT(_xlpm.mat,4)="TIPA",IF(_xlpm.finalFilmCost<>"",_xlpm.finalFilmCost,_xlpm.specialCost),_xlpm.helperCost), _xlpm.rawResult,IF(OR(_xlpm.mat="NK",_xlpm.mat="NKR",_xlpm.mat="NVS"),_xlpm.nkHelperCost,IF(_xlpm.baseCost="","",IF(OR(_xlpm.finalFilmCost<>"",LEFT(_xlpm.mat,4)="TIPA"),_xlpm.baseCost,_xlpm.baseCost+_xlpm.euShip))), _xlpm.upliftFilm,ISNUMBER(MATCH(_xlpm.matKey,{"TIPA312MET";"TIPA302FG";"TIPA302FGW";"TIPA306M";"TIPA306W";"TIPA312MFG";"TIPA312MFGW"},0)), _xlpm.rawResult ))} | P20: =IF(OR(C20="",A$15<=0),"",IFERROR(IF(O$15="Europe to US",IF(A$15<500,10,IF(A$15<1000,8,IF(A$15<2500,6,IF(A$15<5000,5,4)))),VLOOKUP(O$15,[6]HELPER!$AF$2:$AH$3,3,FALSE)),0)) | AG20: 💵 Cost/Kg ($) | AH20: =IF(AH19<>"",IFERROR(AH19*1.16,""),"") -> 17.407229 | AI20: $ | AK20: 💵 Cost/Kg ($) | AL20: =IF(AL19<>"",IFERROR(AL19*1.16,""),"") -> 15.444482 | AM20: $ | AO20: 💵 Cost/Kg ($) | AP20: =IF(AP19<>"",IFERROR(AP19*1.16,""),"") -> 14.81389 | AQ20: $
G21: =85772/(ROUNDDOWN(J3/D3,0)) -> 42886 | J21: =IF($C21="","",IF($E$15="","",IF(ISNUMBER($E$15),_xlfn.LET(_xlpm.cap,IF($Q$15="Quantum",760,1220),IF($E$15+50>_xlpm.cap,"ERROR: Lamination Width > "&_xlpm.cap,$E$15+50)),$E$15))) | K21: 202 | N21: {=IF($C21="","",_xlfn.LET( _xlpm.mat,TRIM($C21), _xlpm.matKey,UPPER(SUBSTITUTE(_xlpm.mat," ","")), _xlpm.pr,IFERROR(LOOKUP(2,1/($H$3:H21<>""),$H$3:H21),""), _xlpm.widthActual,IFERROR(LOOKUP(2,1/($E$3:E21<>""),$E$3:E21),$E21), _xlpm.euShip,IFERROR([6]HELPER!$AH$3,0), _xlpm.metSetup,IFERROR([6]HELPER!$CH$2,0), _xlpm.filmNames,[6]!Table1[Film Type], _xlpm.filmCosts,[6]!Table1[Total Cost], _xlpm.printCosts,[6]!Table1[Printing], _xlpm.printWaste,[6]!Table1[Printing Waste], _xlpm.filmCost,IF(LEFT(_xlpm.mat,4)="TIPA",IFERROR(IF(_xlpm.pr="Not Printed",MIN(_xlfn._xlws.FILTER(_xlpm.filmCosts,(UPPER(SUBSTITUTE(_xlpm.filmNames," ",""))=_xlpm.matKey)*(_xlpm.printCosts=0)*(_xlpm.printWaste=0)*(_xlpm.filmCosts>0))),INDEX(_xlfn._xlws.FILTER(_xlpm.filmCosts,(UPPER(SUBSTITUTE(_xlpm.filmNames," ",""))=_xlpm.matKey)*(_xlpm.filmCosts>0)),1)),""),""), _xlpm.summaryNames,"", _xlpm.summaryThick,"", _xlpm.summaryCosts,"", _xlpm.summaryCost,IF(LEFT(_xlpm.mat,4)="TIPA",IFERROR(IF(_xlpm.pr="Not Printed",MIN(_xlfn._xlws.FILTER(_xlpm.summaryCosts,(UPPER(SUBSTITUTE(_xlpm.summaryNames," ",""))=_xlpm.matKey)*(_xlpm.summaryThick=$K21)*(_xlpm.summaryCosts>0))),INDEX(_xlfn._xlws.FILTER(_xlpm.summaryCosts,(UPPER(SUBSTITUTE(_xlpm.summaryNames," ",""))=_xlpm.matKey)*(_xlpm.summaryThick=$K21)*(_xlpm.summaryCosts>0)),1)),""),""), _xlpm.finalFilmCost,IF(_xlpm.filmCost<>"",_xlpm.filmCost,_xlpm.summaryCost), _xlpm.metFilmCost,IFERROR(INDEX(_xlpm.filmCosts,MATCH("TIPA 312 MFG",_xlpm.filmNames,0)),INDEX(_xlpm.filmCosts,1)), _xlpm.tipa312MfgCost,IFERROR(IF(_xlpm.pr="Not Printed",MIN(_xlfn._xlws.FILTER(_xlpm.filmCosts,(UPPER(SUBSTITUTE(_xlpm.filmNames," ",""))="TIPA312MFG")*(_xlpm.printCosts=0)*(_xlpm.printWaste=0)*(_xlpm.filmCosts>0))),INDEX(_xlfn._xlws.FILTER(_xlpm.filmCosts,(UPPER(SUBSTITUTE(_xlpm.filmNames," ",""))="TIPA312MFG")*(_xlpm.filmCosts>0)),1)),0), _xlpm.metluxCost,IFERROR(INDEX([6]HELPER!$E$2:$E$32,MATCH(TRUE,TRIM([6]HELPER!$A$2:$A$32)="MET LUX",0)),IFERROR(INDEX([6]HELPER!$E$2:$E$32,MATCH(TRUE,TRIM([6]HELPER!$B$2:$B$32)="MET LUX",0)),IFERROR(INDEX([6]HELPER!$E$2:$E$32,MATCH(TRUE,TRIM([6]HELPER!$C$2:$C$32)="MET LUX",0)),IFERROR(INDEX([6]HELPER!$E$2:$E$32,MATCH(TRUE,TRIM([6]HELPER!$D$2:$D$32)="MET LUX",0)),0)))), _xlpm.helperCost,IFERROR(INDEX([6]HELPER!$E$2:$E$32,MATCH(TRUE,TRIM([6]HELPER!$A$2:$A$32)=_xlpm.mat,0)),IFERROR(INDEX([6]HELPER!$E$2:$E$32,MATCH(TRUE,TRIM([6]HELPER!$B$2:$B$32)=_xlpm.mat,0)),IFERROR(INDEX([6]HELPER!$E$2:$E$32,MATCH(TRUE,TRIM([6]HELPER!$C$2:$C$32)=_xlpm.mat,0)),IFERROR(INDEX([6]HELPER!$E$2:$E$32,MATCH(TRUE,TRIM([6]HELPER!$D$2:$D$32)=_xlpm.mat,0)),"")))), _xlpm.specialCost,IFERROR(_xlfn.XLOOKUP(_xlpm.mat,[6]HELPER!$CK$2:$CK$105,[6]HELPER!$CO$2:$CO$105,""),""), _xlpm.nkHelperCost,IFERROR(INDEX([6]HELPER!$E$2:$E$32,MATCH(TRUE,TRIM([6]HELPER!$A$2:$A$32)="NK",0)),IFERROR(INDEX([6]HELPER!$E$2:$E$32,MATCH(TRUE,TRIM([6]HELPER!$B$2:$B$32)="NK",0)),IFERROR(INDEX([6]HELPER!$E$2:$E$32,MATCH(TRUE,TRIM([6]HELPER!$C$2:$C$32)="NK",0)),IFERROR(INDEX([6]HELPER!$E$2:$E$32,MATCH(TRUE,TRIM([6]HELPER!$D$2:$D$32)="NK",0)),0)))), _xlpm.baseCost,IF(LEFT(_xlpm.mat,4)="TIPA",IF(_xlpm.finalFilmCost<>"",_xlpm.finalFilmCost,_xlpm.specialCost),_xlpm.helperCost), _xlpm.rawResult,IF(OR(_xlpm.mat="NK",_xlpm.mat="NKR"),_xlpm.nkHelperCost,IF(_xlpm.baseCost="","",IF(OR(_xlpm.finalFilmCost<>"",LEFT(_xlpm.mat,4)="TIPA"),_xlpm.baseCost,_xlpm.baseCost+_xlpm.euShip))), _xlpm.upliftFilm,ISNUMBER(MATCH(_xlpm.matKey,{"TIPA312MET";"TIPA302FG";"TIPA302FGW";"TIPA306M";"TIPA306W";"TIPA312MFG";"TIPA312MFGW"},0)), IF(AND(_xlpm.upliftFilm,_xlpm.widthActual>=900,_xlpm.rawResult<>""),_xlpm.rawResult*1.25,_xlpm.rawResult) ))} | T21: =IF(OR($S21="",$K21=""),"",IFERROR($S21*(1/$M$26)*($J21/($D21*MAX(1,ROUNDDOWN(760/$D21,0)))),"")) | AG21: ✓ Cost/Kg (verify) | AH21: =IF(AH39<>"",IFERROR(AH17/AH39,""),"") -> 15.006232 | AI21: €/kg | AK21: ✓ Cost/Kg (verify) | AL21: =IF(AL39<>"",IFERROR(AL17/AL39,""),"") -> 13.314209 | AM21: €/kg | AO21: ✓ Cost/Kg (verify) | AP21: =IF(AP39<>"",IFERROR(AP17/AP39,""),"") -> 12.770595 | AQ21: €/kg
J22: =IF($C22="","",IF($E$15="","",IF(ISNUMBER($E$15),_xlfn.LET(_xlpm.cap,IF($Q$15="Quantum",760,1220),IF($E$15+50>_xlpm.cap,"ERROR: Lamination Width > "&_xlpm.cap,$E$15+50)),$E$15))) | N22: {=IF($C22="","",_xlfn.LET( _xlpm.mat,TRIM($C22), _xlpm.matKey,UPPER(SUBSTITUTE(_xlpm.mat," ","")), _xlpm.pr,IFERROR(LOOKUP(2,1/($H$3:H22<>""),$H$3:H22),""), _xlpm.widthActual,IFERROR(LOOKUP(2,1/($E$3:E22<>""),$E$3:E22),$E22), _xlpm.euShip,IFERROR([6]HELPER!$AH$3,0), _xlpm.metSetup,IFERROR([6]HELPER!$CH$2,0), _xlpm.filmNames,[6]!Table1[Film Type], _xlpm.filmCosts,[6]!Table1[Total Cost], _xlpm.printCosts,[6]!Table1[Printing], _xlpm.printWaste,[6]!Table1[Printing Waste], _xlpm.filmCost,IF(LEFT(_xlpm.mat,4)="TIPA",IFERROR(IF(_xlpm.pr="Not Printed",MIN(_xlfn._xlws.FILTER(_xlpm.filmCosts,(UPPER(SUBSTITUTE(_xlpm.filmNames," ",""))=_xlpm.matKey)*(_xlpm.printCosts=0)*(_xlpm.printWaste=0)*(_xlpm.filmCosts>0))),INDEX(_xlfn._xlws.FILTER(_xlpm.filmCosts,(UPPER(SUBSTITUTE(_xlpm.filmNames," ",""))=_xlpm.matKey)*(_xlpm.filmCosts>0)),1)),""),""), _xlpm.summaryNames,"", _xlpm.summaryThick,"", _xlpm.summaryCosts,"", _xlpm.summaryCost,IF(LEFT(_xlpm.mat,4)="TIPA",IFERROR(IF(_xlpm.pr="Not Printed",MIN(_xlfn._xlws.FILTER(_xlpm.summaryCosts,(UPPER(SUBSTITUTE(_xlpm.summaryNames," ",""))=_xlpm.matKey)*(_xlpm.summaryThick=$K22)*(_xlpm.summaryCosts>0))),INDEX(_xlfn._xlws.FILTER(_xlpm.summaryCosts,(UPPER(SUBSTITUTE(_xlpm.summaryNames," ",""))=_xlpm.matKey)*(_xlpm.summaryThick=$K22)*(_xlpm.summaryCosts>0)),1)),""),""), _xlpm.finalFilmCost,IF(_xlpm.filmCost<>"",_xlpm.filmCost,_xlpm.summaryCost), _xlpm.metFilmCost,IFERROR(INDEX(_xlpm.filmCosts,MATCH("TIPA 312 MFG",_xlpm.filmNames,0)),INDEX(_xlpm.filmCosts,1)), _xlpm.tipa312MfgCost,IFERROR(IF(_xlpm.pr="Not Printed",MIN(_xlfn._xlws.FILTER(_xlpm.filmCosts,(UPPER(SUBSTITUTE(_xlpm.filmNames," ",""))="TIPA312MFG")*(_xlpm.printCosts=0)*(_xlpm.printWaste=0)*(_xlpm.filmCosts>0))),INDEX(_xlfn._xlws.FILTER(_xlpm.filmCosts,(UPPER(SUBSTITUTE(_xlpm.filmNames," ",""))="TIPA312MFG")*(_xlpm.filmCosts>0)),1)),0), _xlpm.metluxCost,IFERROR(INDEX([6]HELPER!$E$2:$E$32,MATCH(TRUE,TRIM([6]HELPER!$A$2:$A$32)="MET LUX",0)),IFERROR(INDEX([6]HELPER!$E$2:$E$32,MATCH(TRUE,TRIM([6]HELPER!$B$2:$B$32)="MET LUX",0)),IFERROR(INDEX([6]HELPER!$E$2:$E$32,MATCH(TRUE,TRIM([6]HELPER!$C$2:$C$32)="MET LUX",0)),IFERROR(INDEX([6]HELPER!$E$2:$E$32,MATCH(TRUE,TRIM([6]HELPER!$D$2:$D$32)="MET LUX",0)),0)))), _xlpm.helperCost,IFERROR(INDEX([6]HELPER!$E$2:$E$32,MATCH(TRUE,TRIM([6]HELPER!$A$2:$A$32)=_xlpm.mat,0)),IFERROR(INDEX([6]HELPER!$E$2:$E$32,MATCH(TRUE,TRIM([6]HELPER!$B$2:$B$32)=_xlpm.mat,0)),IFERROR(INDEX([6]HELPER!$E$2:$E$32,MATCH(TRUE,TRIM([6]HELPER!$C$2:$C$32)=_xlpm.mat,0)),IFERROR(INDEX([6]HELPER!$E$2:$E$32,MATCH(TRUE,TRIM([6]HELPER!$D$2:$D$32)=_xlpm.mat,0)),"")))), _xlpm.specialCost,IFERROR(_xlfn.XLOOKUP(_xlpm.mat,[6]HELPER!$CK$2:$CK$105,[6]HELPER!$CO$2:$CO$105,""),""), _xlpm.nkHelperCost,IFERROR(INDEX([6]HELPER!$E$2:$E$32,MATCH(TRUE,TRIM([6]HELPER!$A$2:$A$32)="NK",0)),IFERROR(INDEX([6]HELPER!$E$2:$E$32,MATCH(TRUE,TRIM([6]HELPER!$B$2:$B$32)="NK",0)),IFERROR(INDEX([6]HELPER!$E$2:$E$32,MATCH(TRUE,TRIM([6]HELPER!$C$2:$C$32)="NK",0)),IFERROR(INDEX([6]HELPER!$E$2:$E$32,MATCH(TRUE,TRIM([6]HELPER!$D$2:$D$32)="NK",0)),0)))), _xlpm.baseCost,IF(LEFT(_xlpm.mat,4)="TIPA",IF(_xlpm.finalFilmCost<>"",_xlpm.finalFilmCost,_xlpm.specialCost),_xlpm.helperCost), _xlpm.rawResult,IF(OR(_xlpm.mat="NK",_xlpm.mat="NKR"),_xlpm.nkHelperCost,IF(_xlpm.baseCost="","",IF(OR(_xlpm.finalFilmCost<>"",LEFT(_xlpm.mat,4)="TIPA"),_xlpm.baseCost,_xlpm.baseCost+_xlpm.euShip))), _xlpm.upliftFilm,ISNUMBER(MATCH(_xlpm.matKey,{"TIPA312MET";"TIPA302FG";"TIPA302FGW";"TIPA306M";"TIPA306W";"TIPA312MFG";"TIPA312MFGW"},0)), IF(AND(_xlpm.upliftFilm,_xlpm.widthActual>=900,_xlpm.rawResult<>""),_xlpm.rawResult*1.25,_xlpm.rawResult) ))} | S22: 0.18306 | AG22: 🏭 Machine length (supplier tier) | AH22: =IFERROR(AH41*AH43,"") -> 4646.4 | AI22: m | AK22: 🏭 Machine length (supplier tier) | AL22: =IFERROR(AL41*AL43,"") -> 23232 | AM22: m | AO22: 🏭 Machine length (supplier tier) | AP22: =IFERROR(AP41*AP43,"") -> 46464 | AQ22: m
J23: =IF($C23="","",IF($E$15="","",IF(ISNUMBER($E$15),_xlfn.LET(_xlpm.cap,IF($Q$15="Quantum",760,1220),IF($E$15+50>_xlpm.cap,"ERROR: Lamination Width > "&_xlpm.cap,$E$15+50)),$E$15))) | N23: {=IF($C23="","",_xlfn.LET( _xlpm.mat,TRIM($C23), _xlpm.matKey,UPPER(SUBSTITUTE(_xlpm.mat," ","")), _xlpm.pr,IFERROR(LOOKUP(2,1/($H$3:H23<>""),$H$3:H23),""), _xlpm.widthActual,IFERROR(LOOKUP(2,1/($E$3:E23<>""),$E$3:E23),$E23), _xlpm.euShip,IFERROR([6]HELPER!$AH$3,0), _xlpm.metSetup,IFERROR([6]HELPER!$CH$2,0), _xlpm.filmNames,[6]!Table1[Film Type], _xlpm.filmCosts,[6]!Table1[Total Cost], _xlpm.printCosts,[6]!Table1[Printing], _xlpm.printWaste,[6]!Table1[Printing Waste], _xlpm.filmCost,IF(LEFT(_xlpm.mat,4)="TIPA",IFERROR(IF(_xlpm.pr="Not Printed",MIN(_xlfn._xlws.FILTER(_xlpm.filmCosts,(UPPER(SUBSTITUTE(_xlpm.filmNames," ",""))=_xlpm.matKey)*(_xlpm.printCosts=0)*(_xlpm.printWaste=0)*(_xlpm.filmCosts>0))),INDEX(_xlfn._xlws.FILTER(_xlpm.filmCosts,(UPPER(SUBSTITUTE(_xlpm.filmNames," ",""))=_xlpm.matKey)*(_xlpm.filmCosts>0)),1)),""),""), _xlpm.summaryNames,"", _xlpm.summaryThick,"", _xlpm.summaryCosts,"", _xlpm.summaryCost,IF(LEFT(_xlpm.mat,4)="TIPA",IFERROR(IF(_xlpm.pr="Not Printed",MIN(_xlfn._xlws.FILTER(_xlpm.summaryCosts,(UPPER(SUBSTITUTE(_xlpm.summaryNames," ",""))=_xlpm.matKey)*(_xlpm.summaryThick=$K23)*(_xlpm.summaryCosts>0))),INDEX(_xlfn._xlws.FILTER(_xlpm.summaryCosts,(UPPER(SUBSTITUTE(_xlpm.summaryNames," ",""))=_xlpm.matKey)*(_xlpm.summaryThick=$K23)*(_xlpm.summaryCosts>0)),1)),""),""), _xlpm.finalFilmCost,IF(_xlpm.filmCost<>"",_xlpm.filmCost,_xlpm.summaryCost), _xlpm.metFilmCost,IFERROR(INDEX(_xlpm.filmCosts,MATCH("TIPA 312 MFG",_xlpm.filmNames,0)),INDEX(_xlpm.filmCosts,1)), _xlpm.tipa312MfgCost,IFERROR(IF(_xlpm.pr="Not Printed",MIN(_xlfn._xlws.FILTER(_xlpm.filmCosts,(UPPER(SUBSTITUTE(_xlpm.filmNames," ",""))="TIPA312MFG")*(_xlpm.printCosts=0)*(_xlpm.printWaste=0)*(_xlpm.filmCosts>0))),INDEX(_xlfn._xlws.FILTER(_xlpm.filmCosts,(UPPER(SUBSTITUTE(_xlpm.filmNames," ",""))="TIPA312MFG")*(_xlpm.filmCosts>0)),1)),0), _xlpm.metluxCost,IFERROR(INDEX([6]HELPER!$E$2:$E$32,MATCH(TRUE,TRIM([6]HELPER!$A$2:$A$32)="MET LUX",0)),IFERROR(INDEX([6]HELPER!$E$2:$E$32,MATCH(TRUE,TRIM([6]HELPER!$B$2:$B$32)="MET LUX",0)),IFERROR(INDEX([6]HELPER!$E$2:$E$32,MATCH(TRUE,TRIM([6]HELPER!$C$2:$C$32)="MET LUX",0)),IFERROR(INDEX([6]HELPER!$E$2:$E$32,MATCH(TRUE,TRIM([6]HELPER!$D$2:$D$32)="MET LUX",0)),0)))), _xlpm.helperCost,IFERROR(INDEX([6]HELPER!$E$2:$E$32,MATCH(TRUE,TRIM([6]HELPER!$A$2:$A$32)=_xlpm.mat,0)),IFERROR(INDEX([6]HELPER!$E$2:$E$32,MATCH(TRUE,TRIM([6]HELPER!$B$2:$B$32)=_xlpm.mat,0)),IFERROR(INDEX([6]HELPER!$E$2:$E$32,MATCH(TRUE,TRIM([6]HELPER!$C$2:$C$32)=_xlpm.mat,0)),IFERROR(INDEX([6]HELPER!$E$2:$E$32,MATCH(TRUE,TRIM([6]HELPER!$D$2:$D$32)=_xlpm.mat,0)),"")))), _xlpm.specialCost,IFERROR(_xlfn.XLOOKUP(_xlpm.mat,[6]HELPER!$CK$2:$CK$105,[6]HELPER!$CO$2:$CO$105,""),""), _xlpm.nkHelperCost,IFERROR(INDEX([6]HELPER!$E$2:$E$32,MATCH(TRUE,TRIM([6]HELPER!$A$2:$A$32)="NK",0)),IFERROR(INDEX([6]HELPER!$E$2:$E$32,MATCH(TRUE,TRIM([6]HELPER!$B$2:$B$32)="NK",0)),IFERROR(INDEX([6]HELPER!$E$2:$E$32,MATCH(TRUE,TRIM([6]HELPER!$C$2:$C$32)="NK",0)),IFERROR(INDEX([6]HELPER!$E$2:$E$32,MATCH(TRUE,TRIM([6]HELPER!$D$2:$D$32)="NK",0)),0)))), _xlpm.baseCost,IF(LEFT(_xlpm.mat,4)="TIPA",IF(_xlpm.finalFilmCost<>"",_xlpm.finalFilmCost,_xlpm.specialCost),_xlpm.helperCost), _xlpm.rawResult,IF(OR(_xlpm.mat="NK",_xlpm.mat="NKR"),_xlpm.nkHelperCost,IF(_xlpm.baseCost="","",IF(OR(_xlpm.finalFilmCost<>"",LEFT(_xlpm.mat,4)="TIPA"),_xlpm.baseCost,_xlpm.baseCost+_xlpm.euShip))), _xlpm.upliftFilm,ISNUMBER(MATCH(_xlpm.matKey,{"TIPA312MET";"TIPA302FG";"TIPA302FGW";"TIPA306M";"TIPA306W";"TIPA312MFG";"TIPA312MFGW"},0)), IF(AND(_xlpm.upliftFilm,_xlpm.widthActual>=900,_xlpm.rawResult<>""),_xlpm.rawResult*1.25,_xlpm.rawResult) ))} | AG23: (Raw Material €/kg) | AH23: {=IF(OR(AND(AH13="By Weight",AH6<>""),AND(AH13="By Length",AH14<>""),AND(OR(AH13="IMP",AH13="By Imp"),AH14<>"",AH15<>"")),IFERROR(_xlfn.LET(_xlpm.r,MATCH(1,($B$3:$B$20=AH3)*($D$3:$D$20=AH5)*($A$3:$A$20=IF(AH6<>"",AH6,A3))*($O$3:$O$20=AH11)*($K$8:$K$25=AH4),0)+2,SUMPRODUCT(INDEX($N$3:$N$20,_xlpm.r-2):INDEX($N$3:$N$20,_xlpm.r+3),INDEX($M$3:$M$20,_xlpm.r-2):INDEX($M$3:$M$20,_xlpm.r+3))*(1/INDEX($M$3:$M$20,MATCH(1,($B$3:$B$20=AH3)*($D$3:$D$20=AH5)*($A$3:$A$20=IF(AH6<>"",AH6,A3))*($O$3:$O$20=AH11)*($K$8:$K$25=AH4),0)+5))*(INDEX($J$3:$J$20,_xlpm.r-2)/INDEX($E$3:$E$20,_xlpm.r-2))),""),"")} -> 8.0637343 | AK23: (RM €/kg) | AL23: {=IF(OR(AND(AL13="By Weight",AL6<>""),AND(AL13="By Length",AL14<>""),AND(OR(AL13="IMP",AL13="By Imp"),AL14<>"",AL15<>"")),IFERROR(_xlfn.LET(_xlpm.r,MATCH(1,($B$3:$B$20=AL3)*($D$3:$D$20=AL5)*($A$3:$A$20=IF(AL6<>"",AL6,A9))*($O$3:$O$20=AL11)*($K$8:$K$25=AL4),0)+2,SUMPRODUCT(INDEX($N$3:$N$20,_xlpm.r-2):INDEX($N$3:$N$20,_xlpm.r+3),INDEX($M$3:$M$20,_xlpm.r-2):INDEX($M$3:$M$20,_xlpm.r+3))*(1/INDEX($M$3:$M$20,MATCH(1,($B$3:$B$20=AL3)*($D$3:$D$20=AL5)*($A$3:$A$20=IF(AL6<>"",AL6,A9))*($O$3:$O$20=AL11)*($K$8:$K$25=AL4),0)+5))*(INDEX($J$3:$J$20,_xlpm.r-2)/INDEX($E$3:$E$20,_xlpm.r-2))),""),"")} -> 8.0637343 | AO23: (RM €/kg) | AP23: {=IF(OR(AND(AP13="By Weight",AP6<>""),AND(AP13="By Length",AP14<>""),AND(OR(AP13="IMP",AP13="By Imp"),AP14<>"",AP15<>"")),IFERROR(_xlfn.LET(_xlpm.r,MATCH(1,($B$3:$B$20=AP3)*($D$3:$D$20=AP5)*($A$3:$A$20=IF(AP6<>"",AP6,A15))*($O$3:$O$20=AP11),0)+2,SUMPRODUCT(INDEX($N$3:$N$20,_xlpm.r-2):INDEX($N$3:$N$20,_xlpm.r+3),INDEX($M$3:$M$20,_xlpm.r-2):INDEX($M$3:$M$20,_xlpm.r+3))*(1/INDEX($M$3:$M$20,MATCH(1,($B$3:$B$20=AP3)*($D$3:$D$20=AP5)*($A$3:$A$20=IF(AP6<>"",AP6,A15))*($O$3:$O$20=AP11),0)+5))*(INDEX($J$3:$J$20,_xlpm.r-2)/INDEX($E$3:$E$20,_xlpm.r-2))),""),"")} -> 8.0637343
J24: =IF($C24="","",IF($E$15="","",IF(ISNUMBER($E$15),_xlfn.LET(_xlpm.cap,IF($Q$15="Quantum",760,1220),IF($E$15+50>_xlpm.cap,"ERROR: Lamination Width > "&_xlpm.cap,$E$15+50)),$E$15))) | N24: {=IF($C24="","",_xlfn.LET( _xlpm.mat,TRIM($C24), _xlpm.matKey,UPPER(SUBSTITUTE(_xlpm.mat," ","")), _xlpm.pr,IFERROR(LOOKUP(2,1/($H$3:H24<>""),$H$3:H24),""), _xlpm.widthActual,IFERROR(LOOKUP(2,1/($E$3:E24<>""),$E$3:E24),$E24), _xlpm.euShip,IFERROR([6]HELPER!$AH$3,0), _xlpm.metSetup,IFERROR([6]HELPER!$CH$2,0), _xlpm.filmNames,[6]!Table1[Film Type], _xlpm.filmCosts,[6]!Table1[Total Cost], _xlpm.printCosts,[6]!Table1[Printing], _xlpm.printWaste,[6]!Table1[Printing Waste], _xlpm.filmCost,IF(LEFT(_xlpm.mat,4)="TIPA",IFERROR(IF(_xlpm.pr="Not Printed",MIN(_xlfn._xlws.FILTER(_xlpm.filmCosts,(UPPER(SUBSTITUTE(_xlpm.filmNames," ",""))=_xlpm.matKey)*(_xlpm.printCosts=0)*(_xlpm.printWaste=0)*(_xlpm.filmCosts>0))),INDEX(_xlfn._xlws.FILTER(_xlpm.filmCosts,(UPPER(SUBSTITUTE(_xlpm.filmNames," ",""))=_xlpm.matKey)*(_xlpm.filmCosts>0)),1)),""),""), _xlpm.summaryNames,"", _xlpm.summaryThick,"", _xlpm.summaryCosts,"", _xlpm.summaryCost,IF(LEFT(_xlpm.mat,4)="TIPA",IFERROR(IF(_xlpm.pr="Not Printed",MIN(_xlfn._xlws.FILTER(_xlpm.summaryCosts,(UPPER(SUBSTITUTE(_xlpm.summaryNames," ",""))=_xlpm.matKey)*(_xlpm.summaryThick=$K24)*(_xlpm.summaryCosts>0))),INDEX(_xlfn._xlws.FILTER(_xlpm.summaryCosts,(UPPER(SUBSTITUTE(_xlpm.summaryNames," ",""))=_xlpm.matKey)*(_xlpm.summaryThick=$K24)*(_xlpm.summaryCosts>0)),1)),""),""), _xlpm.finalFilmCost,IF(_xlpm.filmCost<>"",_xlpm.filmCost,_xlpm.summaryCost), _xlpm.metFilmCost,IFERROR(INDEX(_xlpm.filmCosts,MATCH("TIPA 312 MFG",_xlpm.filmNames,0)),INDEX(_xlpm.filmCosts,1)), _xlpm.tipa312MfgCost,IFERROR(IF(_xlpm.pr="Not Printed",MIN(_xlfn._xlws.FILTER(_xlpm.filmCosts,(UPPER(SUBSTITUTE(_xlpm.filmNames," ",""))="TIPA312MFG")*(_xlpm.printCosts=0)*(_xlpm.printWaste=0)*(_xlpm.filmCosts>0))),INDEX(_xlfn._xlws.FILTER(_xlpm.filmCosts,(UPPER(SUBSTITUTE(_xlpm.filmNames," ",""))="TIPA312MFG")*(_xlpm.filmCosts>0)),1)),0), _xlpm.metluxCost,IFERROR(INDEX([6]HELPER!$E$2:$E$32,MATCH(TRUE,TRIM([6]HELPER!$A$2:$A$32)="MET LUX",0)),IFERROR(INDEX([6]HELPER!$E$2:$E$32,MATCH(TRUE,TRIM([6]HELPER!$B$2:$B$32)="MET LUX",0)),IFERROR(INDEX([6]HELPER!$E$2:$E$32,MATCH(TRUE,TRIM([6]HELPER!$C$2:$C$32)="MET LUX",0)),IFERROR(INDEX([6]HELPER!$E$2:$E$32,MATCH(TRUE,TRIM([6]HELPER!$D$2:$D$32)="MET LUX",0)),0)))), _xlpm.helperCost,IFERROR(INDEX([6]HELPER!$E$2:$E$32,MATCH(TRUE,TRIM([6]HELPER!$A$2:$A$32)=_xlpm.mat,0)),IFERROR(INDEX([6]HELPER!$E$2:$E$32,MATCH(TRUE,TRIM([6]HELPER!$B$2:$B$32)=_xlpm.mat,0)),IFERROR(INDEX([6]HELPER!$E$2:$E$32,MATCH(TRUE,TRIM([6]HELPER!$C$2:$C$32)=_xlpm.mat,0)),IFERROR(INDEX([6]HELPER!$E$2:$E$32,MATCH(TRUE,TRIM([6]HELPER!$D$2:$D$32)=_xlpm.mat,0)),"")))), _xlpm.specialCost,IFERROR(_xlfn.XLOOKUP(_xlpm.mat,[6]HELPER!$CK$2:$CK$105,[6]HELPER!$CO$2:$CO$105,""),""), _xlpm.nkHelperCost,IFERROR(INDEX([6]HELPER!$E$2:$E$32,MATCH(TRUE,TRIM([6]HELPER!$A$2:$A$32)="NK",0)),IFERROR(INDEX([6]HELPER!$E$2:$E$32,MATCH(TRUE,TRIM([6]HELPER!$B$2:$B$32)="NK",0)),IFERROR(INDEX([6]HELPER!$E$2:$E$32,MATCH(TRUE,TRIM([6]HELPER!$C$2:$C$32)="NK",0)),IFERROR(INDEX([6]HELPER!$E$2:$E$32,MATCH(TRUE,TRIM([6]HELPER!$D$2:$D$32)="NK",0)),0)))), _xlpm.baseCost,IF(LEFT(_xlpm.mat,4)="TIPA",IF(_xlpm.finalFilmCost<>"",_xlpm.finalFilmCost,_xlpm.specialCost),_xlpm.helperCost), _xlpm.rawResult,IF(OR(_xlpm.mat="NK",_xlpm.mat="NKR"),_xlpm.nkHelperCost,IF(_xlpm.baseCost="","",IF(OR(_xlpm.finalFilmCost<>"",LEFT(_xlpm.mat,4)="TIPA"),_xlpm.baseCost,_xlpm.baseCost+_xlpm.euShip))), _xlpm.upliftFilm,ISNUMBER(MATCH(_xlpm.matKey,{"TIPA312MET";"TIPA302FG";"TIPA302FGW";"TIPA306M";"TIPA306W";"TIPA312MFG";"TIPA312MFGW"},0)), IF(AND(_xlpm.upliftFilm,_xlpm.widthActual>=900,_xlpm.rawResult<>""),_xlpm.rawResult*1.25,_xlpm.rawResult) ))} | AG24: (Shipment €/kg) | AH24: {=IF(OR(AND(AH13="By Weight",AH6<>""),AND(AH13="By Length",AH14<>""),AND(OR(AH13="IMP",AH13="By Imp"),AH14<>"",AH15<>"")),IFERROR(_xlfn.LET(_xlpm.r,MATCH(1,($B$3:$B$20=AH3)*($D$3:$D$20=AH5)*($A$3:$A$20=IF(AH6<>"",AH6,A3))*($O$3:$O$20=AH11)*($K$8:$K$25=AH4),0)+2,SUMPRODUCT(INDEX($P$3:$P$20,_xlpm.r-2):INDEX($P$3:$P$20,_xlpm.r+3),INDEX($M$3:$M$20,_xlpm.r-2):INDEX($M$3:$M$20,_xlpm.r+3))*(1/INDEX($M$3:$M$20,MATCH(1,($B$3:$B$20=AH3)*($D$3:$D$20=AH5)*($A$3:$A$20=IF(AH6<>"",AH6,A3))*($O$3:$O$20=AH11)*($K$8:$K$25=AH4),0)+5))*(INDEX($J$3:$J$20,_xlpm.r-2)/INDEX($E$3:$E$20,_xlpm.r-2))),""),"")} -> 0 | AK24: (Ship €/kg) | AL24: {=IF(OR(AND(AL13="By Weight",AL6<>""),AND(AL13="By Length",AL14<>""),AND(OR(AL13="IMP",AL13="By Imp"),AL14<>"",AL15<>"")),IFERROR(_xlfn.LET(_xlpm.r,MATCH(1,($B$3:$B$20=AL3)*($D$3:$D$20=AL5)*($A$3:$A$20=IF(AL6<>"",AL6,A9))*($O$3:$O$20=AL11)*($K$8:$K$25=AL4),0)+2,SUMPRODUCT(INDEX($P$3:$P$20,_xlpm.r-2):INDEX($P$3:$P$20,_xlpm.r+3),INDEX($M$3:$M$20,_xlpm.r-2):INDEX($M$3:$M$20,_xlpm.r+3))*(1/INDEX($M$3:$M$20,MATCH(1,($B$3:$B$20=AL3)*($D$3:$D$20=AL5)*($A$3:$A$20=IF(AL6<>"",AL6,A9))*($O$3:$O$20=AL11)*($K$8:$K$25=AL4),0)+5))*(INDEX($J$3:$J$20,_xlpm.r-2)/INDEX($E$3:$E$20,_xlpm.r-2))),""),"")} -> 0 | AO24: (Ship €/kg) | AP24: {=IF(OR(AND(AP13="By Weight",AP6<>""),AND(AP13="By Length",AP14<>""),AND(OR(AP13="IMP",AP13="By Imp"),AP14<>"",AP15<>"")),IFERROR(_xlfn.LET(_xlpm.r,MATCH(1,($B$3:$B$20=AP3)*($D$3:$D$20=AP5)*($A$3:$A$20=IF(AP6<>"",AP6,A15))*($O$3:$O$20=AP11),0)+2,SUMPRODUCT(INDEX($P$3:$P$20,_xlpm.r-2):INDEX($P$3:$P$20,_xlpm.r+3),INDEX($M$3:$M$20,_xlpm.r-2):INDEX($M$3:$M$20,_xlpm.r+3))*(1/INDEX($M$3:$M$20,MATCH(1,($B$3:$B$20=AP3)*($D$3:$D$20=AP5)*($A$3:$A$20=IF(AP6<>"",AP6,A15))*($O$3:$O$20=AP11),0)+5))*(INDEX($J$3:$J$20,_xlpm.r-2)/INDEX($E$3:$E$20,_xlpm.r-2))),""),"")} -> 0
J25: =IF($C25="","",IF($E$15="","",IF(ISNUMBER($E$15),_xlfn.LET(_xlpm.cap,IF($Q$15="Quantum",760,1220),IF($E$15+50>_xlpm.cap,"ERROR: Lamination Width > "&_xlpm.cap,$E$15+50)),$E$15))) | N25: {=IF($C25="","",_xlfn.LET( _xlpm.mat,TRIM($C25), _xlpm.matKey,UPPER(SUBSTITUTE(_xlpm.mat," ","")), _xlpm.pr,IFERROR(LOOKUP(2,1/($H$3:H25<>""),$H$3:H25),""), _xlpm.widthActual,IFERROR(LOOKUP(2,1/($E$3:E25<>""),$E$3:E25),$E25), _xlpm.euShip,IFERROR([6]HELPER!$AH$3,0), _xlpm.metSetup,IFERROR([6]HELPER!$CH$2,0), _xlpm.filmNames,[6]!Table1[Film Type], _xlpm.filmCosts,[6]!Table1[Total Cost], _xlpm.printCosts,[6]!Table1[Printing], _xlpm.printWaste,[6]!Table1[Printing Waste], _xlpm.filmCost,IF(LEFT(_xlpm.mat,4)="TIPA",IFERROR(IF(_xlpm.pr="Not Printed",MIN(_xlfn._xlws.FILTER(_xlpm.filmCosts,(UPPER(SUBSTITUTE(_xlpm.filmNames," ",""))=_xlpm.matKey)*(_xlpm.printCosts=0)*(_xlpm.printWaste=0)*(_xlpm.filmCosts>0))),INDEX(_xlfn._xlws.FILTER(_xlpm.filmCosts,(UPPER(SUBSTITUTE(_xlpm.filmNames," ",""))=_xlpm.matKey)*(_xlpm.filmCosts>0)),1)),""),""), _xlpm.summaryNames,"", _xlpm.summaryThick,"", _xlpm.summaryCosts,"", _xlpm.summaryCost,IF(LEFT(_xlpm.mat,4)="TIPA",IFERROR(IF(_xlpm.pr="Not Printed",MIN(_xlfn._xlws.FILTER(_xlpm.summaryCosts,(UPPER(SUBSTITUTE(_xlpm.summaryNames," ",""))=_xlpm.matKey)*(_xlpm.summaryThick=$K25)*(_xlpm.summaryCosts>0))),INDEX(_xlfn._xlws.FILTER(_xlpm.summaryCosts,(UPPER(SUBSTITUTE(_xlpm.summaryNames," ",""))=_xlpm.matKey)*(_xlpm.summaryThick=$K25)*(_xlpm.summaryCosts>0)),1)),""),""), _xlpm.finalFilmCost,IF(_xlpm.filmCost<>"",_xlpm.filmCost,_xlpm.summaryCost), _xlpm.metFilmCost,IFERROR(INDEX(_xlpm.filmCosts,MATCH("TIPA 312 MFG",_xlpm.filmNames,0)),INDEX(_xlpm.filmCosts,1)), _xlpm.tipa312MfgCost,IFERROR(IF(_xlpm.pr="Not Printed",MIN(_xlfn._xlws.FILTER(_xlpm.filmCosts,(UPPER(SUBSTITUTE(_xlpm.filmNames," ",""))="TIPA312MFG")*(_xlpm.printCosts=0)*(_xlpm.printWaste=0)*(_xlpm.filmCosts>0))),INDEX(_xlfn._xlws.FILTER(_xlpm.filmCosts,(UPPER(SUBSTITUTE(_xlpm.filmNames," ",""))="TIPA312MFG")*(_xlpm.filmCosts>0)),1)),0), _xlpm.metluxCost,IFERROR(INDEX([6]HELPER!$E$2:$E$32,MATCH(TRUE,TRIM([6]HELPER!$A$2:$A$32)="MET LUX",0)),IFERROR(INDEX([6]HELPER!$E$2:$E$32,MATCH(TRUE,TRIM([6]HELPER!$B$2:$B$32)="MET LUX",0)),IFERROR(INDEX([6]HELPER!$E$2:$E$32,MATCH(TRUE,TRIM([6]HELPER!$C$2:$C$32)="MET LUX",0)),IFERROR(INDEX([6]HELPER!$E$2:$E$32,MATCH(TRUE,TRIM([6]HELPER!$D$2:$D$32)="MET LUX",0)),0)))), _xlpm.helperCost,IFERROR(INDEX([6]HELPER!$E$2:$E$32,MATCH(TRUE,TRIM([6]HELPER!$A$2:$A$32)=_xlpm.mat,0)),IFERROR(INDEX([6]HELPER!$E$2:$E$32,MATCH(TRUE,TRIM([6]HELPER!$B$2:$B$32)=_xlpm.mat,0)),IFERROR(INDEX([6]HELPER!$E$2:$E$32,MATCH(TRUE,TRIM([6]HELPER!$C$2:$C$32)=_xlpm.mat,0)),IFERROR(INDEX([6]HELPER!$E$2:$E$32,MATCH(TRUE,TRIM([6]HELPER!$D$2:$D$32)=_xlpm.mat,0)),"")))), _xlpm.specialCost,IFERROR(_xlfn.XLOOKUP(_xlpm.mat,[6]HELPER!$CK$2:$CK$105,[6]HELPER!$CO$2:$CO$105,""),""), _xlpm.nkHelperCost,IFERROR(INDEX([6]HELPER!$E$2:$E$32,MATCH(TRUE,TRIM([6]HELPER!$A$2:$A$32)="NK",0)),IFERROR(INDEX([6]HELPER!$E$2:$E$32,MATCH(TRUE,TRIM([6]HELPER!$B$2:$B$32)="NK",0)),IFERROR(INDEX([6]HELPER!$E$2:$E$32,MATCH(TRUE,TRIM([6]HELPER!$C$2:$C$32)="NK",0)),IFERROR(INDEX([6]HELPER!$E$2:$E$32,MATCH(TRUE,TRIM([6]HELPER!$D$2:$D$32)="NK",0)),0)))), _xlpm.baseCost,IF(LEFT(_xlpm.mat,4)="TIPA",IF(_xlpm.finalFilmCost<>"",_xlpm.finalFilmCost,_xlpm.specialCost),_xlpm.helperCost), _xlpm.rawResult,IF(OR(_xlpm.mat="NK",_xlpm.mat="NKR"),_xlpm.nkHelperCost,IF(_xlpm.baseCost="","",IF(OR(_xlpm.finalFilmCost<>"",LEFT(_xlpm.mat,4)="TIPA"),_xlpm.baseCost,_xlpm.baseCost+_xlpm.euShip))), _xlpm.upliftFilm,ISNUMBER(MATCH(_xlpm.matKey,{"TIPA312MET";"TIPA302FG";"TIPA302FGW";"TIPA306M";"TIPA306W";"TIPA312MFG";"TIPA312MFGW"},0)), IF(AND(_xlpm.upliftFilm,_xlpm.widthActual>=900,_xlpm.rawResult<>""),_xlpm.rawResult*1.25,_xlpm.rawResult) ))} | AG25: (Lamination €/kg) | AH25: {=IF(OR(AND(AH13="By Weight",AH6<>""),AND(AH13="By Length",AH14<>""),AND(OR(AH13="IMP",AH13="By Imp"),AH14<>"",AH15<>"")),IFERROR(_xlfn.LET(_xlpm.r,MATCH(1,($B$3:$B$20=AH3)*($D$3:$D$20=AH5)*($A$3:$A$20=IF(AH6<>"",AH6,A3))*($O$3:$O$20=AH11)*($K$8:$K$25=AH4),0)+2,INDEX($R$3:$R$20,_xlpm.r-2)*(1/INDEX($M$3:$M$20,MATCH(1,($B$3:$B$20=AH3)*($D$3:$D$20=AH5)*($A$3:$A$20=IF(AH6<>"",AH6,A3))*($O$3:$O$20=AH11)*($K$8:$K$25=AH4),0)+5))*(INDEX($J$3:$J$20,_xlpm.r-2)/INDEX($E$3:$E$20,_xlpm.r-2))),""),"")} -> 2.533896 | AK25: (Lam €/kg) | AL25: {=IF(OR(AND(AL13="By Weight",AL6<>""),AND(AL13="By Length",AL14<>""),AND(OR(AL13="IMP",AL13="By Imp"),AL14<>"",AL15<>"")),IFERROR(_xlfn.LET(_xlpm.r,MATCH(1,($B$3:$B$20=AL3)*($D$3:$D$20=AL5)*($A$3:$A$20=IF(AL6<>"",AL6,A9))*($O$3:$O$20=AL11)*($K$8:$K$25=AL4),0)+2,INDEX($R$3:$R$20,_xlpm.r-2)*(1/INDEX($M$3:$M$20,MATCH(1,($B$3:$B$20=AL3)*($D$3:$D$20=AL5)*($A$3:$A$20=IF(AL6<>"",AL6,A9))*($O$3:$O$20=AL11)*($K$8:$K$25=AL4),0)+5))*(INDEX($J$3:$J$20,_xlpm.r-2)/INDEX($E$3:$E$20,_xlpm.r-2))),""),"")} -> 2.347861 | AO25: (Lam €/kg) | AP25: {=IF(OR(AND(AP13="By Weight",AP6<>""),AND(AP13="By Length",AP14<>""),AND(OR(AP13="IMP",AP13="By Imp"),AP14<>"",AP15<>"")),IFERROR(_xlfn.LET(_xlpm.r,MATCH(1,($B$3:$B$20=AP3)*($D$3:$D$20=AP5)*($A$3:$A$20=IF(AP6<>"",AP6,A15))*($O$3:$O$20=AP11),0)+2,INDEX($R$3:$R$20,_xlpm.r-2)*(1/INDEX($M$3:$M$20,MATCH(1,($B$3:$B$20=AP3)*($D$3:$D$20=AP5)*($A$3:$A$20=IF(AP6<>"",AP6,A15))*($O$3:$O$20=AP11),0)+5))*(INDEX($J$3:$J$20,_xlpm.r-2)/INDEX($E$3:$E$20,_xlpm.r-2))),""),"")} -> 2.3246067
J26: =IF($C26="","",IF($E$15="","",IF(ISNUMBER($E$15),_xlfn.LET(_xlpm.cap,IF($Q$15="Quantum",760,1220),IF($E$15+50>_xlpm.cap,"ERROR: Lamination Width > "&_xlpm.cap,$E$15+50)),$E$15))) | N26: {=IF($C26="","",_xlfn.LET( _xlpm.mat,TRIM($C26), _xlpm.matKey,UPPER(SUBSTITUTE(_xlpm.mat," ","")), _xlpm.pr,IFERROR(LOOKUP(2,1/($H$3:H26<>""),$H$3:H26),""), _xlpm.widthActual,IFERROR(LOOKUP(2,1/($E$3:E26<>""),$E$3:E26),$E26), _xlpm.euShip,IFERROR([6]HELPER!$AH$3,0), _xlpm.metSetup,IFERROR([6]HELPER!$CH$2,0), _xlpm.filmNames,[6]!Table1[Film Type], _xlpm.filmCosts,[6]!Table1[Total Cost], _xlpm.printCosts,[6]!Table1[Printing], _xlpm.printWaste,[6]!Table1[Printing Waste], _xlpm.filmCost,IF(LEFT(_xlpm.mat,4)="TIPA",IFERROR(IF(_xlpm.pr="Not Printed",MIN(_xlfn._xlws.FILTER(_xlpm.filmCosts,(UPPER(SUBSTITUTE(_xlpm.filmNames," ",""))=_xlpm.matKey)*(_xlpm.printCosts=0)*(_xlpm.printWaste=0)*(_xlpm.filmCosts>0))),INDEX(_xlfn._xlws.FILTER(_xlpm.filmCosts,(UPPER(SUBSTITUTE(_xlpm.filmNames," ",""))=_xlpm.matKey)*(_xlpm.filmCosts>0)),1)),""),""), _xlpm.summaryNames,"", _xlpm.summaryThick,"", _xlpm.summaryCosts,"", _xlpm.summaryCost,IF(LEFT(_xlpm.mat,4)="TIPA",IFERROR(IF(_xlpm.pr="Not Printed",MIN(_xlfn._xlws.FILTER(_xlpm.summaryCosts,(UPPER(SUBSTITUTE(_xlpm.summaryNames," ",""))=_xlpm.matKey)*(_xlpm.summaryThick=$K26)*(_xlpm.summaryCosts>0))),INDEX(_xlfn._xlws.FILTER(_xlpm.summaryCosts,(UPPER(SUBSTITUTE(_xlpm.summaryNames," ",""))=_xlpm.matKey)*(_xlpm.summaryThick=$K26)*(_xlpm.summaryCosts>0)),1)),""),""), _xlpm.finalFilmCost,IF(_xlpm.filmCost<>"",_xlpm.filmCost,_xlpm.summaryCost), _xlpm.metFilmCost,IFERROR(INDEX(_xlpm.filmCosts,MATCH("TIPA 312 MFG",_xlpm.filmNames,0)),INDEX(_xlpm.filmCosts,1)), _xlpm.tipa312MfgCost,IFERROR(IF(_xlpm.pr="Not Printed",MIN(_xlfn._xlws.FILTER(_xlpm.filmCosts,(UPPER(SUBSTITUTE(_xlpm.filmNames," ",""))="TIPA312MFG")*(_xlpm.printCosts=0)*(_xlpm.printWaste=0)*(_xlpm.filmCosts>0))),INDEX(_xlfn._xlws.FILTER(_xlpm.filmCosts,(UPPER(SUBSTITUTE(_xlpm.filmNames," ",""))="TIPA312MFG")*(_xlpm.filmCosts>0)),1)),0), _xlpm.metluxCost,IFERROR(INDEX([6]HELPER!$E$2:$E$32,MATCH(TRUE,TRIM([6]HELPER!$A$2:$A$32)="MET LUX",0)),IFERROR(INDEX([6]HELPER!$E$2:$E$32,MATCH(TRUE,TRIM([6]HELPER!$B$2:$B$32)="MET LUX",0)),IFERROR(INDEX([6]HELPER!$E$2:$E$32,MATCH(TRUE,TRIM([6]HELPER!$C$2:$C$32)="MET LUX",0)),IFERROR(INDEX([6]HELPER!$E$2:$E$32,MATCH(TRUE,TRIM([6]HELPER!$D$2:$D$32)="MET LUX",0)),0)))), _xlpm.helperCost,IFERROR(INDEX([6]HELPER!$E$2:$E$32,MATCH(TRUE,TRIM([6]HELPER!$A$2:$A$32)=_xlpm.mat,0)),IFERROR(INDEX([6]HELPER!$E$2:$E$32,MATCH(TRUE,TRIM([6]HELPER!$B$2:$B$32)=_xlpm.mat,0)),IFERROR(INDEX([6]HELPER!$E$2:$E$32,MATCH(TRUE,TRIM([6]HELPER!$C$2:$C$32)=_xlpm.mat,0)),IFERROR(INDEX([6]HELPER!$E$2:$E$32,MATCH(TRUE,TRIM([6]HELPER!$D$2:$D$32)=_xlpm.mat,0)),"")))), _xlpm.specialCost,IFERROR(_xlfn.XLOOKUP(_xlpm.mat,[6]HELPER!$CK$2:$CK$105,[6]HELPER!$CO$2:$CO$105,""),""), _xlpm.nkHelperCost,IFERROR(INDEX([6]HELPER!$E$2:$E$32,MATCH(TRUE,TRIM([6]HELPER!$A$2:$A$32)="NK",0)),IFERROR(INDEX([6]HELPER!$E$2:$E$32,MATCH(TRUE,TRIM([6]HELPER!$B$2:$B$32)="NK",0)),IFERROR(INDEX([6]HELPER!$E$2:$E$32,MATCH(TRUE,TRIM([6]HELPER!$C$2:$C$32)="NK",0)),IFERROR(INDEX([6]HELPER!$E$2:$E$32,MATCH(TRUE,TRIM([6]HELPER!$D$2:$D$32)="NK",0)),0)))), _xlpm.baseCost,IF(LEFT(_xlpm.mat,4)="TIPA",IF(_xlpm.finalFilmCost<>"",_xlpm.finalFilmCost,_xlpm.specialCost),_xlpm.helperCost), _xlpm.rawResult,IF(OR(_xlpm.mat="NK",_xlpm.mat="NKR"),_xlpm.nkHelperCost,IF(_xlpm.baseCost="","",IF(OR(_xlpm.finalFilmCost<>"",LEFT(_xlpm.mat,4)="TIPA"),_xlpm.baseCost,_xlpm.baseCost+_xlpm.euShip))), _xlpm.upliftFilm,ISNUMBER(MATCH(_xlpm.matKey,{"TIPA312MET";"TIPA302FG";"TIPA302FGW";"TIPA306M";"TIPA306W";"TIPA312MFG";"TIPA312MFGW"},0)), IF(AND(_xlpm.upliftFilm,_xlpm.widthActual>=900,_xlpm.rawResult<>""),_xlpm.rawResult*1.25,_xlpm.rawResult) ))} | AG26: (Lam + Slit + Print €/kg) | AH26: {=IF(OR(AND(AH13="By Weight",AH6<>""),AND(AH13="By Length",AH14<>""),AND(OR(AH13="IMP",AH13="By Imp"),AH14<>"",AH15<>"")),IFERROR(_xlfn.LET(_xlpm.r,MATCH(1,($B$3:$B$20=AH3)*($D$3:$D$20=AH5)*($A$3:$A$20=IF(AH6<>"",AH6,A3))*($O$3:$O$20=AH11)*($K$8:$K$25=AH4),0)+2,(SUM(INDEX($R$3:$S$20,_xlpm.r-2,1):INDEX($R$3:$S$20,_xlpm.r-2,2))+INDEX($U$3:$U$20,_xlpm.r-2))*(1/INDEX($M$3:$M$20,MATCH(1,($B$3:$B$20=AH3)*($D$3:$D$20=AH5)*($A$3:$A$20=IF(AH6<>"",AH6,A3))*($O$3:$O$20=AH11)*($K$8:$K$25=AH4),0)+5))*(INDEX($J$3:$J$20,_xlpm.r-2)/INDEX($E$3:$E$20,_xlpm.r-2))+INDEX($W$3:$W$20,_xlpm.r-2)),""),"")} -> 6.3946875 | AK26: (Lam + Slit + Print) | AL26: {=IF(OR(AND(AL13="By Weight",AL6<>""),AND(AL13="By Length",AL14<>""),AND(OR(AL13="IMP",AL13="By Imp"),AL14<>"",AL15<>"")),IFERROR(_xlfn.LET(_xlpm.r,MATCH(1,($B$3:$B$20=AL3)*($D$3:$D$20=AL5)*($A$3:$A$20=IF(AL6<>"",AL6,A9))*($O$3:$O$20=AL11)*($K$8:$K$25=AL4),0)+2,(SUM(INDEX($R$3:$S$20,_xlpm.r-2,1):INDEX($R$3:$S$20,_xlpm.r-2,2))+INDEX($U$3:$U$20,_xlpm.r-2))*(1/INDEX($M$3:$M$20,MATCH(1,($B$3:$B$20=AL3)*($D$3:$D$20=AL5)*($A$3:$A$20=IF(AL6<>"",AL6,A9))*($O$3:$O$20=AL11)*($K$8:$K$25=AL4),0)+5))*(INDEX($J$3:$J$20,_xlpm.r-2)/INDEX($E$3:$E$20,_xlpm.r-2))+INDEX($W$3:$W$20,_xlpm.r-2)),""),"")} -> 4.8183632 | AO26: (Lam + Slit + Print) | AP26: {=IF(OR(AND(AP13="By Weight",AP6<>""),AND(AP13="By Length",AP14<>""),AND(OR(AP13="IMP",AP13="By Imp"),AP14<>"",AP15<>"")),IFERROR(_xlfn.LET(_xlpm.r,MATCH(1,($B$3:$B$20=AP3)*($D$3:$D$20=AP5)*($A$3:$A$20=IF(AP6<>"",AP6,A15))*($O$3:$O$20=AP11),0)+2,(SUM(INDEX($R$3:$S$20,_xlpm.r-2,1):INDEX($R$3:$S$20,_xlpm.r-2,2))+INDEX($U$3:$U$20,_xlpm.r-2))*(1/INDEX($M$3:$M$20,MATCH(1,($B$3:$B$20=AP3)*($D$3:$D$20=AP5)*($A$3:$A$20=IF(AP6<>"",AP6,A15))*($O$3:$O$20=AP11),0)+5))*(INDEX($J$3:$J$20,_xlpm.r-2)/INDEX($E$3:$E$20,_xlpm.r-2))+INDEX($W$3:$W$20,_xlpm.r-2)),""),"")} -> 4.2892119
AG27: 💵 SELL PRICE PER KG | AK27: 💵 SELL PRICE PER KG | AO27: 💵 SELL PRICE PER KG
AG28: =IF(AH39<>"",IFERROR(AH19/(1-AH1),""),"") -> 17.65439 | AK28: =IF(AL39<>"",IFERROR(AL19/(1-AL1),""),"") -> 15.663775 | AO28: =IF(AP39<>"",IFERROR(AP19/(1-AP1),""),"") -> 15.02423
J29: =IF($C29="","",IF($E$15="","",IF(ISNUMBER($E$15),_xlfn.LET(_xlpm.cap,IF($Q$15="Quantum",760,1220),IF($E$15+50>_xlpm.cap,"ERROR: Lamination Width > "&_xlpm.cap,$E$15+50)),$E$15))) | N29: {=IF($C29="","",_xlfn.LET( _xlpm.mat,TRIM($C29), _xlpm.matKey,UPPER(SUBSTITUTE(_xlpm.mat," ","")), _xlpm.pr,IFERROR(LOOKUP(2,1/($H$3:H29<>""),$H$3:H29),""), _xlpm.widthActual,IFERROR(LOOKUP(2,1/($E$3:E29<>""),$E$3:E29),$E29), _xlpm.euShip,IFERROR([6]HELPER!$AH$3,0), _xlpm.metSetup,IFERROR([6]HELPER!$CH$2,0), _xlpm.filmNames,[6]!Table1[Film Type], _xlpm.filmCosts,[6]!Table1[Total Cost], _xlpm.printCosts,[6]!Table1[Printing], _xlpm.printWaste,[6]!Table1[Printing Waste], _xlpm.filmCost,IF(LEFT(_xlpm.mat,4)="TIPA",IFERROR(IF(_xlpm.pr="Not Printed",MIN(_xlfn._xlws.FILTER(_xlpm.filmCosts,(UPPER(SUBSTITUTE(_xlpm.filmNames," ",""))=_xlpm.matKey)*(_xlpm.printCosts=0)*(_xlpm.printWaste=0)*(_xlpm.filmCosts>0))),INDEX(_xlfn._xlws.FILTER(_xlpm.filmCosts,(UPPER(SUBSTITUTE(_xlpm.filmNames," ",""))=_xlpm.matKey)*(_xlpm.filmCosts>0)),1)),""),""), _xlpm.summaryNames,"", _xlpm.summaryThick,"", _xlpm.summaryCosts,"", _xlpm.summaryCost,IF(LEFT(_xlpm.mat,4)="TIPA",IFERROR(IF(_xlpm.pr="Not Printed",MIN(_xlfn._xlws.FILTER(_xlpm.summaryCosts,(UPPER(SUBSTITUTE(_xlpm.summaryNames," ",""))=_xlpm.matKey)*(_xlpm.summaryThick=$K29)*(_xlpm.summaryCosts>0))),INDEX(_xlfn._xlws.FILTER(_xlpm.summaryCosts,(UPPER(SUBSTITUTE(_xlpm.summaryNames," ",""))=_xlpm.matKey)*(_xlpm.summaryThick=$K29)*(_xlpm.summaryCosts>0)),1)),""),""), _xlpm.finalFilmCost,IF(_xlpm.filmCost<>"",_xlpm.filmCost,_xlpm.summaryCost), _xlpm.metFilmCost,IFERROR(INDEX(_xlpm.filmCosts,MATCH("TIPA 312 MFG",_xlpm.filmNames,0)),INDEX(_xlpm.filmCosts,1)), _xlpm.tipa312MfgCost,IFERROR(IF(_xlpm.pr="Not Printed",MIN(_xlfn._xlws.FILTER(_xlpm.filmCosts,(UPPER(SUBSTITUTE(_xlpm.filmNames," ",""))="TIPA312MFG")*(_xlpm.printCosts=0)*(_xlpm.printWaste=0)*(_xlpm.filmCosts>0))),INDEX(_xlfn._xlws.FILTER(_xlpm.filmCosts,(UPPER(SUBSTITUTE(_xlpm.filmNames," ",""))="TIPA312MFG")*(_xlpm.filmCosts>0)),1)),0), _xlpm.metluxCost,IFERROR(INDEX([6]HELPER!$E$2:$E$32,MATCH(TRUE,TRIM([6]HELPER!$A$2:$A$32)="MET LUX",0)),IFERROR(INDEX([6]HELPER!$E$2:$E$32,MATCH(TRUE,TRIM([6]HELPER!$B$2:$B$32)="MET LUX",0)),IFERROR(INDEX([6]HELPER!$E$2:$E$32,MATCH(TRUE,TRIM([6]HELPER!$C$2:$C$32)="MET LUX",0)),IFERROR(INDEX([6]HELPER!$E$2:$E$32,MATCH(TRUE,TRIM([6]HELPER!$D$2:$D$32)="MET LUX",0)),0)))), _xlpm.helperCost,IFERROR(INDEX([6]HELPER!$E$2:$E$32,MATCH(TRUE,TRIM([6]HELPER!$A$2:$A$32)=_xlpm.mat,0)),IFERROR(INDEX([6]HELPER!$E$2:$E$32,MATCH(TRUE,TRIM([6]HELPER!$B$2:$B$32)=_xlpm.mat,0)),IFERROR(INDEX([6]HELPER!$E$2:$E$32,MATCH(TRUE,TRIM([6]HELPER!$C$2:$C$32)=_xlpm.mat,0)),IFERROR(INDEX([6]HELPER!$E$2:$E$32,MATCH(TRUE,TRIM([6]HELPER!$D$2:$D$32)=_xlpm.mat,0)),"")))), _xlpm.specialCost,IFERROR(_xlfn.XLOOKUP(_xlpm.mat,[6]HELPER!$CK$2:$CK$105,[6]HELPER!$CO$2:$CO$105,""),""), _xlpm.nkHelperCost,IFERROR(INDEX([6]HELPER!$E$2:$E$32,MATCH(TRUE,TRIM([6]HELPER!$A$2:$A$32)="NK",0)),IFERROR(INDEX([6]HELPER!$E$2:$E$32,MATCH(TRUE,TRIM([6]HELPER!$B$2:$B$32)="NK",0)),IFERROR(INDEX([6]HELPER!$E$2:$E$32,MATCH(TRUE,TRIM([6]HELPER!$C$2:$C$32)="NK",0)),IFERROR(INDEX([6]HELPER!$E$2:$E$32,MATCH(TRUE,TRIM([6]HELPER!$D$2:$D$32)="NK",0)),0)))), _xlpm.baseCost,IF(LEFT(_xlpm.mat,4)="TIPA",IF(_xlpm.finalFilmCost<>"",_xlpm.finalFilmCost,_xlpm.specialCost),_xlpm.helperCost), _xlpm.rawResult,IF(OR(_xlpm.mat="NK",_xlpm.mat="NKR"),_xlpm.nkHelperCost,IF(_xlpm.baseCost="","",IF(OR(_xlpm.finalFilmCost<>"",LEFT(_xlpm.mat,4)="TIPA"),_xlpm.baseCost,_xlpm.baseCost+_xlpm.euShip))), _xlpm.upliftFilm,ISNUMBER(MATCH(_xlpm.matKey,{"TIPA312MET";"TIPA302FG";"TIPA302FGW";"TIPA306M";"TIPA306W";"TIPA312MFG";"TIPA312MFGW"},0)), IF(AND(_xlpm.upliftFilm,_xlpm.widthActual>=900,_xlpm.rawResult<>""),_xlpm.rawResult*1.25,_xlpm.rawResult) ))} | T29: =IF(OR($S29="",$K29=""),"",IFERROR($S29*(1/$M$37)*($J29/($D29*MAX(1,ROUNDDOWN(760/$D29,0)))),"")) | AG29: 💵 Sell Price / Meter | AH29: =IF(OR(AH16="",AH39=""),"",IFERROR(AG28*AH39/AH16,"")) -> 0.64404877 | AI29: €/m | AK29: 💵 Sell Price / Meter | AL29: =IF(OR(AL16="",AL39=""),"",IFERROR(AK28*AL39/AL16,"")) -> 0.56693437 | AM29: €/m | AO29: 💵 Sell Price / Meter | AP29: =IF(OR(AP16="",AP39=""),"",IFERROR(AO28*AP39/AP16,"")) -> 0.54324775 | AQ29: €/m
AG30: 💵 Sell Price / KG | AH30: =IFERROR(AG28,"") -> 17.65439 | AI30: €/kg | AK30: 💵 Sell Price / KG | AL30: =IFERROR(AK28,"") -> 15.663775 | AM30: €/kg | AO30: 💵 Sell Price / KG | AP30: =IFERROR(AO28,"") -> 15.02423 | AQ30: €/kg
AG31: 💵 Sell Price / IMP | AH31: =IF(OR(AH29="",AH5="",AH15="",AI15=""),"",IFERROR(AH29*(AI15/1000)/ROUNDDOWN(AH5/AH15,0),"")) | AI31: €/IMP | AK31: 💵 Sell Price / IMP | AL31: =IF(OR(AL29="",AL5="",AL15="",AM15=""),"",IFERROR(AL29*(AM15/1000)/ROUNDDOWN(AL5/AL15,0),"")) | AM31: €/IMP | AO31: 💵 Sell Price / IMP | AP31: =IF(OR(AP29="",AP5="",AP15="",AQ15=""),"",IFERROR(AP29*(AQ15/1000)/ROUNDDOWN(AP5/AP15,0),"")) | AQ31: €/IMP
J32: =IF($C32="","",IF($E$15="","",IF(ISNUMBER($E$15),_xlfn.LET(_xlpm.cap,IF($Q$15="Quantum",760,1220),IF($E$15+50>_xlpm.cap,"ERROR: Lamination Width > "&_xlpm.cap,$E$15+50)),$E$15))) | N32: {=IF($C32="","",_xlfn.LET( _xlpm.mat,TRIM($C32), _xlpm.matKey,UPPER(SUBSTITUTE(_xlpm.mat," ","")), _xlpm.pr,IFERROR(LOOKUP(2,1/($H$3:H32<>""),$H$3:H32),""), _xlpm.widthActual,IFERROR(LOOKUP(2,1/($E$3:E32<>""),$E$3:E32),$E32), _xlpm.euShip,IFERROR([6]HELPER!$AH$3,0), _xlpm.metSetup,IFERROR([6]HELPER!$CH$2,0), _xlpm.filmNames,[6]!Table1[Film Type], _xlpm.filmCosts,[6]!Table1[Total Cost], _xlpm.printCosts,[6]!Table1[Printing], _xlpm.printWaste,[6]!Table1[Printing Waste], _xlpm.filmCost,IF(LEFT(_xlpm.mat,4)="TIPA",IFERROR(IF(_xlpm.pr="Not Printed",MIN(_xlfn._xlws.FILTER(_xlpm.filmCosts,(UPPER(SUBSTITUTE(_xlpm.filmNames," ",""))=_xlpm.matKey)*(_xlpm.printCosts=0)*(_xlpm.printWaste=0)*(_xlpm.filmCosts>0))),INDEX(_xlfn._xlws.FILTER(_xlpm.filmCosts,(UPPER(SUBSTITUTE(_xlpm.filmNames," ",""))=_xlpm.matKey)*(_xlpm.filmCosts>0)),1)),""),""), _xlpm.summaryNames,"", _xlpm.summaryThick,"", _xlpm.summaryCosts,"", _xlpm.summaryCost,IF(LEFT(_xlpm.mat,4)="TIPA",IFERROR(IF(_xlpm.pr="Not Printed",MIN(_xlfn._xlws.FILTER(_xlpm.summaryCosts,(UPPER(SUBSTITUTE(_xlpm.summaryNames," ",""))=_xlpm.matKey)*(_xlpm.summaryThick=$K32)*(_xlpm.summaryCosts>0))),INDEX(_xlfn._xlws.FILTER(_xlpm.summaryCosts,(UPPER(SUBSTITUTE(_xlpm.summaryNames," ",""))=_xlpm.matKey)*(_xlpm.summaryThick=$K32)*(_xlpm.summaryCosts>0)),1)),""),""), _xlpm.finalFilmCost,IF(_xlpm.filmCost<>"",_xlpm.filmCost,_xlpm.summaryCost), _xlpm.metFilmCost,IFERROR(INDEX(_xlpm.filmCosts,MATCH("TIPA 312 MFG",_xlpm.filmNames,0)),INDEX(_xlpm.filmCosts,1)), _xlpm.tipa312MfgCost,IFERROR(IF(_xlpm.pr="Not Printed",MIN(_xlfn._xlws.FILTER(_xlpm.filmCosts,(UPPER(SUBSTITUTE(_xlpm.filmNames," ",""))="TIPA312MFG")*(_xlpm.printCosts=0)*(_xlpm.printWaste=0)*(_xlpm.filmCosts>0))),INDEX(_xlfn._xlws.FILTER(_xlpm.filmCosts,(UPPER(SUBSTITUTE(_xlpm.filmNames," ",""))="TIPA312MFG")*(_xlpm.filmCosts>0)),1)),0), _xlpm.metluxCost,IFERROR(INDEX([6]HELPER!$E$2:$E$32,MATCH(TRUE,TRIM([6]HELPER!$A$2:$A$32)="MET LUX",0)),IFERROR(INDEX([6]HELPER!$E$2:$E$32,MATCH(TRUE,TRIM([6]HELPER!$B$2:$B$32)="MET LUX",0)),IFERROR(INDEX([6]HELPER!$E$2:$E$32,MATCH(TRUE,TRIM([6]HELPER!$C$2:$C$32)="MET LUX",0)),IFERROR(INDEX([6]HELPER!$E$2:$E$32,MATCH(TRUE,TRIM([6]HELPER!$D$2:$D$32)="MET LUX",0)),0)))), _xlpm.helperCost,IFERROR(INDEX([6]HELPER!$E$2:$E$32,MATCH(TRUE,TRIM([6]HELPER!$A$2:$A$32)=_xlpm.mat,0)),IFERROR(INDEX([6]HELPER!$E$2:$E$32,MATCH(TRUE,TRIM([6]HELPER!$B$2:$B$32)=_xlpm.mat,0)),IFERROR(INDEX([6]HELPER!$E$2:$E$32,MATCH(TRUE,TRIM([6]HELPER!$C$2:$C$32)=_xlpm.mat,0)),IFERROR(INDEX([6]HELPER!$E$2:$E$32,MATCH(TRUE,TRIM([6]HELPER!$D$2:$D$32)=_xlpm.mat,0)),"")))), _xlpm.specialCost,IFERROR(_xlfn.XLOOKUP(_xlpm.mat,[6]HELPER!$CK$2:$CK$105,[6]HELPER!$CO$2:$CO$105,""),""), _xlpm.nkHelperCost,IFERROR(INDEX([6]HELPER!$E$2:$E$32,MATCH(TRUE,TRIM([6]HELPER!$A$2:$A$32)="NK",0)),IFERROR(INDEX([6]HELPER!$E$2:$E$32,MATCH(TRUE,TRIM([6]HELPER!$B$2:$B$32)="NK",0)),IFERROR(INDEX([6]HELPER!$E$2:$E$32,MATCH(TRUE,TRIM([6]HELPER!$C$2:$C$32)="NK",0)),IFERROR(INDEX([6]HELPER!$E$2:$E$32,MATCH(TRUE,TRIM([6]HELPER!$D$2:$D$32)="NK",0)),0)))), _xlpm.baseCost,IF(LEFT(_xlpm.mat,4)="TIPA",IF(_xlpm.finalFilmCost<>"",_xlpm.finalFilmCost,_xlpm.specialCost),_xlpm.helperCost), _xlpm.rawResult,IF(OR(_xlpm.mat="NK",_xlpm.mat="NKR"),_xlpm.nkHelperCost,IF(_xlpm.baseCost="","",IF(OR(_xlpm.finalFilmCost<>"",LEFT(_xlpm.mat,4)="TIPA"),_xlpm.baseCost,_xlpm.baseCost+_xlpm.euShip))), _xlpm.upliftFilm,ISNUMBER(MATCH(_xlpm.matKey,{"TIPA312MET";"TIPA302FG";"TIPA302FGW";"TIPA306M";"TIPA306W";"TIPA312MFG";"TIPA312MFGW"},0)), IF(AND(_xlpm.upliftFilm,_xlpm.widthActual>=900,_xlpm.rawResult<>""),_xlpm.rawResult*1.25,_xlpm.rawResult) ))} | AG32: 💵 USD Price / Meter | AH32: =IFERROR(AH29*1.16,"") -> 0.74709657 | AI32: $/m | AK32: 💵 USD Price / Meter | AL32: =IFERROR(AL29*1.16,"") -> 0.65764386 | AM32: $/m | AO32: 💵 USD Price / Meter | AP32: =IFERROR(AP29*1.16,"") -> 0.63016739 | AQ32: $/m
AG33: 💵 USD Price / KG | AH33: =IFERROR(AH30*1.16,"") -> 20.479093 | AI33: $/kg | AK33: 💵 USD Price / KG | AL33: =IFERROR(AL30*1.16,"") -> 18.169979 | AM33: $/kg | AO33: 💵 USD Price / KG | AP33: =IFERROR(AP30*1.16,"") -> 17.428106 | AQ33: $/kg
J34: =IF($C34="","",IF($E$15="","",IF(ISNUMBER($E$15),_xlfn.LET(_xlpm.cap,IF($Q$15="Quantum",760,1220),IF($E$15+50>_xlpm.cap,"ERROR: Lamination Width > "&_xlpm.cap,$E$15+50)),$E$15))) | N34: {=IF($C34="","",_xlfn.LET( _xlpm.mat,TRIM($C34), _xlpm.matKey,UPPER(SUBSTITUTE(_xlpm.mat," ","")), _xlpm.pr,IFERROR(LOOKUP(2,1/($H$3:H34<>""),$H$3:H34),""), _xlpm.widthActual,IFERROR(LOOKUP(2,1/($E$3:E34<>""),$E$3:E34),$E34), _xlpm.euShip,IFERROR([6]HELPER!$AH$3,0), _xlpm.metSetup,IFERROR([6]HELPER!$CH$2,0), _xlpm.filmNames,[6]!Table1[Film Type], _xlpm.filmCosts,[6]!Table1[Total Cost], _xlpm.printCosts,[6]!Table1[Printing], _xlpm.printWaste,[6]!Table1[Printing Waste], _xlpm.filmCost,IF(LEFT(_xlpm.mat,4)="TIPA",IFERROR(IF(_xlpm.pr="Not Printed",MIN(_xlfn._xlws.FILTER(_xlpm.filmCosts,(UPPER(SUBSTITUTE(_xlpm.filmNames," ",""))=_xlpm.matKey)*(_xlpm.printCosts=0)*(_xlpm.printWaste=0)*(_xlpm.filmCosts>0))),INDEX(_xlfn._xlws.FILTER(_xlpm.filmCosts,(UPPER(SUBSTITUTE(_xlpm.filmNames," ",""))=_xlpm.matKey)*(_xlpm.filmCosts>0)),1)),""),""), _xlpm.summaryNames,"", _xlpm.summaryThick,"", _xlpm.summaryCosts,"", _xlpm.summaryCost,IF(LEFT(_xlpm.mat,4)="TIPA",IFERROR(IF(_xlpm.pr="Not Printed",MIN(_xlfn._xlws.FILTER(_xlpm.summaryCosts,(UPPER(SUBSTITUTE(_xlpm.summaryNames," ",""))=_xlpm.matKey)*(_xlpm.summaryThick=$K34)*(_xlpm.summaryCosts>0))),INDEX(_xlfn._xlws.FILTER(_xlpm.summaryCosts,(UPPER(SUBSTITUTE(_xlpm.summaryNames," ",""))=_xlpm.matKey)*(_xlpm.summaryThick=$K34)*(_xlpm.summaryCosts>0)),1)),""),""), _xlpm.finalFilmCost,IF(_xlpm.filmCost<>"",_xlpm.filmCost,_xlpm.summaryCost), _xlpm.metFilmCost,IFERROR(INDEX(_xlpm.filmCosts,MATCH("TIPA 312 MFG",_xlpm.filmNames,0)),INDEX(_xlpm.filmCosts,1)), _xlpm.tipa312MfgCost,IFERROR(IF(_xlpm.pr="Not Printed",MIN(_xlfn._xlws.FILTER(_xlpm.filmCosts,(UPPER(SUBSTITUTE(_xlpm.filmNames," ",""))="TIPA312MFG")*(_xlpm.printCosts=0)*(_xlpm.printWaste=0)*(_xlpm.filmCosts>0))),INDEX(_xlfn._xlws.FILTER(_xlpm.filmCosts,(UPPER(SUBSTITUTE(_xlpm.filmNames," ",""))="TIPA312MFG")*(_xlpm.filmCosts>0)),1)),0), _xlpm.metluxCost,IFERROR(INDEX([6]HELPER!$E$2:$E$32,MATCH(TRUE,TRIM([6]HELPER!$A$2:$A$32)="MET LUX",0)),IFERROR(INDEX([6]HELPER!$E$2:$E$32,MATCH(TRUE,TRIM([6]HELPER!$B$2:$B$32)="MET LUX",0)),IFERROR(INDEX([6]HELPER!$E$2:$E$32,MATCH(TRUE,TRIM([6]HELPER!$C$2:$C$32)="MET LUX",0)),IFERROR(INDEX([6]HELPER!$E$2:$E$32,MATCH(TRUE,TRIM([6]HELPER!$D$2:$D$32)="MET LUX",0)),0)))), _xlpm.helperCost,IFERROR(INDEX([6]HELPER!$E$2:$E$32,MATCH(TRUE,TRIM([6]HELPER!$A$2:$A$32)=_xlpm.mat,0)),IFERROR(INDEX([6]HELPER!$E$2:$E$32,MATCH(TRUE,TRIM([6]HELPER!$B$2:$B$32)=_xlpm.mat,0)),IFERROR(INDEX([6]HELPER!$E$2:$E$32,MATCH(TRUE,TRIM([6]HELPER!$C$2:$C$32)=_xlpm.mat,0)),IFERROR(INDEX([6]HELPER!$E$2:$E$32,MATCH(TRUE,TRIM([6]HELPER!$D$2:$D$32)=_xlpm.mat,0)),"")))), _xlpm.specialCost,IFERROR(_xlfn.XLOOKUP(_xlpm.mat,[6]HELPER!$CK$2:$CK$105,[6]HELPER!$CO$2:$CO$105,""),""), _xlpm.nkHelperCost,IFERROR(INDEX([6]HELPER!$E$2:$E$32,MATCH(TRUE,TRIM([6]HELPER!$A$2:$A$32)="NK",0)),IFERROR(INDEX([6]HELPER!$E$2:$E$32,MATCH(TRUE,TRIM([6]HELPER!$B$2:$B$32)="NK",0)),IFERROR(INDEX([6]HELPER!$E$2:$E$32,MATCH(TRUE,TRIM([6]HELPER!$C$2:$C$32)="NK",0)),IFERROR(INDEX([6]HELPER!$E$2:$E$32,MATCH(TRUE,TRIM([6]HELPER!$D$2:$D$32)="NK",0)),0)))), _xlpm.baseCost,IF(LEFT(_xlpm.mat,4)="TIPA",IF(_xlpm.finalFilmCost<>"",_xlpm.finalFilmCost,_xlpm.specialCost),_xlpm.helperCost), _xlpm.rawResult,IF(OR(_xlpm.mat="NK",_xlpm.mat="NKR"),_xlpm.nkHelperCost,IF(_xlpm.baseCost="","",IF(OR(_xlpm.finalFilmCost<>"",LEFT(_xlpm.mat,4)="TIPA"),_xlpm.baseCost,_xlpm.baseCost+_xlpm.euShip))), _xlpm.upliftFilm,ISNUMBER(MATCH(_xlpm.matKey,{"TIPA312MET";"TIPA302FG";"TIPA302FGW";"TIPA306M";"TIPA306W";"TIPA312MFG";"TIPA312MFGW"},0)), IF(AND(_xlpm.upliftFilm,_xlpm.widthActual>=900,_xlpm.rawResult<>""),_xlpm.rawResult*1.25,_xlpm.rawResult) ))} | AG34: 💵 USD Price / IMP | AH34: =IF(OR(AH32="",AH5="",AH15="",AI15=""),"",IFERROR(AH32*(AI15/1000)/(AH5/AH15),"")) -> 0.39446699 | AI34: $/IMP | AK34: 💵 USD Price / IMP | AL34: =IF(OR(AL32="",AL5="",AL15="",AM15=""),"",IFERROR(AL32*(AM15/1000)/(AL5/AL15),"")) -> 0.34723596 | AM34: $/IMP | AO34: 💵 USD Price / IMP | AP34: =IF(OR(AP32="",AP5="",AP15="",AQ15=""),"",IFERROR(AP32*(AQ15/1000)/(AP5/AP15),"")) -> 0.33272838 | AQ34: $/IMP
J35: =IF($C35="","",IF($E$15="","",IF(ISNUMBER($E$15),_xlfn.LET(_xlpm.cap,IF($Q$15="Quantum",760,1220),IF($E$15+50>_xlpm.cap,"ERROR: Lamination Width > "&_xlpm.cap,$E$15+50)),$E$15))) | N35: {=IF($C35="","",_xlfn.LET( _xlpm.mat,TRIM($C35), _xlpm.matKey,UPPER(SUBSTITUTE(_xlpm.mat," ","")), _xlpm.pr,IFERROR(LOOKUP(2,1/($H$3:H35<>""),$H$3:H35),""), _xlpm.widthActual,IFERROR(LOOKUP(2,1/($E$3:E35<>""),$E$3:E35),$E35), _xlpm.euShip,IFERROR([6]HELPER!$AH$3,0), _xlpm.metSetup,IFERROR([6]HELPER!$CH$2,0), _xlpm.filmNames,[6]!Table1[Film Type], _xlpm.filmCosts,[6]!Table1[Total Cost], _xlpm.printCosts,[6]!Table1[Printing], _xlpm.printWaste,[6]!Table1[Printing Waste], _xlpm.filmCost,IF(LEFT(_xlpm.mat,4)="TIPA",IFERROR(IF(_xlpm.pr="Not Printed",MIN(_xlfn._xlws.FILTER(_xlpm.filmCosts,(UPPER(SUBSTITUTE(_xlpm.filmNames," ",""))=_xlpm.matKey)*(_xlpm.printCosts=0)*(_xlpm.printWaste=0)*(_xlpm.filmCosts>0))),INDEX(_xlfn._xlws.FILTER(_xlpm.filmCosts,(UPPER(SUBSTITUTE(_xlpm.filmNames," ",""))=_xlpm.matKey)*(_xlpm.filmCosts>0)),1)),""),""), _xlpm.summaryNames,"", _xlpm.summaryThick,"", _xlpm.summaryCosts,"", _xlpm.summaryCost,IF(LEFT(_xlpm.mat,4)="TIPA",IFERROR(IF(_xlpm.pr="Not Printed",MIN(_xlfn._xlws.FILTER(_xlpm.summaryCosts,(UPPER(SUBSTITUTE(_xlpm.summaryNames," ",""))=_xlpm.matKey)*(_xlpm.summaryThick=$K35)*(_xlpm.summaryCosts>0))),INDEX(_xlfn._xlws.FILTER(_xlpm.summaryCosts,(UPPER(SUBSTITUTE(_xlpm.summaryNames," ",""))=_xlpm.matKey)*(_xlpm.summaryThick=$K35)*(_xlpm.summaryCosts>0)),1)),""),""), _xlpm.finalFilmCost,IF(_xlpm.filmCost<>"",_xlpm.filmCost,_xlpm.summaryCost), _xlpm.metFilmCost,IFERROR(INDEX(_xlpm.filmCosts,MATCH("TIPA 312 MFG",_xlpm.filmNames,0)),INDEX(_xlpm.filmCosts,1)), _xlpm.tipa312MfgCost,IFERROR(IF(_xlpm.pr="Not Printed",MIN(_xlfn._xlws.FILTER(_xlpm.filmCosts,(UPPER(SUBSTITUTE(_xlpm.filmNames," ",""))="TIPA312MFG")*(_xlpm.printCosts=0)*(_xlpm.printWaste=0)*(_xlpm.filmCosts>0))),INDEX(_xlfn._xlws.FILTER(_xlpm.filmCosts,(UPPER(SUBSTITUTE(_xlpm.filmNames," ",""))="TIPA312MFG")*(_xlpm.filmCosts>0)),1)),0), _xlpm.metluxCost,IFERROR(INDEX([6]HELPER!$E$2:$E$32,MATCH(TRUE,TRIM([6]HELPER!$A$2:$A$32)="MET LUX",0)),IFERROR(INDEX([6]HELPER!$E$2:$E$32,MATCH(TRUE,TRIM([6]HELPER!$B$2:$B$32)="MET LUX",0)),IFERROR(INDEX([6]HELPER!$E$2:$E$32,MATCH(TRUE,TRIM([6]HELPER!$C$2:$C$32)="MET LUX",0)),IFERROR(INDEX([6]HELPER!$E$2:$E$32,MATCH(TRUE,TRIM([6]HELPER!$D$2:$D$32)="MET LUX",0)),0)))), _xlpm.helperCost,IFERROR(INDEX([6]HELPER!$E$2:$E$32,MATCH(TRUE,TRIM([6]HELPER!$A$2:$A$32)=_xlpm.mat,0)),IFERROR(INDEX([6]HELPER!$E$2:$E$32,MATCH(TRUE,TRIM([6]HELPER!$B$2:$B$32)=_xlpm.mat,0)),IFERROR(INDEX([6]HELPER!$E$2:$E$32,MATCH(TRUE,TRIM([6]HELPER!$C$2:$C$32)=_xlpm.mat,0)),IFERROR(INDEX([6]HELPER!$E$2:$E$32,MATCH(TRUE,TRIM([6]HELPER!$D$2:$D$32)=_xlpm.mat,0)),"")))), _xlpm.specialCost,IFERROR(_xlfn.XLOOKUP(_xlpm.mat,[6]HELPER!$CK$2:$CK$105,[6]HELPER!$CO$2:$CO$105,""),""), _xlpm.nkHelperCost,IFERROR(INDEX([6]HELPER!$E$2:$E$32,MATCH(TRUE,TRIM([6]HELPER!$A$2:$A$32)="NK",0)),IFERROR(INDEX([6]HELPER!$E$2:$E$32,MATCH(TRUE,TRIM([6]HELPER!$B$2:$B$32)="NK",0)),IFERROR(INDEX([6]HELPER!$E$2:$E$32,MATCH(TRUE,TRIM([6]HELPER!$C$2:$C$32)="NK",0)),IFERROR(INDEX([6]HELPER!$E$2:$E$32,MATCH(TRUE,TRIM([6]HELPER!$D$2:$D$32)="NK",0)),0)))), _xlpm.baseCost,IF(LEFT(_xlpm.mat,4)="TIPA",IF(_xlpm.finalFilmCost<>"",_xlpm.finalFilmCost,_xlpm.specialCost),_xlpm.helperCost), _xlpm.rawResult,IF(OR(_xlpm.mat="NK",_xlpm.mat="NKR"),_xlpm.nkHelperCost,IF(_xlpm.baseCost="","",IF(OR(_xlpm.finalFilmCost<>"",LEFT(_xlpm.mat,4)="TIPA"),_xlpm.baseCost,_xlpm.baseCost+_xlpm.euShip))), _xlpm.upliftFilm,ISNUMBER(MATCH(_xlpm.matKey,{"TIPA312MET";"TIPA302FG";"TIPA302FGW";"TIPA306M";"TIPA306W";"TIPA312MFG";"TIPA312MFGW"},0)), IF(AND(_xlpm.upliftFilm,_xlpm.widthActual>=900,_xlpm.rawResult<>""),_xlpm.rawResult*1.25,_xlpm.rawResult) ))} | AG35: 💰 Total Sell Price (€) | AH35: {=IFERROR(_xlfn.SWITCH(AH13,"By Imp",AH14*AH31,"IMP",AH14*AH31,"By Length",AH14*AH29,"By Weight",AH14*AH30,AG28*AH39),"")} | AI35: € total | AK35: 💰 Total Sell Price (€) | AL35: {=IFERROR(_xlfn.SWITCH(AL13,"By Imp",AL14*AL31,"IMP",AL14*AL31,"By Length",AL14*AL29,"By Weight",AL14*AL30,AK28*AL39),"")} | AM35: € total | AO35: 💰 Total Sell Price (€) | AP35: {=IFERROR(_xlfn.SWITCH(AP13,"By Imp",AP14*AP31,"IMP",AP14*AP31,"By Length",AP14*AP29,"By Weight",AP14*AP30,AO28*AP39),"")} | AQ35: € total
J36: =IF($C36="","",IF($E$15="","",IF(ISNUMBER($E$15),_xlfn.LET(_xlpm.cap,IF($Q$15="Quantum",760,1220),IF($E$15+50>_xlpm.cap,"ERROR: Lamination Width > "&_xlpm.cap,$E$15+50)),$E$15))) | N36: {=IF($C36="","",_xlfn.LET( _xlpm.mat,TRIM($C36), _xlpm.matKey,UPPER(SUBSTITUTE(_xlpm.mat," ","")), _xlpm.pr,IFERROR(LOOKUP(2,1/($H$3:H36<>""),$H$3:H36),""), _xlpm.widthActual,IFERROR(LOOKUP(2,1/($E$3:E36<>""),$E$3:E36),$E36), _xlpm.euShip,IFERROR([6]HELPER!$AH$3,0), _xlpm.metSetup,IFERROR([6]HELPER!$CH$2,0), _xlpm.filmNames,[6]!Table1[Film Type], _xlpm.filmCosts,[6]!Table1[Total Cost], _xlpm.printCosts,[6]!Table1[Printing], _xlpm.printWaste,[6]!Table1[Printing Waste], _xlpm.filmCost,IF(LEFT(_xlpm.mat,4)="TIPA",IFERROR(IF(_xlpm.pr="Not Printed",MIN(_xlfn._xlws.FILTER(_xlpm.filmCosts,(UPPER(SUBSTITUTE(_xlpm.filmNames," ",""))=_xlpm.matKey)*(_xlpm.printCosts=0)*(_xlpm.printWaste=0)*(_xlpm.filmCosts>0))),INDEX(_xlfn._xlws.FILTER(_xlpm.filmCosts,(UPPER(SUBSTITUTE(_xlpm.filmNames," ",""))=_xlpm.matKey)*(_xlpm.filmCosts>0)),1)),""),""), _xlpm.summaryNames,"", _xlpm.summaryThick,"", _xlpm.summaryCosts,"", _xlpm.summaryCost,IF(LEFT(_xlpm.mat,4)="TIPA",IFERROR(IF(_xlpm.pr="Not Printed",MIN(_xlfn._xlws.FILTER(_xlpm.summaryCosts,(UPPER(SUBSTITUTE(_xlpm.summaryNames," ",""))=_xlpm.matKey)*(_xlpm.summaryThick=$K36)*(_xlpm.summaryCosts>0))),INDEX(_xlfn._xlws.FILTER(_xlpm.summaryCosts,(UPPER(SUBSTITUTE(_xlpm.summaryNames," ",""))=_xlpm.matKey)*(_xlpm.summaryThick=$K36)*(_xlpm.summaryCosts>0)),1)),""),""), _xlpm.finalFilmCost,IF(_xlpm.filmCost<>"",_xlpm.filmCost,_xlpm.summaryCost), _xlpm.metFilmCost,IFERROR(INDEX(_xlpm.filmCosts,MATCH("TIPA 312 MFG",_xlpm.filmNames,0)),INDEX(_xlpm.filmCosts,1)), _xlpm.tipa312MfgCost,IFERROR(IF(_xlpm.pr="Not Printed",MIN(_xlfn._xlws.FILTER(_xlpm.filmCosts,(UPPER(SUBSTITUTE(_xlpm.filmNames," ",""))="TIPA312MFG")*(_xlpm.printCosts=0)*(_xlpm.printWaste=0)*(_xlpm.filmCosts>0))),INDEX(_xlfn._xlws.FILTER(_xlpm.filmCosts,(UPPER(SUBSTITUTE(_xlpm.filmNames," ",""))="TIPA312MFG")*(_xlpm.filmCosts>0)),1)),0), _xlpm.metluxCost,IFERROR(INDEX([6]HELPER!$E$2:$E$32,MATCH(TRUE,TRIM([6]HELPER!$A$2:$A$32)="MET LUX",0)),IFERROR(INDEX([6]HELPER!$E$2:$E$32,MATCH(TRUE,TRIM([6]HELPER!$B$2:$B$32)="MET LUX",0)),IFERROR(INDEX([6]HELPER!$E$2:$E$32,MATCH(TRUE,TRIM([6]HELPER!$C$2:$C$32)="MET LUX",0)),IFERROR(INDEX([6]HELPER!$E$2:$E$32,MATCH(TRUE,TRIM([6]HELPER!$D$2:$D$32)="MET LUX",0)),0)))), _xlpm.helperCost,IFERROR(INDEX([6]HELPER!$E$2:$E$32,MATCH(TRUE,TRIM([6]HELPER!$A$2:$A$32)=_xlpm.mat,0)),IFERROR(INDEX([6]HELPER!$E$2:$E$32,MATCH(TRUE,TRIM([6]HELPER!$B$2:$B$32)=_xlpm.mat,0)),IFERROR(INDEX([6]HELPER!$E$2:$E$32,MATCH(TRUE,TRIM([6]HELPER!$C$2:$C$32)=_xlpm.mat,0)),IFERROR(INDEX([6]HELPER!$E$2:$E$32,MATCH(TRUE,TRIM([6]HELPER!$D$2:$D$32)=_xlpm.mat,0)),"")))), _xlpm.specialCost,IFERROR(_xlfn.XLOOKUP(_xlpm.mat,[6]HELPER!$CK$2:$CK$105,[6]HELPER!$CO$2:$CO$105,""),""), _xlpm.nkHelperCost,IFERROR(INDEX([6]HELPER!$E$2:$E$32,MATCH(TRUE,TRIM([6]HELPER!$A$2:$A$32)="NK",0)),IFERROR(INDEX([6]HELPER!$E$2:$E$32,MATCH(TRUE,TRIM([6]HELPER!$B$2:$B$32)="NK",0)),IFERROR(INDEX([6]HELPER!$E$2:$E$32,MATCH(TRUE,TRIM([6]HELPER!$C$2:$C$32)="NK",0)),IFERROR(INDEX([6]HELPER!$E$2:$E$32,MATCH(TRUE,TRIM([6]HELPER!$D$2:$D$32)="NK",0)),0)))), _xlpm.baseCost,IF(LEFT(_xlpm.mat,4)="TIPA",IF(_xlpm.finalFilmCost<>"",_xlpm.finalFilmCost,_xlpm.specialCost),_xlpm.helperCost), _xlpm.rawResult,IF(OR(_xlpm.mat="NK",_xlpm.mat="NKR"),_xlpm.nkHelperCost,IF(_xlpm.baseCost="","",IF(OR(_xlpm.finalFilmCost<>"",LEFT(_xlpm.mat,4)="TIPA"),_xlpm.baseCost,_xlpm.baseCost+_xlpm.euShip))), _xlpm.upliftFilm,ISNUMBER(MATCH(_xlpm.matKey,{"TIPA312MET";"TIPA302FG";"TIPA302FGW";"TIPA306M";"TIPA306W";"TIPA312MFG";"TIPA312MFGW"},0)), IF(AND(_xlpm.upliftFilm,_xlpm.widthActual>=900,_xlpm.rawResult<>""),_xlpm.rawResult*1.25,_xlpm.rawResult) ))} | AG36: 💰 Total Sell Price ($) | AH36: {=IFERROR(_xlfn.SWITCH(AH13,"By Imp",AH14*AH34,"IMP",AH14*AH34,"By Length",AH14*AH32,"By Weight",AH14*AH33,AG28*AH39*1.16),"")} -> 20827.857 | AI36: $ total | AK36: 💰 Total Sell Price ($) | AL36: {=IFERROR(_xlfn.SWITCH(AL13,"By Imp",AL14*AL34,"IMP",AL14*AL34,"By Length",AL14*AL32,"By Weight",AL14*AL33,AK28*AL39*1.16),"")} -> 91670.294 | AM36: $ total | AO36: 💰 Total Sell Price ($) | AP36: {=IFERROR(_xlfn.SWITCH(AP13,"By Imp",AP14*AP34,"IMP",AP14*AP34,"By Length",AP14*AP32,"By Weight",AP14*AP33,AO28*AP39*1.16),"")} -> 175680.59 | AQ36: $ total
J37: =IF($C37="","",IF($E$15="","",IF(ISNUMBER($E$15),_xlfn.LET(_xlpm.cap,IF($Q$15="Quantum",760,1220),IF($E$15+50>_xlpm.cap,"ERROR: Lamination Width > "&_xlpm.cap,$E$15+50)),$E$15))) | N37: {=IF($C37="","",_xlfn.LET( _xlpm.mat,TRIM($C37), _xlpm.matKey,UPPER(SUBSTITUTE(_xlpm.mat," ","")), _xlpm.pr,IFERROR(LOOKUP(2,1/($H$3:H37<>""),$H$3:H37),""), _xlpm.widthActual,IFERROR(LOOKUP(2,1/($E$3:E37<>""),$E$3:E37),$E37), _xlpm.euShip,IFERROR([6]HELPER!$AH$3,0), _xlpm.metSetup,IFERROR([6]HELPER!$CH$2,0), _xlpm.filmNames,[6]!Table1[Film Type], _xlpm.filmCosts,[6]!Table1[Total Cost], _xlpm.printCosts,[6]!Table1[Printing], _xlpm.printWaste,[6]!Table1[Printing Waste], _xlpm.filmCost,IF(LEFT(_xlpm.mat,4)="TIPA",IFERROR(IF(_xlpm.pr="Not Printed",MIN(_xlfn._xlws.FILTER(_xlpm.filmCosts,(UPPER(SUBSTITUTE(_xlpm.filmNames," ",""))=_xlpm.matKey)*(_xlpm.printCosts=0)*(_xlpm.printWaste=0)*(_xlpm.filmCosts>0))),INDEX(_xlfn._xlws.FILTER(_xlpm.filmCosts,(UPPER(SUBSTITUTE(_xlpm.filmNames," ",""))=_xlpm.matKey)*(_xlpm.filmCosts>0)),1)),""),""), _xlpm.summaryNames,"", _xlpm.summaryThick,"", _xlpm.summaryCosts,"", _xlpm.summaryCost,IF(LEFT(_xlpm.mat,4)="TIPA",IFERROR(IF(_xlpm.pr="Not Printed",MIN(_xlfn._xlws.FILTER(_xlpm.summaryCosts,(UPPER(SUBSTITUTE(_xlpm.summaryNames," ",""))=_xlpm.matKey)*(_xlpm.summaryThick=$K37)*(_xlpm.summaryCosts>0))),INDEX(_xlfn._xlws.FILTER(_xlpm.summaryCosts,(UPPER(SUBSTITUTE(_xlpm.summaryNames," ",""))=_xlpm.matKey)*(_xlpm.summaryThick=$K37)*(_xlpm.summaryCosts>0)),1)),""),""), _xlpm.finalFilmCost,IF(_xlpm.filmCost<>"",_xlpm.filmCost,_xlpm.summaryCost), _xlpm.metFilmCost,IFERROR(INDEX(_xlpm.filmCosts,MATCH("TIPA 312 MFG",_xlpm.filmNames,0)),INDEX(_xlpm.filmCosts,1)), _xlpm.tipa312MfgCost,IFERROR(IF(_xlpm.pr="Not Printed",MIN(_xlfn._xlws.FILTER(_xlpm.filmCosts,(UPPER(SUBSTITUTE(_xlpm.filmNames," ",""))="TIPA312MFG")*(_xlpm.printCosts=0)*(_xlpm.printWaste=0)*(_xlpm.filmCosts>0))),INDEX(_xlfn._xlws.FILTER(_xlpm.filmCosts,(UPPER(SUBSTITUTE(_xlpm.filmNames," ",""))="TIPA312MFG")*(_xlpm.filmCosts>0)),1)),0), _xlpm.metluxCost,IFERROR(INDEX([6]HELPER!$E$2:$E$32,MATCH(TRUE,TRIM([6]HELPER!$A$2:$A$32)="MET LUX",0)),IFERROR(INDEX([6]HELPER!$E$2:$E$32,MATCH(TRUE,TRIM([6]HELPER!$B$2:$B$32)="MET LUX",0)),IFERROR(INDEX([6]HELPER!$E$2:$E$32,MATCH(TRUE,TRIM([6]HELPER!$C$2:$C$32)="MET LUX",0)),IFERROR(INDEX([6]HELPER!$E$2:$E$32,MATCH(TRUE,TRIM([6]HELPER!$D$2:$D$32)="MET LUX",0)),0)))), _xlpm.helperCost,IFERROR(INDEX([6]HELPER!$E$2:$E$32,MATCH(TRUE,TRIM([6]HELPER!$A$2:$A$32)=_xlpm.mat,0)),IFERROR(INDEX([6]HELPER!$E$2:$E$32,MATCH(TRUE,TRIM([6]HELPER!$B$2:$B$32)=_xlpm.mat,0)),IFERROR(INDEX([6]HELPER!$E$2:$E$32,MATCH(TRUE,TRIM([6]HELPER!$C$2:$C$32)=_xlpm.mat,0)),IFERROR(INDEX([6]HELPER!$E$2:$E$32,MATCH(TRUE,TRIM([6]HELPER!$D$2:$D$32)=_xlpm.mat,0)),"")))), _xlpm.specialCost,IFERROR(_xlfn.XLOOKUP(_xlpm.mat,[6]HELPER!$CK$2:$CK$105,[6]HELPER!$CO$2:$CO$105,""),""), _xlpm.nkHelperCost,IFERROR(INDEX([6]HELPER!$E$2:$E$32,MATCH(TRUE,TRIM([6]HELPER!$A$2:$A$32)="NK",0)),IFERROR(INDEX([6]HELPER!$E$2:$E$32,MATCH(TRUE,TRIM([6]HELPER!$B$2:$B$32)="NK",0)),IFERROR(INDEX([6]HELPER!$E$2:$E$32,MATCH(TRUE,TRIM([6]HELPER!$C$2:$C$32)="NK",0)),IFERROR(INDEX([6]HELPER!$E$2:$E$32,MATCH(TRUE,TRIM([6]HELPER!$D$2:$D$32)="NK",0)),0)))), _xlpm.baseCost,IF(LEFT(_xlpm.mat,4)="TIPA",IF(_xlpm.finalFilmCost<>"",_xlpm.finalFilmCost,_xlpm.specialCost),_xlpm.helperCost), _xlpm.rawResult,IF(OR(_xlpm.mat="NK",_xlpm.mat="NKR"),_xlpm.nkHelperCost,IF(_xlpm.baseCost="","",IF(OR(_xlpm.finalFilmCost<>"",LEFT(_xlpm.mat,4)="TIPA"),_xlpm.baseCost,_xlpm.baseCost+_xlpm.euShip))), _xlpm.upliftFilm,ISNUMBER(MATCH(_xlpm.matKey,{"TIPA312MET";"TIPA302FG";"TIPA302FGW";"TIPA306M";"TIPA306W";"TIPA312MFG";"TIPA312MFGW"},0)), IF(AND(_xlpm.upliftFilm,_xlpm.widthActual>=900,_xlpm.rawResult<>""),_xlpm.rawResult*1.25,_xlpm.rawResult) ))} | AG37: 📏 Meter MOQ | AH37: =IFERROR(AH38/($M$8*($D$3/$J$3))+5,"") -> 13846.888 | AI37: m | AK37: 📏 Meter MOQ | AL37: =IFERROR(AL38/($M$14*($D$9/$J$9))+5,"") -> 13846.888 | AM37: m | AO37: 📏 Meter MOQ | AP37: =IFERROR(AP38/($M$20*($D$15/$J$15))+5,"") -> 13846.888 | AQ37: m
J38: =IF($C38="","",IF($E$15="","",IF(ISNUMBER($E$15),_xlfn.LET(_xlpm.cap,IF($Q$15="Quantum",760,1220),IF($E$15+50>_xlpm.cap,"ERROR: Lamination Width > "&_xlpm.cap,$E$15+50)),$E$15))) | N38: {=IF($C38="","",_xlfn.LET( _xlpm.mat,TRIM($C38), _xlpm.matKey,UPPER(SUBSTITUTE(_xlpm.mat," ","")), _xlpm.pr,IFERROR(LOOKUP(2,1/($H$3:H38<>""),$H$3:H38),""), _xlpm.widthActual,IFERROR(LOOKUP(2,1/($E$3:E38<>""),$E$3:E38),$E38), _xlpm.euShip,IFERROR([6]HELPER!$AH$3,0), _xlpm.metSetup,IFERROR([6]HELPER!$CH$2,0), _xlpm.filmNames,[6]!Table1[Film Type], _xlpm.filmCosts,[6]!Table1[Total Cost], _xlpm.printCosts,[6]!Table1[Printing], _xlpm.printWaste,[6]!Table1[Printing Waste], _xlpm.filmCost,IF(LEFT(_xlpm.mat,4)="TIPA",IFERROR(IF(_xlpm.pr="Not Printed",MIN(_xlfn._xlws.FILTER(_xlpm.filmCosts,(UPPER(SUBSTITUTE(_xlpm.filmNames," ",""))=_xlpm.matKey)*(_xlpm.printCosts=0)*(_xlpm.printWaste=0)*(_xlpm.filmCosts>0))),INDEX(_xlfn._xlws.FILTER(_xlpm.filmCosts,(UPPER(SUBSTITUTE(_xlpm.filmNames," ",""))=_xlpm.matKey)*(_xlpm.filmCosts>0)),1)),""),""), _xlpm.summaryNames,"", _xlpm.summaryThick,"", _xlpm.summaryCosts,"", _xlpm.summaryCost,IF(LEFT(_xlpm.mat,4)="TIPA",IFERROR(IF(_xlpm.pr="Not Printed",MIN(_xlfn._xlws.FILTER(_xlpm.summaryCosts,(UPPER(SUBSTITUTE(_xlpm.summaryNames," ",""))=_xlpm.matKey)*(_xlpm.summaryThick=$K38)*(_xlpm.summaryCosts>0))),INDEX(_xlfn._xlws.FILTER(_xlpm.summaryCosts,(UPPER(SUBSTITUTE(_xlpm.summaryNames," ",""))=_xlpm.matKey)*(_xlpm.summaryThick=$K38)*(_xlpm.summaryCosts>0)),1)),""),""), _xlpm.finalFilmCost,IF(_xlpm.filmCost<>"",_xlpm.filmCost,_xlpm.summaryCost), _xlpm.metFilmCost,IFERROR(INDEX(_xlpm.filmCosts,MATCH("TIPA 312 MFG",_xlpm.filmNames,0)),INDEX(_xlpm.filmCosts,1)), _xlpm.tipa312MfgCost,IFERROR(IF(_xlpm.pr="Not Printed",MIN(_xlfn._xlws.FILTER(_xlpm.filmCosts,(UPPER(SUBSTITUTE(_xlpm.filmNames," ",""))="TIPA312MFG")*(_xlpm.printCosts=0)*(_xlpm.printWaste=0)*(_xlpm.filmCosts>0))),INDEX(_xlfn._xlws.FILTER(_xlpm.filmCosts,(UPPER(SUBSTITUTE(_xlpm.filmNames," ",""))="TIPA312MFG")*(_xlpm.filmCosts>0)),1)),0), _xlpm.metluxCost,IFERROR(INDEX([6]HELPER!$E$2:$E$32,MATCH(TRUE,TRIM([6]HELPER!$A$2:$A$32)="MET LUX",0)),IFERROR(INDEX([6]HELPER!$E$2:$E$32,MATCH(TRUE,TRIM([6]HELPER!$B$2:$B$32)="MET LUX",0)),IFERROR(INDEX([6]HELPER!$E$2:$E$32,MATCH(TRUE,TRIM([6]HELPER!$C$2:$C$32)="MET LUX",0)),IFERROR(INDEX([6]HELPER!$E$2:$E$32,MATCH(TRUE,TRIM([6]HELPER!$D$2:$D$32)="MET LUX",0)),0)))), _xlpm.helperCost,IFERROR(INDEX([6]HELPER!$E$2:$E$32,MATCH(TRUE,TRIM([6]HELPER!$A$2:$A$32)=_xlpm.mat,0)),IFERROR(INDEX([6]HELPER!$E$2:$E$32,MATCH(TRUE,TRIM([6]HELPER!$B$2:$B$32)=_xlpm.mat,0)),IFERROR(INDEX([6]HELPER!$E$2:$E$32,MATCH(TRUE,TRIM([6]HELPER!$C$2:$C$32)=_xlpm.mat,0)),IFERROR(INDEX([6]HELPER!$E$2:$E$32,MATCH(TRUE,TRIM([6]HELPER!$D$2:$D$32)=_xlpm.mat,0)),"")))), _xlpm.specialCost,IFERROR(_xlfn.XLOOKUP(_xlpm.mat,[6]HELPER!$CK$2:$CK$105,[6]HELPER!$CO$2:$CO$105,""),""), _xlpm.nkHelperCost,IFERROR(INDEX([6]HELPER!$E$2:$E$32,MATCH(TRUE,TRIM([6]HELPER!$A$2:$A$32)="NK",0)),IFERROR(INDEX([6]HELPER!$E$2:$E$32,MATCH(TRUE,TRIM([6]HELPER!$B$2:$B$32)="NK",0)),IFERROR(INDEX([6]HELPER!$E$2:$E$32,MATCH(TRUE,TRIM([6]HELPER!$C$2:$C$32)="NK",0)),IFERROR(INDEX([6]HELPER!$E$2:$E$32,MATCH(TRUE,TRIM([6]HELPER!$D$2:$D$32)="NK",0)),0)))), _xlpm.baseCost,IF(LEFT(_xlpm.mat,4)="TIPA",IF(_xlpm.finalFilmCost<>"",_xlpm.finalFilmCost,_xlpm.specialCost),_xlpm.helperCost), _xlpm.rawResult,IF(OR(_xlpm.mat="NK",_xlpm.mat="NKR"),_xlpm.nkHelperCost,IF(_xlpm.baseCost="","",IF(OR(_xlpm.finalFilmCost<>"",LEFT(_xlpm.mat,4)="TIPA"),_xlpm.baseCost,_xlpm.baseCost+_xlpm.euShip))), _xlpm.upliftFilm,ISNUMBER(MATCH(_xlpm.matKey,{"TIPA312MET";"TIPA302FG";"TIPA302FGW";"TIPA306M";"TIPA306W";"TIPA312MFG";"TIPA312MFGW"},0)), IF(AND(_xlpm.upliftFilm,_xlpm.widthActual>=900,_xlpm.rawResult<>""),_xlpm.rawResult*1.25,_xlpm.rawResult) ))} | T38: =IF(OR($S38="",$K38=""),"",IFERROR($S38*(1/$M$41)*($J38/($D38*MAX(1,ROUNDDOWN(760/$D38,0)))),"")) | AG38: ⚖️ KG MOQ | AH38: =_xlfn.LET(_xlpm.lam,UPPER(SUBSTITUTE(AH3&"","LAMINATE","")),IF(_xlpm.lam="608W",2000,IF(_xlpm.lam="608",750,500))) -> 500 | AI38: Kg | AK38: ⚖️ KG MOQ | AL38: =_xlfn.LET(_xlpm.lam,UPPER(SUBSTITUTE(AL3&"","LAMINATE","")),IF(_xlpm.lam="608W",2000,IF(_xlpm.lam="608",750,500))) -> 500 | AM38: Kg | AO38: ⚖️ KG MOQ | AP38: =_xlfn.LET(_xlpm.lam,UPPER(SUBSTITUTE(AP3&"","LAMINATE","")),IF(_xlpm.lam="608W",2000,IF(_xlpm.lam="608",750,500))) -> 500 | AQ38: Kg
J39: =IF($C39="","",IF($E$15="","",IF(ISNUMBER($E$15),_xlfn.LET(_xlpm.cap,IF($Q$15="Quantum",760,1220),IF($E$15+50>_xlpm.cap,"ERROR: Lamination Width > "&_xlpm.cap,$E$15+50)),$E$15))) | N39: {=IF($C39="","",_xlfn.LET( _xlpm.mat,TRIM($C39), _xlpm.matKey,UPPER(SUBSTITUTE(_xlpm.mat," ","")), _xlpm.pr,IFERROR(LOOKUP(2,1/($H$3:H39<>""),$H$3:H39),""), _xlpm.widthActual,IFERROR(LOOKUP(2,1/($E$3:E39<>""),$E$3:E39),$E39), _xlpm.euShip,IFERROR([6]HELPER!$AH$3,0), _xlpm.metSetup,IFERROR([6]HELPER!$CH$2,0), _xlpm.filmNames,[6]!Table1[Film Type], _xlpm.filmCosts,[6]!Table1[Total Cost], _xlpm.printCosts,[6]!Table1[Printing], _xlpm.printWaste,[6]!Table1[Printing Waste], _xlpm.filmCost,IF(LEFT(_xlpm.mat,4)="TIPA",IFERROR(IF(_xlpm.pr="Not Printed",MIN(_xlfn._xlws.FILTER(_xlpm.filmCosts,(UPPER(SUBSTITUTE(_xlpm.filmNames," ",""))=_xlpm.matKey)*(_xlpm.printCosts=0)*(_xlpm.printWaste=0)*(_xlpm.filmCosts>0))),INDEX(_xlfn._xlws.FILTER(_xlpm.filmCosts,(UPPER(SUBSTITUTE(_xlpm.filmNames," ",""))=_xlpm.matKey)*(_xlpm.filmCosts>0)),1)),""),""), _xlpm.summaryNames,"", _xlpm.summaryThick,"", _xlpm.summaryCosts,"", _xlpm.summaryCost,IF(LEFT(_xlpm.mat,4)="TIPA",IFERROR(IF(_xlpm.pr="Not Printed",MIN(_xlfn._xlws.FILTER(_xlpm.summaryCosts,(UPPER(SUBSTITUTE(_xlpm.summaryNames," ",""))=_xlpm.matKey)*(_xlpm.summaryThick=$K39)*(_xlpm.summaryCosts>0))),INDEX(_xlfn._xlws.FILTER(_xlpm.summaryCosts,(UPPER(SUBSTITUTE(_xlpm.summaryNames," ",""))=_xlpm.matKey)*(_xlpm.summaryThick=$K39)*(_xlpm.summaryCosts>0)),1)),""),""), _xlpm.finalFilmCost,IF(_xlpm.filmCost<>"",_xlpm.filmCost,_xlpm.summaryCost), _xlpm.metFilmCost,IFERROR(INDEX(_xlpm.filmCosts,MATCH("TIPA 312 MFG",_xlpm.filmNames,0)),INDEX(_xlpm.filmCosts,1)), _xlpm.tipa312MfgCost,IFERROR(IF(_xlpm.pr="Not Printed",MIN(_xlfn._xlws.FILTER(_xlpm.filmCosts,(UPPER(SUBSTITUTE(_xlpm.filmNames," ",""))="TIPA312MFG")*(_xlpm.printCosts=0)*(_xlpm.printWaste=0)*(_xlpm.filmCosts>0))),INDEX(_xlfn._xlws.FILTER(_xlpm.filmCosts,(UPPER(SUBSTITUTE(_xlpm.filmNames," ",""))="TIPA312MFG")*(_xlpm.filmCosts>0)),1)),0), _xlpm.metluxCost,IFERROR(INDEX([6]HELPER!$E$2:$E$32,MATCH(TRUE,TRIM([6]HELPER!$A$2:$A$32)="MET LUX",0)),IFERROR(INDEX([6]HELPER!$E$2:$E$32,MATCH(TRUE,TRIM([6]HELPER!$B$2:$B$32)="MET LUX",0)),IFERROR(INDEX([6]HELPER!$E$2:$E$32,MATCH(TRUE,TRIM([6]HELPER!$C$2:$C$32)="MET LUX",0)),IFERROR(INDEX([6]HELPER!$E$2:$E$32,MATCH(TRUE,TRIM([6]HELPER!$D$2:$D$32)="MET LUX",0)),0)))), _xlpm.helperCost,IFERROR(INDEX([6]HELPER!$E$2:$E$32,MATCH(TRUE,TRIM([6]HELPER!$A$2:$A$32)=_xlpm.mat,0)),IFERROR(INDEX([6]HELPER!$E$2:$E$32,MATCH(TRUE,TRIM([6]HELPER!$B$2:$B$32)=_xlpm.mat,0)),IFERROR(INDEX([6]HELPER!$E$2:$E$32,MATCH(TRUE,TRIM([6]HELPER!$C$2:$C$32)=_xlpm.mat,0)),IFERROR(INDEX([6]HELPER!$E$2:$E$32,MATCH(TRUE,TRIM([6]HELPER!$D$2:$D$32)=_xlpm.mat,0)),"")))), _xlpm.specialCost,IFERROR(_xlfn.XLOOKUP(_xlpm.mat,[6]HELPER!$CK$2:$CK$105,[6]HELPER!$CO$2:$CO$105,""),""), _xlpm.nkHelperCost,IFERROR(INDEX([6]HELPER!$E$2:$E$32,MATCH(TRUE,TRIM([6]HELPER!$A$2:$A$32)="NK",0)),IFERROR(INDEX([6]HELPER!$E$2:$E$32,MATCH(TRUE,TRIM([6]HELPER!$B$2:$B$32)="NK",0)),IFERROR(INDEX([6]HELPER!$E$2:$E$32,MATCH(TRUE,TRIM([6]HELPER!$C$2:$C$32)="NK",0)),IFERROR(INDEX([6]HELPER!$E$2:$E$32,MATCH(TRUE,TRIM([6]HELPER!$D$2:$D$32)="NK",0)),0)))), _xlpm.baseCost,IF(LEFT(_xlpm.mat,4)="TIPA",IF(_xlpm.finalFilmCost<>"",_xlpm.finalFilmCost,_xlpm.specialCost),_xlpm.helperCost), _xlpm.rawResult,IF(OR(_xlpm.mat="NK",_xlpm.mat="NKR"),_xlpm.nkHelperCost,IF(_xlpm.baseCost="","",IF(OR(_xlpm.finalFilmCost<>"",LEFT(_xlpm.mat,4)="TIPA"),_xlpm.baseCost,_xlpm.baseCost+_xlpm.euShip))), _xlpm.upliftFilm,ISNUMBER(MATCH(_xlpm.matKey,{"TIPA312MET";"TIPA302FG";"TIPA302FGW";"TIPA306M";"TIPA306W";"TIPA312MFG";"TIPA312MFGW"},0)), IF(AND(_xlpm.upliftFilm,_xlpm.widthActual>=900,_xlpm.rawResult<>""),_xlpm.rawResult*1.25,_xlpm.rawResult) ))} | AG39: ⚖️ Total KG | AH39: =IF(OR(AH13="IMP",AH13="By Imp"),IFERROR(AH16*$M$8*($D$3/$J$3)+5,""),IF(AH13="By Length",IFERROR(AH14*$M$8*($D$3/$J$3)+5,""),IF(AH13="By Weight",IFERROR(IF(AH6<>"",AH6,A3),""),""))) -> 508.51513 | AI39: Kg | AK39: ⚖️ Total KG | AL39: =IF(OR(AL13="IMP",AL13="By Imp"),IFERROR(AL16*$M$14*($D$9/$J$9)+5,""),IF(AL13="By Length",IFERROR(AL14*$M$14*($D$9/$J$9)+5,""),IF(AL13="By Weight",IFERROR(IF(AL6<>"",AL6,A9),""),""))) -> 2522.5756 | AM39: Kg | AO39: ⚖️ Total KG | AP39: =IF(OR(AP13="IMP",AP13="By Imp"),IFERROR(AP16*$M$20*($D$15/$J$15)+5,""),IF(AP13="By Length",IFERROR(AP14*$M$20*($D$15/$J$15)+5,""),IF(AP13="By Weight",IFERROR(IF(AP6<>"",AP6,A15),""),""))) -> 5040.1513 | AQ39: Kg
